Workbook
Name ___a65537: [1]BLSHEET06!#REF!
Name ___a65537: [1]BLSHEET06!#REF!
Name ___a65537: [1]BLSHEET06!#REF!
Name ___a65537: [1]BLSHEET06!#REF!
Name ___a65537: [1]BLSHEET06!#REF!
Name ___a65537: [1]BLSHEET06!#REF!
Name ___a65537: [1]BLSHEET06!#REF!
Name ___a65537: [1]BLSHEET06!#REF!
Name ___a65537: [1]BLSHEET06!#REF!
Name ___a65537: [1]BLSHEET06!#REF!
Name __a65537: [1]BLSHEET06!#REF!
Name __a65537: [1]BLSHEET06!#REF!
Name __a65537: [1]BLSHEET06!#REF!
Name __a65537: [1]BLSHEET06!#REF!
Name __a65537: [1]BLSHEET06!#REF!
Name __a65537: [1]BLSHEET06!#REF!
Name __a65537: [1]BLSHEET06!#REF!
Name __a65537: [1]BLSHEET06!#REF!
Name __a65537: [1]BLSHEET06!#REF!
Name __a65537: [1]BLSHEET06!#REF!
Name __jj102: #REF!
Name _a65537: [1]BLSHEET06!#REF!
Name _a65537: [1]BLSHEET06!#REF!
Name _a65537: [1]BLSHEET06!#REF!
Name _a65537: [1]BLSHEET06!#REF!
Name _a65537: [1]BLSHEET06!#REF!
Name _a65537: [1]BLSHEET06!#REF!
Name _a65537: [1]BLSHEET06!#REF!
Name _a65537: [1]BLSHEET06!#REF!
Name _a65537: [1]BLSHEET06!#REF!
Name _a65537: [1]BLSHEET06!#REF!
Name _a65537: [1]BLSHEET06!#REF!
Name _jj102: #REF!
Name A: [2]BLSHEET06!#REF!
Name A: [2]BLSHEET06!#REF!
Name A: [2]BLSHEET06!#REF!
Name A: [2]BLSHEET06!#REF!
Name A: [2]BLSHEET06!#REF!
Name A: [2]BLSHEET06!#REF!
Name A: [2]BLSHEET06!#REF!
Name A: [2]BLSHEET06!#REF!
Name A: [2]BLSHEET06!#REF!
Name A: [2]BLSHEET06!#REF!
Name A: [2]BLSHEET06!#REF!
Name a17J554: [3]Sheet4!#REF!
Name a17J554: [3]Sheet4!#REF!
Name a17J554: [3]Sheet4!#REF!
Name a17J554: [3]Sheet4!#REF!
Name a17J554: [3]Sheet4!#REF!
Name a17J554: [3]Sheet4!#REF!
Name a17J554: [3]Sheet4!#REF!
Name a17J554: [3]Sheet4!#REF!
Name a17J554: [3]Sheet4!#REF!
Name a17J554: [3]Sheet4!#REF!
Name abc: [1]BLSHEET06!#REF!
Name abc: [1]BLSHEET06!#REF!
Name abc: [1]BLSHEET06!#REF!
Name abc: [1]BLSHEET06!#REF!
Name abc: [1]BLSHEET06!#REF!
Name abc: [1]BLSHEET06!#REF!

Sheet Req_PNB
C1: FINANCIAL ANALYSIS :
I2: (Rs. In Lacs)
D3: 2014-15 | E3: 2015-16 | F3: 2016-17 | G3: 2017-18 | H3: 2018-19 | I3: 2019-20 | J3: 2020-21 | K3: 2021-22 | L3: 2022-23
D4: (Projected)
C5: Gross turnover
C6: - Domestic | D6: ='P L '!D29-D10 -> 1961.7343 | E6: ='P L '!E29-E10 -> 1961.7343 | F6: ='P L '!F29-F10 -> 2206.9511 | G6: ='P L '!G29-G10 -> 2452.1678 | H6: ='P L '!H29-H10 -> 2697.3846 | I6: ='P L '!I29-I10 -> 2942.6014 | J6: ='P L '!J29-J10 -> 3187.8182 | K6: ='P L '!K29-K10 -> 3433.035 | L6: ='P L '!L29-L10 -> 2942.6014
C7: - Export
C8: % growth * | E8: =(E6-D6)/D6*100 -> 0 | F8: =(F6-E6)/E6*100 -> 12.5 | G8: =(G6-F6)/F6*100 -> 11.111111 | H8: =(H6-G6)/G6*100 -> 10 | I8: =(I6-H6)/H6*100 -> 9.0909091 | J8: =(J6-I6)/I6*100 -> 8.3333333 | K8: =(K6-J6)/J6*100 -> 7.6923077 | L8: =(L6-K6)/K6*100 -> -14.285714
C9: Net sales (net of excise duty etc.) | D9: =D6 -> 1961.7343 | E9: =E6 -> 1961.7343 | F9: =F6 -> 2206.9511 | G9: =G6 -> 2452.1678 | H9: =H6 -> 2697.3846 | I9: =I6 -> 2942.6014 | J9: =J6 -> 3187.8182 | K9: =K6 -> 3433.035 | L9: =L6 -> 2942.6014
C10: Other income | D10: ='P L '!D28 -> 50.300879 | E10: ='P L '!E28 -> 50.300879 | F10: ='P L '!F28 -> 56.588489 | G10: ='P L '!G28 -> 62.876099 | H10: ='P L '!H28 -> 69.163708 | I10: ='P L '!I28 -> 75.451318 | J10: ='P L '!J28 -> 81.738928 | K10: ='P L '!K28 -> 88.026538 | L10: ='P L '!L28 -> 75.451318
C11: Operating profit/ loss* | D11: =#REF! -> #REF! | E11: =#REF! -> #REF! | F11: =#REF! -> #REF! | G11: =#REF! -> #REF! | H11: =#REF! -> #REF! | I11: =#REF! -> #REF! | J11: =#REF! -> #REF! | K11: =#REF! -> #REF! | L11: =#REF! -> #REF!
C12: Profit before tax | D12: =#REF! -> #REF! | E12: =#REF! -> #REF! | F12: =#REF! -> #REF! | G12: =#REF! -> #REF! | H12: =#REF! -> #REF! | I12: =#REF! -> #REF! | J12: =#REF! -> #REF! | K12: =#REF! -> #REF! | L12: =#REF! -> #REF!
C13: Profit after tax | D13: =#REF! -> #REF! | E13: =#REF! -> #REF! | F13: =#REF! -> #REF! | G13: =#REF! -> #REF! | H13: =#REF! -> #REF! | I13: =#REF! -> #REF! | J13: =#REF! -> #REF! | K13: =#REF! -> #REF! | L13: =#REF! -> #REF!
C14: Depreciation | D14: =#REF! -> #REF! | E14: =#REF! -> #REF! | F14: =#REF! -> #REF! | G14: =#REF! -> #REF! | H14: =#REF! -> #REF! | I14: =#REF! -> #REF! | J14: =#REF! -> #REF! | K14: =#REF! -> #REF! | L14: =#REF! -> #REF!
C15: Cash profit/ (loss) * | D15: =D13+D14 -> #REF! | E15: =E13+E14 -> #REF! | F15: =F13+F14 -> #REF! | G15: =G13+G14 -> #REF! | H15: =H13+H14 -> #REF! | I15: =I13+I14 -> #REF! | J15: =J13+J14 -> #REF! | K15: =K13+K14 -> #REF! | L15: =L13+L14 -> #REF!
C16: EBIDTA/PBIDTA | D16: =#REF!+#REF!+#REF!+#REF!+#REF! -> #REF! | E16: =#REF!+#REF!+#REF!+#REF!+#REF! -> #REF! | F16: =#REF!+#REF!+#REF!+#REF!+#REF! -> #REF! | G16: =#REF!+#REF!+#REF!+#REF!+#REF! -> #REF! | H16: =#REF!+#REF!+#REF!+#REF!+#REF! -> #REF! | I16: =#REF!+#REF!+#REF!+#REF!+#REF! -> #REF! | J16: =#REF!+#REF!+#REF!+#REF!+#REF! -> #REF! | K16: =#REF!+#REF!+#REF!+#REF!+#REF! -> #REF! | L16: =#REF!+#REF!+#REF!+#REF!+#REF! -> #REF!
C17: Paid up capital | D17: =#REF! -> #REF! | E17: =#REF! -> #REF! | F17: =#REF! -> #REF! | G17: =#REF! -> #REF! | H17: =#REF! -> #REF! | I17: =#REF! -> #REF! | J17: =#REF! -> #REF! | K17: =#REF! -> #REF! | L17: =#REF! -> #REF!
C18: Unsecured loan (quasi capital) | D18: =#REF! -> #REF! | E18: =#REF! -> #REF! | F18: =#REF! -> #REF! | G18: =#REF! -> #REF! | H18: =#REF! -> #REF! | I18: =#REF! -> #REF! | J18: =#REF! -> #REF! | K18: =#REF! -> #REF! | L18: =#REF! -> #REF!
C19: Reserves and surplus excluding revaluation reserves | D19: =#REF! -> #REF! | E19: =#REF! -> #REF! | F19: =#REF! -> #REF! | G19: =#REF! -> #REF! | H19: =#REF! -> #REF! | I19: =#REF! -> #REF! | J19: =#REF! -> #REF! | K19: =#REF! -> #REF! | L19: =#REF! -> #REF!
C20: Misc. expenditure not written off | D20: 0 | E20: 0 | F20: 0 | G20: 0 | H20: 0 | I20: 0 | J20: 0 | K20: 0 | L20: 0
C21: Accumulated losses * | D21: 0 | E21: 0 | F21: 0 | G21: 0 | H21: 0 | I21: 0 | J21: 0 | K21: 0 | L21: 0
C22: Deferred tax liability/ asset | D22: 0 | E22: 0 | F22: 0 | G22: 0 | H22: 0 | I22: 0 | J22: 0 | K22: 0 | L22: 0
C23: a) Tangible Net Worth | D23: =#REF! -> #REF! | E23: =#REF! -> #REF! | F23: =#REF! -> #REF! | G23: =#REF! -> #REF! | H23: =#REF! -> #REF! | I23: =#REF! -> #REF! | J23: =#REF! -> #REF! | K23: =#REF! -> #REF! | L23: =#REF! -> #REF! | N23: =D23-D17-D19 -> #REF! | O23: =E23-E17-E19 -> #REF! | P23: =F23-F17-F19 -> #REF! | Q23: =G23-G17-G19 -> #REF! | R23: =H23-H17-H19 -> #REF! | S23: =I23-I17-I19 -> #REF! | T23: =J23-J17-J19 -> #REF! | U23: =K23-K17-K19 -> #REF! | V23: =L23-L17-L19 -> #REF!
C24: b) Investment in allied concerns and amount of cross holdings | D24: 0 | E24: 0 | F24: 0 | G24: 0 | H24: 0 | I24: 0 | J24: 0 | K24: 0 | L24: 0
C25: c) Net owned funds/Adjusted TNW 9a-b)* | D25: =D23-D24 -> #REF! | E25: =E23-E24 -> #REF! | F25: =F23-F24 -> #REF! | G25: =G23-G24 -> #REF! | H25: =H23-H24 -> #REF! | I25: =I23-I24 -> #REF! | J25: =J23-J24 -> #REF! | K25: =K23-K24 -> #REF! | L25: =L23-L24 -> #REF!
C26: Share application money | D26: 0 | E26: 0 | F26: 0 | G26: 0 | H26: 0 | I26: 0 | J26: 0 | K26: 0 | L26: 0
C27: Total Borrowings | D27: ='B S '!E28+'B S '!E29+'B S '!E30 -> 2830 | E27: ='B S '!F28+'B S '!F29+'B S '!F30 -> 2530 | F27: ='B S '!G28+'B S '!G29+'B S '!G30 -> 2170 | G27: ='B S '!H28+'B S '!H29+'B S '!H30 -> 1690 | H27: ='B S '!I28+'B S '!I29+'B S '!I30 -> 1070 | I27: ='B S '!J28+'B S '!J29+'B S '!J30 -> 406 | J27: ='B S '!K28+'B S '!K29+'B S '!K30 -> 354.8 | K27: ='B S '!L28+'B S '!L29+'B S '!L30 -> 163.84 | L27: ='B S '!M28+'B S '!M29+'B S '!M30 -> 131.072
C28: Secured | D28: ='B S '!E28+'B S '!E30 -> 2430 | E28: ='B S '!F28+'B S '!F30 -> 2130 | F28: ='B S '!G28+'B S '!G30 -> 1770 | G28: ='B S '!H28+'B S '!H30 -> 1290 | H28: ='B S '!I28+'B S '!I30 -> 750 | I28: ='B S '!J28+'B S '!J30 -> 150 | J28: ='B S '!K28+'B S '!K30 -> 150 | K28: ='B S '!L28+'B S '!L30 -> 0 | L28: ='B S '!M28+'B S '!M30 -> 0
C29: Unsecured | D29: ='B S '!E29 -> 400 | E29: ='B S '!F29 -> 400 | F29: ='B S '!G29 -> 400 | G29: ='B S '!H29 -> 400 | H29: ='B S '!I29 -> 320 | I29: ='B S '!J29 -> 256 | J29: ='B S '!K29 -> 204.8 | K29: ='B S '!L29 -> 163.84 | L29: ='B S '!M29 -> 131.072
C30: Other investments (excluding investment in allied concerns considered for arriving at net owned funds) | D30: 0 | E30: 0 | F30: 0 | G30: 0 | H30: 0 | I30: 0 | J30: 0 | K30: 0 | L30: 0
C31: Total Assets | D31: =#REF! -> #REF! | E31: =#REF! -> #REF! | F31: =#REF! -> #REF! | G31: =#REF! -> #REF! | H31: =#REF! -> #REF! | I31: =#REF! -> #REF! | J31: =#REF! -> #REF! | K31: =#REF! -> #REF! | L31: =[13]CMA!M192 -> 2230.0314
C32: - Current assets | D32: =#REF! -> #REF! | E32: =#REF! -> #REF! | F32: =#REF! -> #REF! | G32: =#REF! -> #REF! | H32: =#REF! -> #REF! | I32: =#REF! -> #REF! | J32: =#REF! -> #REF! | K32: =#REF! -> #REF! | L32: =[13]CMA!M166 -> 463.14585
C33: - Non-current assets | D33: =#REF! -> #REF! | E33: =#REF! -> #REF! | F33: =#REF! -> #REF! | G33: =#REF! -> #REF! | H33: =#REF! -> #REF! | I33: =#REF! -> #REF! | J33: =#REF! -> #REF! | K33: =#REF! -> #REF! | L33: =[13]CMA!M188 -> 535
C34: Out of which net fixed assets | D34: =#REF! -> #REF! | E34: =#REF! -> #REF! | F34: =#REF! -> #REF! | G34: =#REF! -> #REF! | H34: =#REF! -> #REF! | I34: =#REF! -> #REF! | J34: =#REF! -> #REF! | K34: =#REF! -> #REF! | L34: =[13]CMA!M178 -> 1231.8855
C35: Net working capital * | D35: =#REF! -> #REF! | E35: =#REF! -> #REF! | F35: =#REF! -> #REF! | G35: =#REF! -> #REF! | H35: =#REF! -> #REF! | I35: =#REF! -> #REF! | J35: =#REF! -> #REF! | K35: =#REF! -> #REF! | L35: =[13]CMA!M205 -> 426.58878
C36: Current ratio | D36: =#REF! -> #REF! | E36: =#REF! -> #REF! | F36: =#REF! -> #REF! | G36: =#REF! -> #REF! | H36: =#REF! -> #REF! | I36: =#REF! -> #REF! | J36: =#REF! -> #REF! | K36: =#REF! -> #REF! | L36: =[13]CMA!M203 -> 12.669117
C37: Debt equity ratio | D37: =#REF! -> #REF! | E37: =#REF! -> #REF! | F37: =#REF! -> #REF! | G37: =#REF! -> #REF! | H37: =#REF! -> #REF! | I37: =#REF! -> #REF! | J37: =#REF! -> #REF! | K37: =#REF! -> #REF! | L37: =[13]CMA!M204 -> 0.24341418
C38: Term liability/ Adjusted TNW | D38: =D28/D25 -> #REF! | E38: =E28/E25 -> #REF! | F38: =F28/F25 -> #REF! | G38: =G28/G25 -> #REF! | H38: =H28/H25 -> #REF! | I38: =I28/I25 -> #REF! | J38: =J28/J25 -> #REF! | K38: =K28/K25 -> #REF! | L38: =L27/L25 -> #REF!
C39: TOL/ adjusted TNW | D39: =#REF! -> #REF! | E39: =#REF! -> #REF! | F39: =#REF! -> #REF! | G39: =#REF! -> #REF! | H39: =#REF! -> #REF! | I39: =#REF! -> #REF! | J39: =#REF! -> #REF! | K39: =#REF! -> #REF! | L39: =[13]CMA!M390 -> 0.19902539
C40: Operating profit/ sales | D40: =D11/D9 -> #REF! | E40: =E11/E9 -> #REF! | F40: =F11/F9 -> #REF! | G40: =G11/G9 -> #REF! | H40: =H11/H9 -> #REF! | I40: =I11/I9 -> #REF! | J40: =J11/J9 -> #REF! | K40: =K11/K9 -> #REF! | L40: =L11/L9 -> #REF!
C41: Long term sources | D41: =#REF! -> #REF! | E41: =#REF! -> #REF! | F41: =#REF! -> #REF! | G41: =#REF! -> #REF! | H41: =#REF! -> #REF! | I41: =#REF! -> #REF! | J41: =#REF! -> #REF! | K41: =#REF! -> #REF! | L41: =[13]CMA!M306 -> 299.06612
C42: Long term uses | D42: =#REF! -> #REF! | E42: =#REF! -> #REF! | F42: =#REF! -> #REF! | G42: =#REF! -> #REF! | H42: =#REF! -> #REF! | I42: =#REF! -> #REF! | J42: =#REF! -> #REF! | K42: =#REF! -> #REF! | L42: =[13]CMA!M307 -> 200
C43: Surplus/ Deficit | D43: =D41-D42 -> #REF! | E43: =E41-E42 -> #REF! | F43: =F41-F42 -> #REF! | G43: =G41-G42 -> #REF! | H43: =H41-H42 -> #REF! | I43: =I41-I42 -> #REF! | J43: =J41-J42 -> #REF! | K43: =K41-K42 -> #REF! | L43: =L41-L42 -> 99.06612
C44: Short Term Sources | D44: =#REF! -> #REF! | E44: =#REF! -> #REF! | F44: =#REF! -> #REF! | G44: =#REF! -> #REF! | H44: =#REF! -> #REF! | I44: =#REF! -> #REF! | J44: =#REF! -> #REF! | K44: =#REF! -> #REF! | L44: =[13]CMA!M311 -> 0
C45: Short Term Uses | D45: =#REF! -> #REF! | E45: =#REF! -> #REF! | F45: =#REF! -> #REF! | G45: =#REF! -> #REF! | H45: =#REF! -> #REF! | I45: =#REF! -> #REF! | J45: =#REF! -> #REF! | K45: =#REF! -> #REF! | L45: =[13]CMA!M312 -> 99.06612
C46: Surplus/ Deficit ** | D46: =D44-D45 -> #REF! | E46: =E44-E45 -> #REF! | F46: =F44-F45 -> #REF! | G46: =G44-G45 -> #REF! | H46: =H44-H45 -> #REF! | I46: =I44-I45 -> #REF! | J46: =J44-J45 -> #REF! | K46: =K44-K45 -> #REF! | L46: =L44-L45 -> -99.06612
D48: =D43+D46 -> #REF! | E48: =E43+E46 -> #REF! | F48: =F43+F46 -> #REF! | G48: =G43+G46 -> #REF! | H48: =H43+H46 -> #REF! | I48: =I43+I46 -> #REF! | J48: =J43+J46 -> #REF! | K48: =K43+K46 -> #REF! | L48: =L43+L46 -> -3.126388e-13
C51: AMOUNT OF LOAN REQUIRED:
C53: TERM LOAN: | E53: Rs. | F53: ='CAPITAL COST'!D50 -> 2700 | G53: Lacs
C55: CASH CREDIT: | E55: Rs. | F55: 0 | G55: Lacs
C59: Detailed Sensitivity Analysis:
C61: Scenario I – Normal Scenario
D62: =D3 -> 2014-15 | E62: =E3 -> 2015-16 | F62: =F3 -> 2016-17 | G62: =G3 -> 2017-18 | H62: =H3 -> 2018-19 | I62: =I3 -> 2019-20 | J62: =J3 -> 2020-21 | K62: =K3 -> 2021-22 | L62: =L3 -> 2022-23
C63: 1. PBT | D63: =#REF! -> #REF! | E63: =#REF! -> #REF! | F63: =#REF! -> #REF! | G63: =#REF! -> #REF! | H63: =#REF! -> #REF! | I63: =#REF! -> #REF! | J63: =#REF! -> #REF! | K63: =#REF! -> #REF! | L63: =#REF! -> #REF!
C64: 2. Cash Profit | D64: =D15 -> #REF! | E64: =E15 -> #REF! | F64: =F15 -> #REF! | G64: =G15 -> #REF! | H64: =H15 -> #REF! | I64: =I15 -> #REF! | J64: =J15 -> #REF! | K64: =K15 -> #REF! | L64: =L15 -> #REF!
C65: Average DSCR | D65: =#REF! -> #REF!
C66: IRR | D66: =#REF! -> #REF!
C69: Scenario II - By drop in capacity utilization by 10%
D70: =D62 -> 2014-15 | E70: =E62 -> 2015-16 | F70: =F62 -> 2016-17 | G70: =G62 -> 2017-18 | H70: =H62 -> 2018-19 | I70: =I62 -> 2019-20 | J70: =J62 -> 2020-21 | K70: =K62 -> 2021-22 | L70: =L62 -> 2022-23
C71: 1. PBT | D71: ='P L _Case_II'!D55 -> 173.26791 | E71: ='P L _Case_II'!E55 -> 259.13865 | F71: ='P L _Case_II'!F55 -> 363.52877 | G71: ='P L _Case_II'!G55 -> 443.49834 | H71: ='P L _Case_II'!H55 -> 601.81445 | I71: ='P L _Case_II'!I55 -> 588.88067 | J71: ='P L _Case_II'!J55 -> 606.32652 | K71: ='P L _Case_II'!K55 -> 587.36813 | L71: ='P L _Case_II'!L55 -> 573.09374
C72: 2. Cash Profit | D72: =D71+'P L _Case_II'!D49 -> 625.46197 | E72: =E71+'P L _Case_II'!E49 -> 711.33271 | F72: =F71+'P L _Case_II'!F49 -> 815.72283 | G72: =G71+'P L _Case_II'!G49 -> 895.6924 | H72: =H71+'P L _Case_II'!H49 -> 1054.0085 | I72: =I71+'P L _Case_II'!I49 -> 1041.0747 | J72: =J71+'P L _Case_II'!J49 -> 1058.5206 | K72: =K71+'P L _Case_II'!K49 -> 1039.5622 | L72: =L71+'P L _Case_II'!L49 -> 1025.2878
C73: Average DSCR | D73: ='P L _Case_II'!D71 -> #REF!
C74: IRR | D74: =IRR_CASE_II!E33 -> 0.1304865
C76: Scenario III - By drop in receipts by 5%
D77: =D70 -> 2014-15 | E77: =E70 -> 2015-16 | F77: =F70 -> 2016-17 | G77: =G70 -> 2017-18 | H77: =H70 -> 2018-19 | I77: =I70 -> 2019-20 | J77: =J70 -> 2020-21 | K77: =K70 -> 2021-22 | L77: =L70 -> 2022-23
C78: 1. PBT | D78: ='P L _Case_III'!D55 -> 374.30812 | E78: ='P L _Case_III'!E55 -> 427.41975 | F78: ='P L _Case_III'!F55 -> 503.94956 | G78: ='P L _Case_III'!G55 -> 557.25253 | H78: ='P L _Case_III'!H55 -> 698.73358 | I78: ='P L _Case_III'!I55 -> 672.6074 | J78: ='P L _Case_III'!J55 -> 684.52012 | K78: ='P L _Case_III'!K55 -> 660.0286 | L78: ='P L _Case_III'!L55 -> 641.20474
C79: 2. Cash Profit | D79: =D78+'P L _Case_III'!D49 -> 826.50218 | E79: =E78+'P L _Case_III'!E49 -> 879.61381 | F79: =F78+'P L _Case_III'!F49 -> 956.14362 | G79: =G78+'P L _Case_III'!G49 -> 1009.4466 | H79: =H78+'P L _Case_III'!H49 -> 1150.9276 | I79: =I78+'P L _Case_III'!I49 -> 1124.8015 | J79: =J78+'P L _Case_III'!J49 -> 1136.7142 | K79: =K78+'P L _Case_III'!K49 -> 1112.2227 | L79: =L78+'P L _Case_III'!L49 -> 1093.3988
C80: Average DSCR | D80: ='P L _Case_III'!D71 -> #REF!
C81: IRR | D81: =IRR_CASE_III!E33 -> 0.150178
C83: Scenario IV - By drop in receipts by 10%
D84: =D77 -> 2014-15 | E84: =E77 -> 2015-16 | F84: =F77 -> 2016-17 | G84: =G77 -> 2017-18 | H84: =H77 -> 2018-19 | I84: =I77 -> 2019-20 | J84: =J77 -> 2020-21 | K84: =K77 -> 2021-22 | L84: =L77 -> 2022-23
C85: 1. PBT | D85: ='P L _Case_IV'!D55 -> 275.94136 | E85: ='P L _Case_IV'!E55 -> 316.75715 | F85: ='P L _Case_IV'!F55 -> 380.99112 | G85: ='P L _Case_IV'!G55 -> 421.99824 | H85: ='P L _Case_IV'!H55 -> 551.18344 | I85: ='P L _Case_IV'!I55 -> 525.05726 | J85: ='P L _Case_IV'!J55 -> 536.96998 | K85: ='P L _Case_IV'!K55 -> 512.47846 | L85: ='P L _Case_IV'!L55 -> 493.6546
C86: 2. Cash Profit | D86: =D85+'P L _Case_IV'!D49 -> 728.13542 | E86: =E85+'P L _Case_IV'!E49 -> 768.95121 | F86: =F85+'P L _Case_IV'!F49 -> 833.18518 | G86: =G85+'P L _Case_IV'!G49 -> 874.1923 | H86: =H85+'P L _Case_IV'!H49 -> 1003.3775 | I86: =I85+'P L _Case_IV'!I49 -> 977.25132 | J86: =J85+'P L _Case_IV'!J49 -> 989.16404 | K86: =K85+'P L _Case_IV'!K49 -> 964.67252 | L86: =L85+'P L _Case_IV'!L49 -> 945.84866
C87: Average DSCR | D87: ='P L _Case_IV'!D71 -> #REF!
C88: IRR | D88: =IRR_CASE_IV!E33 -> 0.12266
C91: Scenario | D91: Average DSCR | E91: IRR | F91: BEP% | G91: Cash BEP%
C92: Base case | D92: =D65 -> #REF! | E92: =D66 -> #REF! | F92: =#REF! -> #REF! | G92: =#REF! -> #REF!
C93: 10% decrease in capacity utilization | D93: =D73 -> #REF! | E93: =D74 -> 0.1304865 | F93: ='BEP ANAYSIS_II'!E27 -> #REF! | G93: ='BEP ANAYSIS_II'!E29 -> #REF!
C94: 10% decrease in gross rentals | D94: =D87 -> #REF! | E94: =D88 -> 0.12266 | F94: ='BEP ANAYSIS_IV'!E27 -> #REF! | G94: ='BEP ANAYSIS_IV'!E29 -> #REF!
B99: Brief explanation for each major individual item of cost of Project:
C101: Break-up of each item numbered below:
B103: Sl.No. | C103: Items | E103: Amount (In lacs)
B104: 1 | C104: Land & site development | E104: ='CAPITAL COST'!C12 -> 0
B105: 2 | C105: Building & civil works | E105: ='CAPITAL COST'!C14 -> 2878.9368
B106: 3 | C106: Misc. Fixed Assets | E106: ='CAPITAL COST'!C16 -> 375.3
B107: 4 | C107: Electrical Installations | E107: ='CAPITAL COST'!C18 -> 140.5
B108: 5 | C108: Plant & Machinery | E108: ='CAPITAL COST'!C20 -> 467.53924
B109: 6 | C109: Preliminary and preoperative expenses | E109: ='CAPITAL COST'!C22 -> 285.72
B110: 7 | C110: Margin money for Working Capital | E110: ='CAPITAL COST'!C24 -> 22
B111: 8 | C111: Contingency | E111: ='CAPITAL COST'!#REF! -> #REF!
C113: Total | E113: =SUM(E104:E111) -> #REF!
B116: Floor-wise Details of no. of rooms, lobby, restaurant etc.

Sheet IRR_CASE_II
F2: (34)
E4: ANNEXURE IX
D5: Internal Rate of Return
E6: Rs. In Lakhs
B8: Year | D8: Construction | E8: Year 1 | F8: Year 2 | G8: Year 3 | H8: Year 4 | I8: Year 5 | J8: Year 6 | K8: Year 7 | L8: Year 8 | M8: Year 9
B10: CASH INFLOW | Q10: 0.1304865
B12: Profit After Tax | E12: ='P L _Case_II'!D59 -> 173.26791 | F12: ='P L _Case_II'!E59 -> 259.13865 | G12: ='P L _Case_II'!F59 -> 363.52877 | H12: ='P L _Case_II'!G59 -> 443.49834 | I12: ='P L _Case_II'!H59 -> 437.83929 | J12: ='P L _Case_II'!I59 -> 363.01551 | K12: ='P L _Case_II'!J59 -> 342.952 | L12: ='P L _Case_II'!K59 -> 290.2259 | M12: ='P L _Case_II'!L59 -> #VALUE!
B13: Depreciation | E13: ='P L '!D53 -> 452.19406 | F13: ='P L '!E53 -> 452.19406 | G13: ='P L '!F53 -> 452.19406 | H13: ='P L '!G53 -> 452.19406 | I13: ='P L '!H53 -> 452.19406 | J13: ='P L '!I53 -> 452.19406 | K13: ='P L '!J53 -> 452.19406 | L13: ='P L '!K53 -> 452.19406 | M13: ='P L '!L53 -> 452.19406
B14: Interest on Term Loan | E14: ='P L '!D50 -> 254.71875 | F14: ='P L '!E50 -> 240.1125 | G14: ='P L '!F50 -> 217.7875 | H14: ='P L '!G50 -> 186.675 | I14: ='P L '!H50 -> 147.25 | J14: ='P L '!I50 -> 99.0375 | K14: ='P L '!J50 -> 45.125 | L14: ='P L '!K50 -> 2.375 | M14: ='P L '!L50 -> 0
B15: Residual Value of Fixed Assets | L15: =0.5*'B S '!L13 -> 598.15591 | N15: *
B17: TOTAL CASH INFLOW | D17: =SUM(D10:D15) -> 0 | E17: =SUM(E10:E15) -> 880.18072 | F17: =SUM(F10:F15) -> 951.44521 | G17: =SUM(G10:G15) -> 1033.5103 | H17: =SUM(H10:H15) -> 1082.3674 | I17: =SUM(I10:I15) -> 1037.2833 | J17: =SUM(J10:J15) -> 914.24707 | K17: =SUM(K10:K15) -> 840.27106 | ... M17: =SUM(M10:M15) -> #VALUE!
B19: CASH OUTFLOWS
B21: Capital Expenditure | D21: ='CAPITAL COST'!D36+'CAPITAL COST'!D34 -> 4263.8643 | E21: 0 | F21: 0 | G21: 0 | H21: 0 | I21: 0 | J21: 0 | K21: 0 | L21: 0 | M21: 0
B23: TOTAL CASH OUTFLOW | D23: =SUM(D19:D22) -> 4263.8643 | E23: =SUM(E19:E22) -> 0 | F23: =SUM(F19:F22) -> 0 | G23: =SUM(G19:G22) -> 0 | H23: =SUM(H19:H22) -> 0 | I23: =SUM(I19:I22) -> 0 | J23: =SUM(J19:J22) -> 0 | K23: =SUM(K19:K22) -> 0 | ... M23: =SUM(M19:M22) -> 0
B25: NET CASH FLOW | D25: =D17-D23 -> -4263.8643 | E25: =E17-E23 -> 880.18072 | F25: =F17-F23 -> 951.44521 | G25: =G17-G23 -> 1033.5103 | H25: =H17-H23 -> 1082.3674 | I25: =I17-I23 -> 1037.2833 | J25: =J17-J23 -> 914.24707 | K25: =K17-K23 -> 840.27106 | ... M25: =M17-M23 -> #VALUE!
B27: Discounting Factor | D27: 1 | E27: 1 | F27: =1/(1+Q10) -> 0.88457492 | G27: =+F27/(1+$Q$10) -> 0.78247278 | H27: =+G27/(1+$Q$10) -> 0.69215579 | I27: =+H27/(1+$Q$10) -> 0.61226365 | J27: =+I27/(1+$Q$10) -> 0.54159307 | K27: =+J27/(1+$Q$10) -> 0.47907964 | L27: =+K27/(1+$Q$10) -> 0.42378183 | M27: =+L27/(1+$Q$10) -> 0.37486678
B28: Present Value | D28: =D25*D27 -> -4263.8643 | E28: =E25*E27 -> 880.18072 | F28: =F25*F27 -> 841.62457 | G28: =G25*G27 -> 808.6937 | H28: =H25*H27 -> 749.16687 | I28: =I25*I27 -> 635.09089 | J28: =J25*J27 -> 495.14987 | K28: =K25*K27 -> 402.55676 | ... M28: =M25*M27 -> #VALUE!
B31: Net Present Value (Rs.) | E31: =SUM(D28:L28) -> 1117.7173
B33: The Internal Rate of Return is | E33: =Q10 -> 0.1304865
B36: * Residual value of fixed assets has been considered at 50% of Book WDV

Sheet BEP ANAYSIS_II
F2: (30)
E4: ANNEXURE V
E5: Break Even Analysis
F6: Rs. In Lakhs
B7: Year | D7: Basis | E7: Year 1 | F7: Year 2 | G7: Year 3 | H7: Year 4 | I7: Year 5 | J7: Year 6 | K7: Year 7 | L7: Year 8 | M7: Year 9
B9: Gross Revenue Receipt | E9: ='P L _Case_II'!D25 -> 1475.5014 | F9: ='P L _Case_II'!E25 -> 1721.4183 | G9: ='P L _Case_II'!F25 -> 1967.3352 | H9: ='P L _Case_II'!G25 -> 2213.252 | I9: ='P L _Case_II'!H25 -> 2459.1689 | J9: ='P L _Case_II'!I25 -> 2459.1689 | K9: ='P L _Case_II'!J25 -> 2459.1689 | L9: ='P L _Case_II'!K25 -> 2459.1689 | M9: ='P L _Case_II'!L25 -> 2459.1689
B11: VARIABLE COSTS
B14: TOTAL VARIABLE COSTS | E14: ='P L _Case_II'!D51+'P L _Case_II'!D58-E20 -> #REF! | F14: ='P L _Case_II'!E51+'P L _Case_II'!E58-F20 -> #REF! | G14: ='P L _Case_II'!F51+'P L _Case_II'!F58-G20 -> #REF! | H14: ='P L _Case_II'!G51+'P L _Case_II'!G58-H20 -> #REF! | I14: ='P L _Case_II'!H51+'P L _Case_II'!H58-I20 -> #REF! | J14: ='P L _Case_II'!I51+'P L _Case_II'!I58-J20 -> #REF! | K14: ='P L _Case_II'!J51+'P L _Case_II'!J58-K20 -> #REF! | L14: ='P L _Case_II'!K51+'P L _Case_II'!K58-L20 -> #REF! | M14: ='P L _Case_II'!L51+'P L _Case_II'!L58-M20 -> #VALUE!
B16: CONTRIBUTION | E16: =E9-E14 -> #REF! | F16: =F9-F14 -> #REF! | G16: =G9-G14 -> #REF! | H16: =H9-H14 -> #REF! | I16: =I9-I14 -> #REF! | J16: =J9-J14 -> #REF! | K16: =K9-K14 -> #REF! | L16: =L9-L14 -> #REF! | M16: =M9-M14 -> #VALUE!
B18: FIXED COSTS
B20: TOTAL FIXED COSTS | E20: =#REF! -> #REF! | F20: =#REF! -> #REF! | G20: =#REF! -> #REF! | H20: =#REF! -> #REF! | I20: =#REF! -> #REF! | J20: =#REF! -> #REF! | K20: =#REF! -> #REF! | L20: =#REF! -> #REF! | M20: =#REF! -> #REF!
B22: P/V Ratio | E22: =E16/E9*100 -> #REF! | F22: =F16/F9*100 -> #REF! | G22: =G16/G9*100 -> #REF! | H22: =H16/H9*100 -> #REF! | I22: =I16/I9*100 -> #REF! | J22: =J16/J9*100 -> #REF! | K22: =K16/K9*100 -> #REF! | L22: =L16/L9*100 -> #REF! | M22: =M16/M9*100 -> #VALUE!
B23: Break Even Sales | E23: =+E20/E22*100 -> #REF! | F23: =+F20/F22*100 -> #REF! | G23: =+G20/G22*100 -> #REF! | H23: =+H20/H22*100 -> #REF! | I23: =+I20/I22*100 -> #REF! | J23: =+J20/J22*100 -> #REF! | K23: =+K20/K22*100 -> #REF! | L23: =+L20/L22*100 -> #REF! | M23: =+M20/M22*100 -> #REF!
B24: Break Even Point Room Occupancy Achieved | E24: =+E23/E9*100 -> #REF! | F24: =+F23/F9*100 -> #REF! | G24: =+G23/G9*100 -> #REF! | H24: =+H23/H9*100 -> #REF! | I24: =+I23/I9*100 -> #REF! | J24: =+J23/J9*100 -> #REF! | K24: =+K23/K9*100 -> #REF! | L24: =+L23/L9*100 -> #REF! | M24: =+M23/M9*100 -> #REF!
B25: Average Break Even Point Room Occupancy Achieved | E25: =AVERAGE(E24:L24) -> #REF!
B26: Break Even Point Room Capacity | E26: =E23/SALESPROJECTION!E81*100 -> #REF! | F26: =F23/SALESPROJECTION!F81*100 -> #REF! | G26: =G23/SALESPROJECTION!G81*100 -> #REF! | H26: =H23/SALESPROJECTION!H81*100 -> #REF! | I26: =I23/SALESPROJECTION!I81*100 -> #REF! | J26: =J23/SALESPROJECTION!J81*100 -> #REF! | K26: =K23/SALESPROJECTION!K81*100 -> #REF! | L26: =L23/SALESPROJECTION!L81*100 -> #REF! | M26: =M23/SALESPROJECTION!M81*100 -> #REF!
B27: Average Break Even Point Room Capacity | E27: =AVERAGE(E26:L26) -> #REF!
B28: Cash Break Even Point Room Capacity | E28: =(((E20-('P L _Case_II'!D49*0.75))/E22*100/SALESPROJECTION!E81*100)) -> #REF! | F28: =(((F20-('P L _Case_II'!E49*0.75))/F22*100/SALESPROJECTION!F81*100)) -> #REF! | G28: =(((G20-('P L _Case_II'!F49*0.75))/G22*100/SALESPROJECTION!G81*100)) -> #REF! | H28: =(((H20-('P L _Case_II'!G49*0.75))/H22*100/SALESPROJECTION!H81*100)) -> #REF! | I28: =(((I20-('P L _Case_II'!H49*0.75))/I22*100/SALESPROJECTION!I81*100)) -> #REF! | J28: =(((J20-('P L _Case_II'!I49*0.75))/J22*100/SALESPROJECTION!J81*100)) -> #REF! | K28: =(((K20-('P L _Case_II'!J49*0.75))/K22*100/SALESPROJECTION!K81*100)) -> #REF! | L28: =(((L20-('P L _Case_II'!K49*0.75))/L22*100/SALESPROJECTION!L81*100)) -> #REF! | M28: =(((M20-('P L _Case_II'!L49*0.75))/M22*100/SALESPROJECTION!M81*100)) -> #REF!
B29: Average Cash Break Even Point Room Capacity | E29: =AVERAGE(E28:L28) -> #REF!
E32: =E20+E14 -> #REF! | F32: =F20+F14 -> #REF! | G32: =G20+G14 -> #REF! | H32: =H20+H14 -> #REF! | I32: =I20+I14 -> #REF! | J32: =J20+J14 -> #REF! | K32: =K20+K14 -> #REF! | L32: =L20+L14 -> #REF! | M32: =M20+M14 -> #REF!
E33: =E32-'P L _Case_II'!D51-'P L _Case_II'!D58 -> #REF! | F33: =F32-'P L _Case_II'!E51-'P L _Case_II'!E58 -> #REF! | G33: =G32-'P L _Case_II'!F51-'P L _Case_II'!F58 -> #REF! | H33: =H32-'P L _Case_II'!G51-'P L _Case_II'!G58 -> #REF! | I33: =I32-'P L _Case_II'!H51-'P L _Case_II'!H58 -> #REF! | J33: =J32-'P L _Case_II'!I51-'P L _Case_II'!I58 -> #REF! | K33: =K32-'P L _Case_II'!J51-'P L _Case_II'!J58 -> #REF! | L33: =L32-'P L _Case_II'!K51-'P L _Case_II'!K58 -> #REF! | M33: =M32-'P L _Case_II'!L51-'P L _Case_II'!L58 -> #REF!

Sheet P  L _Case_II
D2: (28)
D4: ANNEXURE III
C5: Projected Profitability
J6: Rs. In Lacs
A8: Year | D8: 1 | E8: 2 | F8: 3 | G8: 4 | H8: 5 | I8: 6 | J8: 7 | K8: 8 | L8: 9
A10: Room Charges | D10: =SALESPROJECTION!E74 -> 3668.25 | E10: =SALESPROJECTION!F74 -> 3668.25 | F10: =SALESPROJECTION!G74 -> 3668.25 | G10: =SALESPROJECTION!H74 -> 3668.25 | H10: =SALESPROJECTION!I74 -> 3668.25 | I10: =SALESPROJECTION!J74 -> 3668.25 | J10: =SALESPROJECTION!K74 -> 3668.25 | K10: =SALESPROJECTION!L74 -> 3668.25 | L10: =SALESPROJECTION!M74 -> 3668.25
A11: F & B Sales | D11: =SALESPROJECTION!E75 -> 884.33569 | E11: =SALESPROJECTION!F75 -> 884.33569 | F11: =SALESPROJECTION!G75 -> 884.33569 | G11: =SALESPROJECTION!H75 -> 884.33569 | H11: =SALESPROJECTION!I75 -> 884.33569 | I11: =SALESPROJECTION!J75 -> 884.33569 | J11: =SALESPROJECTION!K75 -> 884.33569 | K11: =SALESPROJECTION!L75 -> 884.33569 | L11: =SALESPROJECTION!M75 -> 884.33569
A12: Banquet Hall Receipts | D12: =SALESPROJECTION!E76 -> 195 | E12: =SALESPROJECTION!F76 -> 195 | F12: =SALESPROJECTION!G76 -> 195 | G12: =SALESPROJECTION!H76 -> 195 | H12: =SALESPROJECTION!I76 -> 195 | I12: =SALESPROJECTION!J76 -> 195 | J12: =SALESPROJECTION!K76 -> 195 | K12: =SALESPROJECTION!L76 -> 195 | L12: =SALESPROJECTION!M76 -> 195
A13: Conference Hall Receipts | D13: =SALESPROJECTION!E79 -> 45 | E13: =SALESPROJECTION!F79 -> 45 | F13: =SALESPROJECTION!G79 -> 45 | G13: =SALESPROJECTION!H79 -> 45 | H13: =SALESPROJECTION!I79 -> 45 | I13: =SALESPROJECTION!J79 -> 45 | J13: =SALESPROJECTION!K79 -> 45 | K13: =SALESPROJECTION!L79 -> 45 | L13: =SALESPROJECTION!M79 -> 45
A14: Other Income | D14: =SALESPROJECTION!E80 -> 125.7522 | E14: =SALESPROJECTION!F80 -> 125.7522 | F14: =SALESPROJECTION!G80 -> 125.7522 | G14: =SALESPROJECTION!H80 -> 125.7522 | H14: =SALESPROJECTION!I80 -> 125.7522 | I14: =SALESPROJECTION!J80 -> 125.7522 | J14: =SALESPROJECTION!K80 -> 125.7522 | K14: =SALESPROJECTION!L80 -> 125.7522 | L14: =SALESPROJECTION!M80 -> 125.7522
A15: Gross Revenue Receipt | D15: =SUM(D10:D14) -> 4918.3379 | E15: =SUM(E10:E14) -> 4918.3379 | F15: =SUM(F10:F14) -> 4918.3379 | G15: =SUM(G10:G14) -> 4918.3379 | H15: =SUM(H10:H14) -> 4918.3379 | I15: =SUM(I10:I14) -> 4918.3379 | J15: =SUM(J10:J14) -> 4918.3379 | K15: =SUM(K10:K14) -> 4918.3379 | L15: =SUM(L10:L14) -> 4918.3379 | T15: =E15-SALESPROJECTION!F81 -> -111.75 | U15: =F15-SALESPROJECTION!G81 -> -111.75 | V15: =G15-SALESPROJECTION!H81 -> -111.75 | W15: =H15-SALESPROJECTION!I81 -> -111.75 | X15: =I15-SALESPROJECTION!J81 -> -111.75 | Y15: =J15-SALESPROJECTION!K81 -> -111.75
A16: Envisaged Occupancy | D16: =40%-10% -> 0.3 | E16: =D16+0.05 -> 0.35 | F16: =E16+0.05 -> 0.4 | G16: =F16+0.05 -> 0.45 | H16: =G16+5% -> 0.5 | I16: =H16 -> 0.5 | J16: =I16 -> 0.5 | K16: =J16 -> 0.5 | L16: =K16 -> 0.5
A18: Projected Sales
A20: Room Sales | D20: =D16*D10 -> 1100.475 | E20: =E16*E10 -> 1283.8875 | F20: =F16*F10 -> 1467.3 | G20: =G16*G10 -> 1650.7125 | H20: =H16*H10 -> 1834.125 | I20: =I16*I10 -> 1834.125 | J20: =J16*J10 -> 1834.125 | K20: =K16*K10 -> 1834.125 | L20: =L16*L10 -> 1834.125
A21: F & B Sales | D21: =$D$16*D11 -> 265.30071 | E21: =$E$16*E11 -> 309.51749 | F21: =$F$16*F11 -> 353.73428 | G21: =$G$16*G11 -> 397.95106 | H21: =$H$16*H11 -> 442.16784 | I21: =$I$16*I11 -> 442.16784 | J21: =$J$16*J11 -> 442.16784 | K21: =$K$16*K11 -> 442.16784 | L21: =$K$16*L11 -> 442.16784
A22: Banquet Hall Receipts | D22: =$D$16*D12 -> 58.5 | E22: =$E$16*E12 -> 68.25 | F22: =$F$16*F12 -> 78 | G22: =$G$16*G12 -> 87.75 | H22: =$H$16*H12 -> 97.5 | I22: =$I$16*I12 -> 97.5 | J22: =$J$16*J12 -> 97.5 | K22: =$K$16*K12 -> 97.5 | L22: =$K$16*L12 -> 97.5
A23: Conference Hall Receipts | D23: =$D$16*D13 -> 13.5 | E23: =$E$16*E13 -> 15.75 | F23: =$F$16*F13 -> 18 | G23: =$G$16*G13 -> 20.25 | H23: =$H$16*H13 -> 22.5 | I23: =$I$16*I13 -> 22.5 | J23: =$J$16*J13 -> 22.5 | K23: =$K$16*K13 -> 22.5 | L23: =$K$16*L13 -> 22.5
A24: Other Income | D24: =D16*D14 -> 37.725659 | E24: =E16*E14 -> 44.013269 | F24: =F16*F14 -> 50.300879 | G24: =G16*G14 -> 56.588489 | H24: =H16*H14 -> 62.876099 | I24: =I16*I14 -> 62.876099 | J24: =J16*J14 -> 62.876099 | K24: =K16*K14 -> 62.876099 | L24: =L16*L14 -> 62.876099
A25: Total Projected Sales | D25: =SUM(D20:D24) -> 1475.5014 | E25: =SUM(E20:E24) -> 1721.4183 | F25: =SUM(F20:F24) -> 1967.3352 | G25: =SUM(G20:G24) -> 2213.252 | H25: =SUM(H20:H24) -> 2459.1689 | I25: =SUM(I20:I24) -> 2459.1689 | J25: =SUM(J20:J24) -> 2459.1689 | K25: =SUM(K20:K24) -> 2459.1689 | L25: =SUM(L20:L24) -> 2459.1689
A27: Revenue Expenses | B27: As | C27: of
A29: Food & Beverages Cost | B29: 0.4 | C29: F & B sales | D29: =ROUND(B29*D21,2) -> 106.12 | E29: =B29*E21 -> 123.807 | F29: =B29*F21 -> 141.49371 | G29: =B29*G21 -> 159.18042 | H29: =B29*H21 -> 176.86714 | I29: =B29*I21 -> 176.86714 | J29: =$B$29*J21 -> 176.86714 | K29: =$B$29*K21 -> 176.86714 | L29: =$B$29*L21 -> 176.86714
A30: Banquet & Conference Hall Expenses | B30: 0.25 | C30: B & C Receipts | D30: =(D22+D23)*$B$30 -> 18 | E30: =(E22+E23)*$B$30 -> 21 | F30: =(F22+F23)*$B$30 -> 24 | G30: =(G22+G23)*$B$30 -> 27 | H30: =(H22+H23)*$B$30 -> 30 | I30: =(I22+I23)*$B$30 -> 30 | J30: =(J22+J23)*$B$30 -> 30 | K30: =(K22+K23)*$B$30 -> 30 | L30: =(L22+L23)*$B$30 -> 30
A31: Employee Related Expenses | B31: 0.09 | C31: Total Sales | D31: =B31*D25 -> 132.79512 | E31: =B31*E25*1.05 -> 162.67403 | F31: =B31*F25*1.1 -> 194.76618 | G31: =B31*G25*1.2 -> 239.03122 | H31: =B31*H25*1.2 -> 265.59025 | I31: =B31*I25*1.25 -> 276.65651 | J31: =$B$31*J25*1.3 -> 287.72277 | K31: =$B$31*K25*1.35 -> 298.78903 | L31: =$B$31*L25*1.4 -> 309.85529 | P31: Increasing
A32: Power, Fuel & Water Charges | B32: 0.075 | C32: Total Sales | D32: =ROUND(B32*D25,2) -> 110.66 | E32: =B32*E25 -> 129.10637 | F32: =B32*F25 -> 147.55014 | G32: =B32*G25 -> 165.9939 | H32: =B32*H25 -> 184.43767 | I32: =B32*I25 -> 184.43767 | J32: =$B$32*J25 -> 184.43767 | K32: =$B$32*K25 -> 184.43767 | L32: =$B$32*L25 -> 184.43767
A33: Repair & Maintenance | B33: 0.005 | C33: Assets | D33: =depreciation!D147*0.5% -> 19.058351 | E33: =depreciation!E147*1% -> 33.594762 | F33: =depreciation!F147*1.25% -> 37.528526 | G33: =depreciation!G147*2.5% -> 64.002201 | H33: =depreciation!H147*2.5% -> 55.69735 | I33: =depreciation!I147*3% -> 56.570998 | J33: =depreciation!J147*3.5% -> 54.197705 | K33: =depreciation!K147*4% -> 47.852472 | L33: =depreciation!L147*4.75% -> 39.383093 | P33: Increasing
A34: Discount on Room Rentals | B34: 0.05 | C34: Room Sales | D34: =D20*B34 -> 55.02375 | E34: =E20*B34*1.5 -> 96.291563 | F34: =F20*B34*2 -> 146.73 | G34: =G20*B34*2.15 -> 177.45159 | H34: =H20*B34*2.25 -> 206.33906 | I34: =I20*B34*2.5 -> 229.26563 | J34: =J20*$B$34*2.5 -> 229.26563 | K34: =K20*$B$34*2.5 -> 229.26563 | L34: =L20*$B$34*2.5 -> 229.26563 | P34: Increasing | Q34: Max 25%
A35: Room Upkeep Exp. | B35: 0.04 | C35: Room Sales | D35: =B35*D20 -> 44.019 | E35: =B35*E20*1.25 -> 64.194375 | F35: =B35*F20*1.25 -> 73.365 | G35: =B35*G20*1.25 -> 82.535625 | H35: =B35*H20*1.25 -> 91.70625 | I35: =B35*I20*1.25 -> 91.70625 | J35: =B35*J20*1.25 -> 91.70625 | K35: =B35*K20*1.25 -> 91.70625 | L35: =B35*L20*1.25 -> 91.70625 | P35: Increasing | Q35: Normal
A36: General Upkeep & Services | B36: 0.01 | C36: Total Sales | D36: =B36*D25 -> 14.755014 | E36: =B36*E25 -> 17.214183 | F36: =B36*F25*1.1 -> 21.640687 | G36: =B36*G25*1.2 -> 26.559025 | H36: =B36*H25*1.2 -> 29.510027 | I36: =B36*I25*1.2 -> 29.510027 | J36: =B36*J25*1.2 -> 29.510027 | K36: =B36*K25*1.2 -> 29.510027 | L36: =B36*L25*1.2 -> 29.510027 | P36: Increasing | Q36: Normal
A37: Administration Expenses | B37: 0.0225 | C37: Total Sales | D37: =B37*D25 -> 33.198781 | E37: =B37*E25*1.1 -> 42.605102 | F37: =B37*F25*1.1 -> 48.691545 | G37: =B37*G25*1.15 -> 57.267897 | H37: =B37*H25*1.2 -> 66.397561 | I37: =B37*I25*1.25 -> 69.164127 | J37: =B37*J25*1.3 -> 71.930692 | K37: =B37*K25*1.35 -> 74.697257 | L37: =B37*L25*1.4 -> 77.463822 | P37: Increasing
A38: Management expenses | B38: 0.025 | C38: Total Sales | D38: =B38*D25 -> 36.887534 | E38: =B38*E25*1.1 -> 47.339002 | F38: =B38*F25*1.1 -> 54.101717 | G38: =B38*G25*1.25 -> 69.164127 | H38: =B38*H25*1.25 -> 76.849029 | I38: =B38*I25*1.25 -> 76.849029 | J38: =B38*J25*1.25 -> 76.849029 | K38: =B38*K25*1.25 -> 76.849029 | L38: =B38*L25*1.25 -> 76.849029 | P38: Increasing | Q38: Normal
A39: Advertisement & Sales Promotion | B39: 0.0125 | C39: Total Sales | D39: =B39*D25 -> 18.443767 | E39: =B39*E25*1.5 -> 32.276592 | F39: =B39*F25*2 -> 49.183379 | G39: =B39*G25*2.5 -> 69.164127 | H39: =B39*H25*2.75 -> 84.533932 | I39: =B39*I25*3.5 -> 107.58864 | J39: =B39*J25*3.75 -> 115.27354 | K39: =B39*K25*4 -> 122.95845 | L39: =B39*L25*4.25 -> 130.64335 | P39: Increasing
A40: Insurance Charges
A41: Building | B41: 0.0033 | D41: =B41*'CAPITAL COST'!C14 -> 9.5004913 | E41: =D41 -> 9.5004913 | F41: =E41 -> 9.5004913 | G41: =F41 -> 9.5004913 | H41: =G41 -> 9.5004913 | I41: =H41 -> 9.5004913 | J41: =I41 -> 9.5004913 | K41: =J41 -> 9.5004913 | L41: =K41 -> 9.5004913 | V41: =B41*depreciation!D128 -> 10.488325 | W41: =B41*'CAPITAL COST'!D14 -> 9.5004913
A42: Plant & Equipment | B42: 0.005 | D42: =B42*'CAPITAL COST'!D20+(ASSETS!I82-ASSETS!I78+('details of fixed assets '!F145/100000+'details of fixed assets '!F146/100000))*B42 -> 3.6821262 | E42: =D42 -> 3.6821262 | F42: =E42 -> 3.6821262 | G42: =F42 -> 3.6821262 | H42: =G42 -> 3.6821262 | I42: =H42 -> 3.6821262 | J42: =I42 -> 3.6821262 | K42: =J42 -> 3.6821262 | L42: =K42 -> 3.6821262 | W42: =B42*('CAPITAL COST'!D20+'CAPITAL COST'!D16) -> 4.2141962
A43: Furniture & Accessories | B43: 0.0025 | D43: =B43*(SUM('details of fixed assets '!F138:F144))/100000 -> 0.38145 | E43: =D43 -> 0.38145 | F43: =E43 -> 0.38145 | G43: =F43 -> 0.38145 | H43: =G43 -> 0.38145 | I43: =H43 -> 0.38145 | J43: =I43 -> 0.38145 | K43: =J43 -> 0.38145 | L43: =K43 -> 0.38145
A44: Inventory | B44: 0.002 | D44: =+' wORKING CAPITAL'!E15*$B$44 -> 0.024 | E44: =+' wORKING CAPITAL'!F15*$B$44 -> 0.023922285 | F44: =+' wORKING CAPITAL'!G15*$B$44 -> 0.026530071 | G44: =+' wORKING CAPITAL'!H15*$B$44 -> 0.029477856 | H44: =+' wORKING CAPITAL'!I15*$B$44 -> 0.03891077 | I44: =+' wORKING CAPITAL'!J15*$B$44 -> 0.049522799 | J44: =+' wORKING CAPITAL'!K15*$B$44 -> 0.061313941 | K44: =+' wORKING CAPITAL'!L15*$B$44 -> 0.074284198 | L44: =+' wORKING CAPITAL'!M15*$B$44 -> 0.070746855
A45: Brokerage & Commission | B45: 0.005 | C45: Total Sales | D45: =B45*D25 -> 7.3775068 | E45: =B45*E25 -> 8.6070913 | F45: =B45*F25*1.25 -> 12.295845 | G45: =B45*G25*1.75 -> 19.365955 | H45: =B45*H25*2 -> 24.591689 | I45: =B45*I25*2.5 -> 30.739612 | J45: =B45*J25*3 -> 36.887534 | K45: =B45*K25*3.5 -> 43.035456 | L45: =B45*L25*3.6 -> 44.265041 | U45: =MIN(2,#REF!,#REF!,#REF!,#REF!,#REF!,#REF!,#REF!,#REF!) -> #REF!
A46: Interest on Term Loan | D46: =Interest!I58 -> 240.1125 | E46: =Interest!I70 -> 217.7875 | F46: =Interest!I82 -> 186.675 | G46: =Interest!I94 -> 147.25 | H46: =Interest!I106 -> 99.0375 | I46: =Interest!I118 -> 45.125 | J46: =Interest!I130 -> 2.375 | K46: =Interest!I142 -> 0 | L46: =Interest!I154 -> 0
A47: Interest on Working Capital Loan | D47: =' wORKING CAPITAL'!E29 -> 0 | E47: =' wORKING CAPITAL'!F29 -> 0 | F47: =' wORKING CAPITAL'!G29 -> 0 | G47: =' wORKING CAPITAL'!H29 -> 0 | H47: =' wORKING CAPITAL'!I29 -> 0 | I47: =' wORKING CAPITAL'!J29 -> 0 | J47: =' wORKING CAPITAL'!K29 -> 0 | K47: =' wORKING CAPITAL'!L29 -> 0 | L47: =' wORKING CAPITAL'!M29 -> 0
A49: Depreciation | D49: =depreciation!D139 -> 452.19406 | E49: =depreciation!E139 -> 452.19406 | F49: =depreciation!F139 -> 452.19406 | G49: =depreciation!G139 -> 452.19406 | H49: =depreciation!H139 -> 452.19406 | I49: =depreciation!I139 -> 452.19406 | J49: =depreciation!J139 -> 452.19406 | K49: =depreciation!K139 -> 452.19406 | L49: =depreciation!L139 -> 452.19406
A51: Total Operating Costs | D51: =SUM(D29:D50) -> 1302.2335 | E51: =SUM(E29:E50) -> 1462.2796 | F51: =SUM(F29:F50) -> 1603.8064 | G51: =SUM(G29:G50) -> 1769.7537 | H51: =SUM(H29:H50) -> 1857.3545 | I51: =SUM(I29:I50) -> 1870.2883 | J51: =SUM(J29:J50) -> 1852.8424 | K51: =SUM(K29:K50) -> 1871.8008 | L51: =SUM(L29:L50) -> 1886.0752
A55: Gross Profit | D55: =D25-D51 -> 173.26791 | E55: =E25-E51 -> 259.13865 | F55: =F25-F51 -> 363.52877 | G55: =G25-G51 -> 443.49834 | H55: =H25-H51 -> 601.81445 | I55: =I25-I51 -> 588.88067 | J55: =J25-J51 -> 606.32652 | K55: =K25-K51 -> 587.36813 | L55: =L25-L51 -> 573.09374
A57: PBIT | D57: =D55+D47+D46 -> 413.38041 | E57: =E55+E47+E46 -> 476.92615 | F57: =F55+F47+F46 -> 550.20377 | G57: =G55+G47+G46 -> 590.74834 | H57: =H55+H47+H46 -> 700.85195 | I57: =I55+I47+I46 -> 634.00567 | J57: =J55+J47+J46 -> 608.70152 | K57: =K55+K47+K46 -> 587.36813 | L57: =L55+L47+L46 -> 573.09374
A58: Provision For Tax being MAT | D58: ='iNCOME tAX cOMPUTATION'!D19*0 -> 0 | E58: 0 | F58: 0 | G58: 0 | H58: ='iNCOME tAX cOMPUTATION'!H19*0.85 -> 163.97516 | I58: ='iNCOME tAX cOMPUTATION'!I19 -> 225.86516 | J58: ='iNCOME tAX cOMPUTATION'!J19 -> 263.37452 | K58: ='iNCOME tAX cOMPUTATION'!K19 -> 297.14223 | L58: ='iNCOME tAX cOMPUTATION'!L19 -> #VALUE!
A59: Profit After Tax | D59: =D55-D58 -> 173.26791 | E59: =E55-E58 -> 259.13865 | F59: =F55-F58 -> 363.52877 | G59: =G55-G58 -> 443.49834 | H59: =H55-H58 -> 437.83929 | I59: =I55-I58 -> 363.01551 | J59: =J55-J58 -> 342.952 | K59: =K55-K58 -> 290.2259 | L59: =L55-L58 -> #VALUE!
A60: Cummulative Reserve | D60: =D59 -> 173.26791 | E60: =D60+E59 -> 432.40656 | F60: =E60+F59 -> 795.93533 | G60: =F60+G59 -> 1239.4337 | H60: =G60+H59 -> 1677.273 | I60: =H60+I59 -> 2040.2885 | J60: =I60+J59 -> 2383.2405 | K60: =J60+K59 -> 2673.4664 | L60: =K60+L59 -> #VALUE!
A61: Cash Profit | D61: =D55+D49 -> 625.46197 | E61: =E55+E49 -> 711.33271 | F61: =F55+F49 -> 815.72283 | G61: =G55+G49 -> 895.6924 | H61: =H55+H49 -> 1054.0085 | I61: =I55+I49 -> 1041.0747 | J61: =J55+J49 -> 1058.5206 | K61: =K55+K49 -> 1039.5622 | L61: =L55+L49 -> 1025.2878
A62: % of Cash Profit | D62: =D61/D25*100 -> 42.389793 | E62: =E61/E25*100 -> 41.32248 | F62: =F61/F25*100 -> 41.463338 | G62: =G61/G25*100 -> 40.469517 | H62: =H61/H25*100 -> 42.860354 | I62: =I61/I25*100 -> 42.334413 | J62: =J61/J25*100 -> 43.043833 | K62: =K61/K25*100 -> 42.272907 | L62: =L61/L25*100 -> 41.692451
A63: % of PAT | D63: =D59/D25*100 -> 11.742986 | E63: =E59/E25*100 -> 15.053788 | F63: =F59/F25*100 -> 18.478233 | G63: =G59/G25*100 -> 20.038312 | H63: =H59/H25*100 -> 17.80436 | I63: =I59/I25*100 -> 14.761715 | J63: =J59/J25*100 -> 13.945849 | K63: =K59/K25*100 -> 11.801788 | L63: =L59/L25*100 -> #VALUE!
A64: Retained Profit | D64: =D59 -> 173.26791 | E64: =E59 -> 259.13865 | F64: =F59 -> 363.52877 | G64: =G59 -> 443.49834 | H64: =H59 -> 437.83929 | I64: =I59 -> 363.01551 | J64: =J59 -> 342.952 | K64: =K59 -> 290.2259 | L64: =L59 -> #VALUE!
A66: DSCR
A67: Cash Profit & Intt On T L | D67: =D59+D49+D46 -> 865.57447 | E67: =E59+E49+E46 -> 929.12021 | F67: =F59+F49+F46 -> 1002.3978 | G67: =G59+G49+G46 -> 1042.9424 | H67: =H59+H49+H46 -> 989.07085 | I67: =I59+I49+I46 -> 860.33457 | J67: =J59+J49+J46 -> 797.52106 | K67: =K59+K49+K46 -> 742.41996 | L67: =L59+L49+L46 -> #VALUE!
A68: TL & Intt | D68: =#REF! -> #REF! | E68: =#REF! -> #REF! | F68: =#REF! -> #REF! | G68: =#REF! -> #REF! | H68: =#REF! -> #REF! | I68: =#REF! -> #REF! | J68: =#REF! -> #REF! | K68: =#REF! -> #REF! | L68: =#REF! -> #REF!
D69: =D67/D68 -> #REF! | E69: =E67/E68 -> #REF! | F69: =F67/F68 -> #REF! | G69: =G67/G68 -> #REF! | H69: =H67/H68 -> #REF! | I69: =I67/I68 -> #REF! | J69: =J67/J68 -> #REF! | K69: =K67/K68 -> #REF! | L69: =L67/L68 -> #VALUE!
D71: =AVERAGE(D69:K69) -> #REF!
D118: =D55+D49 -> 625.46197 | E118: =E55+E49 -> 711.33271 | F118: =F55+F49 -> 815.72283 | G118: =G55+G49 -> 895.6924 | H118: =H55+H49 -> 1054.0085 | I118: =I55+I49 -> 1041.0747 | J118: =J55+J49 -> 1058.5206 | K118: =K55+K49 -> 1039.5622 | L118: =L55+L49 -> 1025.2878
D120: =D118/D25*100 -> 42.389793 | E120: =E118/E25*100 -> 41.32248 | F120: =F118/F25*100 -> 41.463338 | G120: =G118/G25*100 -> 40.469517 | H120: =H118/H25*100 -> 42.860354 | I120: =I118/I25*100 -> 42.334413 | J120: =J118/J25*100 -> 43.043833 | K120: =K118/K25*100 -> 42.272907 | L120: =L118/L25*100 -> 41.692451
D122: =D49+D46+D55 -> 865.57447 | E122: =E49+E46+E55 -> 929.12021 | F122: =F49+F46+F55 -> 1002.3978 | G122: =G49+G46+G55 -> 1042.9424 | H122: =H49+H46+H55 -> 1153.046 | I122: =I49+I46+I55 -> 1086.1997 | J122: =J49+J46+J55 -> 1060.8956 | K122: =K49+K46+K55 -> 1039.5622 | L122: =L49+L46+L55 -> 1025.2878
D124: =D122/D25*100 -> 58.663075 | E124: =E122/E25*100 -> 53.974111 | F124: =F122/F25*100 -> 50.952062 | G124: =G122/G25*100 -> 47.122622 | H124: =H122/H25*100 -> 46.887629 | I124: =I122/I25*100 -> 44.169382 | J124: =J122/J25*100 -> 43.140411 | K124: =K122/K25*100 -> 42.272907 | L124: =L122/L25*100 -> 41.692451
D126: =D46+D49 -> 692.30656 | E126: =E46+E49 -> 669.98156 | F126: =F46+F49 -> 638.86906 | G126: =G46+G49 -> 599.44406 | H126: =H46+H49 -> 551.23156 | I126: =I46+I49 -> 497.31906 | J126: =J46+J49 -> 454.56906 | K126: =K46+K49 -> 452.19406 | L126: =L46+L49 -> 452.19406

Sheet IRR_CASE_III
F2: (34)
E4: ANNEXURE IX
D5: Internal Rate of Return
E6: Rs. In Lakhs
B8: Year | D8: Construction | E8: Year 1 | F8: Year 2 | G8: Year 3 | H8: Year 4 | I8: Year 5 | J8: Year 6 | K8: Year 7 | L8: Year 8 | M8: Year 9
B10: CASH INFLOW | Q10: 0.150178
B12: Profit After Tax | E12: ='P L _Case_III'!D59 -> 374.30812 | F12: ='P L _Case_III'!E59 -> 427.41975 | G12: ='P L _Case_III'!F59 -> 374.79916 | H12: ='P L _Case_III'!G59 -> 397.07843 | I12: ='P L _Case_III'!H59 -> 505.82163 | J12: ='P L _Case_III'!I59 -> 446.74223 | K12: ='P L _Case_III'!J59 -> 421.1456 | L12: ='P L _Case_III'!K59 -> 362.88636 | M12: ='P L _Case_III'!L59 -> #VALUE!
B13: Depreciation | E13: ='P L '!D53 -> 452.19406 | F13: ='P L '!E53 -> 452.19406 | G13: ='P L '!F53 -> 452.19406 | H13: ='P L '!G53 -> 452.19406 | I13: ='P L '!H53 -> 452.19406 | J13: ='P L '!I53 -> 452.19406 | K13: ='P L '!J53 -> 452.19406 | L13: ='P L '!K53 -> 452.19406 | M13: ='P L '!L53 -> 452.19406
B14: Interest on Term Loan | E14: ='P L '!D50 -> 254.71875 | F14: ='P L '!E50 -> 240.1125 | G14: ='P L '!F50 -> 217.7875 | H14: ='P L '!G50 -> 186.675 | I14: ='P L '!H50 -> 147.25 | J14: ='P L '!I50 -> 99.0375 | K14: ='P L '!J50 -> 45.125 | L14: ='P L '!K50 -> 2.375 | M14: ='P L '!L50 -> 0
B15: Residual Value of Fixed Assets | L15: =0.5*'B S '!L13 -> 598.15591 | N15: *
B17: TOTAL CASH INFLOW | D17: =SUM(D10:D15) -> 0 | E17: =SUM(E10:E15) -> 1081.2209 | F17: =SUM(F10:F15) -> 1119.7263 | G17: =SUM(G10:G15) -> 1044.7807 | H17: =SUM(H10:H15) -> 1035.9475 | I17: =SUM(I10:I15) -> 1105.2657 | J17: =SUM(J10:J15) -> 997.97379 | K17: =SUM(K10:K15) -> 918.46465 | ... M17: =SUM(M10:M15) -> #VALUE!
B19: CASH OUTFLOWS
B21: Capital Expenditure | D21: ='CAPITAL COST'!D36+'CAPITAL COST'!D34 -> 4263.8643 | E21: 0 | F21: 0 | G21: 0 | H21: 0 | I21: 0 | J21: 0 | K21: 0 | L21: 0 | M21: 0
B23: TOTAL CASH OUTFLOW | D23: =SUM(D19:D22) -> 4263.8643 | E23: =SUM(E19:E22) -> 0 | F23: =SUM(F19:F22) -> 0 | G23: =SUM(G19:G22) -> 0 | H23: =SUM(H19:H22) -> 0 | I23: =SUM(I19:I22) -> 0 | J23: =SUM(J19:J22) -> 0 | K23: =SUM(K19:K22) -> 0 | ... M23: =SUM(M19:M22) -> 0
B25: NET CASH FLOW | D25: =D17-D23 -> -4263.8643 | E25: =E17-E23 -> 1081.2209 | F25: =F17-F23 -> 1119.7263 | G25: =G17-G23 -> 1044.7807 | H25: =H17-H23 -> 1035.9475 | I25: =I17-I23 -> 1105.2657 | J25: =J17-J23 -> 997.97379 | K25: =K17-K23 -> 918.46465 | ... M25: =M17-M23 -> #VALUE!
B27: Discounting Factor | D27: 1 | E27: 1 | F27: =1/(1+Q10) -> 0.86943064 | G27: =+F27/(1+$Q$10) -> 0.75590965 | H27: =+G27/(1+$Q$10) -> 0.65721101 | I27: =+H27/(1+$Q$10) -> 0.57139939 | J27: =+I27/(1+$Q$10) -> 0.49679214 | K27: =+J27/(1+$Q$10) -> 0.43192631 | L27: =+K27/(1+$Q$10) -> 0.37552997 | M27: =+L27/(1+$Q$10) -> 0.32649727
B28: Present Value | D28: =D25*D27 -> -4263.8643 | E28: =E25*E27 -> 1081.2209 | F28: =F25*F27 -> 973.52437 | G28: =G25*G27 -> 789.75983 | H28: =H25*H27 -> 680.83609 | I28: =I25*I27 -> 631.54814 | J28: =J25*J27 -> 495.78554 | K28: =K25*K27 -> 396.70905 | ... M28: =M25*M27 -> #VALUE!
B31: Net Present Value (Rs.) | E31: =SUM(D28:L28) -> 1317.1241
B33: The Internal Rate of Return is | E33: =Q10 -> 0.150178
B36: * Residual value of fixed assets has been considered at 50% of Book WDV

Sheet P  L _Case_III
D2: (28)
D4: ANNEXURE III
C5: Projected Profitability
J6: Rs. In Lacs
A8: Year | D8: 1 | E8: 2 | F8: 3 | G8: 4 | H8: 5 | I8: 6 | J8: 7 | K8: 8 | L8: 9
A10: Room Charges | D10: =SALESPROJECTION!E74 -> 3668.25 | E10: =SALESPROJECTION!F74 -> 3668.25 | F10: =SALESPROJECTION!G74 -> 3668.25 | G10: =SALESPROJECTION!H74 -> 3668.25 | H10: =SALESPROJECTION!I74 -> 3668.25 | I10: =SALESPROJECTION!J74 -> 3668.25 | J10: =SALESPROJECTION!K74 -> 3668.25 | K10: =SALESPROJECTION!L74 -> 3668.25 | L10: =SALESPROJECTION!M74 -> 3668.25
A11: F & B Sales | D11: =SALESPROJECTION!E75 -> 884.33569 | E11: =SALESPROJECTION!F75 -> 884.33569 | F11: =SALESPROJECTION!G75 -> 884.33569 | G11: =SALESPROJECTION!H75 -> 884.33569 | H11: =SALESPROJECTION!I75 -> 884.33569 | I11: =SALESPROJECTION!J75 -> 884.33569 | J11: =SALESPROJECTION!K75 -> 884.33569 | K11: =SALESPROJECTION!L75 -> 884.33569 | L11: =SALESPROJECTION!M75 -> 884.33569
A12: Banquet Hall Receipts | D12: =SALESPROJECTION!E76 -> 195 | E12: =SALESPROJECTION!F76 -> 195 | F12: =SALESPROJECTION!G76 -> 195 | G12: =SALESPROJECTION!H76 -> 195 | H12: =SALESPROJECTION!I76 -> 195 | I12: =SALESPROJECTION!J76 -> 195 | J12: =SALESPROJECTION!K76 -> 195 | K12: =SALESPROJECTION!L76 -> 195 | L12: =SALESPROJECTION!M76 -> 195
A13: Conference Hall Receipts | D13: =SALESPROJECTION!E79 -> 45 | E13: =SALESPROJECTION!F79 -> 45 | F13: =SALESPROJECTION!G79 -> 45 | G13: =SALESPROJECTION!H79 -> 45 | H13: =SALESPROJECTION!I79 -> 45 | I13: =SALESPROJECTION!J79 -> 45 | J13: =SALESPROJECTION!K79 -> 45 | K13: =SALESPROJECTION!L79 -> 45 | L13: =SALESPROJECTION!M79 -> 45
A14: Other Income | D14: =SALESPROJECTION!E80 -> 125.7522 | E14: =SALESPROJECTION!F80 -> 125.7522 | F14: =SALESPROJECTION!G80 -> 125.7522 | G14: =SALESPROJECTION!H80 -> 125.7522 | H14: =SALESPROJECTION!I80 -> 125.7522 | I14: =SALESPROJECTION!J80 -> 125.7522 | J14: =SALESPROJECTION!K80 -> 125.7522 | K14: =SALESPROJECTION!L80 -> 125.7522 | L14: =SALESPROJECTION!M80 -> 125.7522
A15: Gross Revenue Receipt | D15: =SUM(D10:D14) -> 4918.3379 | E15: =SUM(E10:E14) -> 4918.3379 | F15: =SUM(F10:F14) -> 4918.3379 | G15: =SUM(G10:G14) -> 4918.3379 | H15: =SUM(H10:H14) -> 4918.3379 | I15: =SUM(I10:I14) -> 4918.3379 | J15: =SUM(J10:J14) -> 4918.3379 | K15: =SUM(K10:K14) -> 4918.3379 | L15: =SUM(L10:L14) -> 4918.3379 | T15: =E15-SALESPROJECTION!F81 -> -111.75 | U15: =F15-SALESPROJECTION!G81 -> -111.75 | V15: =G15-SALESPROJECTION!H81 -> -111.75 | W15: =H15-SALESPROJECTION!I81 -> -111.75 | X15: =I15-SALESPROJECTION!J81 -> -111.75 | Y15: =J15-SALESPROJECTION!K81 -> -111.75
A16: Envisaged Occupancy | D16: =40% -> 0.4 | E16: =D16+0.05 -> 0.45 | F16: =E16+0.05 -> 0.5 | G16: =F16+0.05 -> 0.55 | H16: =G16+5% -> 0.6 | I16: =H16 -> 0.6 | J16: =I16 -> 0.6 | K16: =J16 -> 0.6 | L16: =K16 -> 0.6
A18: Projected Sales
A20: Room Sales | D20: =D16*D10 -> 1467.3 | E20: =E16*E10 -> 1650.7125 | F20: =F16*F10 -> 1834.125 | G20: =G16*G10 -> 2017.5375 | H20: =H16*H10 -> 2200.95 | I20: =I16*I10 -> 2200.95 | J20: =J16*J10 -> 2200.95 | K20: =K16*K10 -> 2200.95 | L20: =L16*L10 -> 2200.95
A21: F & B Sales | D21: =$D$16*D11 -> 353.73428 | E21: =$E$16*E11 -> 397.95106 | F21: =$F$16*F11 -> 442.16784 | G21: =$G$16*G11 -> 486.38463 | H21: =$H$16*H11 -> 530.60141 | I21: =$I$16*I11 -> 530.60141 | J21: =$J$16*J11 -> 530.60141 | K21: =$K$16*K11 -> 530.60141 | L21: =$K$16*L11 -> 530.60141
A22: Banquet Hall Receipts | D22: =$D$16*D12 -> 78 | E22: =$E$16*E12 -> 87.75 | F22: =$F$16*F12 -> 97.5 | G22: =$G$16*G12 -> 107.25 | H22: =$H$16*H12 -> 117 | I22: =$I$16*I12 -> 117 | J22: =$J$16*J12 -> 117 | K22: =$K$16*K12 -> 117 | L22: =$K$16*L12 -> 117
A23: Conference Hall Receipts | D23: =$D$16*D13 -> 18 | E23: =$E$16*E13 -> 20.25 | F23: =$F$16*F13 -> 22.5 | G23: =$G$16*G13 -> 24.75 | H23: =$H$16*H13 -> 27 | I23: =$I$16*I13 -> 27 | J23: =$J$16*J13 -> 27 | K23: =$K$16*K13 -> 27 | L23: =$K$16*L13 -> 27
A24: Other Income | D24: =D16*D14 -> 50.300879 | E24: =E16*E14 -> 56.588489 | F24: =F16*F14 -> 62.876099 | G24: =G16*G14 -> 69.163708 | H24: =H16*H14 -> 75.451318 | I24: =I16*I14 -> 75.451318 | J24: =J16*J14 -> 75.451318 | K24: =K16*K14 -> 75.451318 | L24: =L16*L14 -> 75.451318
A25: Total Projected Sales | D25: =SUM(D20:D24) -> 1967.3352 | E25: =SUM(E20:E24) -> 2213.252 | F25: =SUM(F20:F24) -> 2459.1689 | G25: =SUM(G20:G24) -> 2705.0858 | H25: =SUM(H20:H24) -> 2951.0027 | I25: =SUM(I20:I24) -> 2951.0027 | J25: =SUM(J20:J24) -> 2951.0027 | K25: =SUM(K20:K24) -> 2951.0027 | L25: =SUM(L20:L24) -> 2951.0027
A27: Revenue Expenses | B27: As | C27: of
A29: Food & Beverages Cost | B29: 0.4 | C29: F & B sales | D29: =ROUND(B29*D21,2) -> 141.49 | E29: =B29*E21 -> 159.18042 | F29: =B29*F21 -> 176.86714 | G29: =B29*G21 -> 194.55385 | H29: =B29*H21 -> 212.24057 | I29: =B29*I21 -> 212.24057 | J29: =$B$29*J21 -> 212.24057 | K29: =$B$29*K21 -> 212.24057 | L29: =$B$29*L21 -> 212.24057
A30: Banquet & Conference Hall Expenses | B30: 0.25 | C30: B & C Receipts | D30: =(D22+D23)*$B$30 -> 24 | E30: =(E22+E23)*$B$30 -> 27 | F30: =(F22+F23)*$B$30 -> 30 | G30: =(G22+G23)*$B$30 -> 33 | H30: =(H22+H23)*$B$30 -> 36 | I30: =(I22+I23)*$B$30 -> 36 | J30: =(J22+J23)*$B$30 -> 36 | K30: =(K22+K23)*$B$30 -> 36 | L30: =(L22+L23)*$B$30 -> 36
A31: Employee Related Expenses | B31: 0.09 | C31: Total Sales | D31: =B31*D25 -> 177.06016 | E31: =B31*E25*1.05 -> 209.15232 | F31: =B31*F25*1.1 -> 243.45773 | G31: =B31*G25*1.2 -> 292.14927 | H31: =B31*H25*1.2 -> 318.70829 | I31: =B31*I25*1.25 -> 331.98781 | J31: =$B$31*J25*1.3 -> 345.26732 | K31: =$B$31*K25*1.35 -> 358.54683 | L31: =$B$31*L25*1.4 -> 371.82634 | P31: Increasing
A32: Power, Fuel & Water Charges | B32: 0.075 | C32: Total Sales | D32: =ROUND(B32*D25,2) -> 147.55 | E32: =B32*E25 -> 165.9939 | F32: =B32*F25 -> 184.43767 | G32: =B32*G25 -> 202.88144 | H32: =B32*H25 -> 221.3252 | I32: =B32*I25 -> 221.3252 | J32: =$B$32*J25 -> 221.3252 | K32: =$B$32*K25 -> 221.3252 | L32: =$B$32*L25 -> 221.3252
A33: Repair & Maintenance | B33: 0.005 | C33: Assets | D33: =depreciation!D147*0.5% -> 19.058351 | E33: =depreciation!E147*1% -> 33.594762 | F33: =depreciation!F147*1.25% -> 37.528526 | G33: =depreciation!G147*2.5% -> 64.002201 | H33: =depreciation!H147*2.5% -> 55.69735 | I33: =depreciation!I147*3% -> 56.570998 | J33: =depreciation!J147*3.5% -> 54.197705 | K33: =depreciation!K147*4% -> 47.852472 | L33: =depreciation!L147*4.75% -> 39.383093 | P33: Increasing
A34: Discount on Room Rentals | B34: 0.05 | C34: Room Sales | D34: =D20*B34 -> 73.365 | E34: =E20*B34*1.5 -> 123.80344 | F34: =F20*B34*2 -> 183.4125 | G34: =G20*B34*2.15 -> 216.88528 | H34: =H20*B34*2.25 -> 247.60688 | I34: =I20*B34*2.5 -> 275.11875 | J34: =J20*$B$34*2.5 -> 275.11875 | K34: =K20*$B$34*2.5 -> 275.11875 | L34: =L20*$B$34*2.5 -> 275.11875 | P34: Increasing | Q34: Max 25%
A35: Room Upkeep Exp. | B35: 0.04 | C35: Room Sales | D35: =B35*D20 -> 58.692 | E35: =B35*E20*1.25 -> 82.535625 | F35: =B35*F20*1.25 -> 91.70625 | G35: =B35*G20*1.25 -> 100.87688 | H35: =B35*H20*1.25 -> 110.0475 | I35: =B35*I20*1.25 -> 110.0475 | J35: =B35*J20*1.25 -> 110.0475 | K35: =B35*K20*1.25 -> 110.0475 | L35: =B35*L20*1.25 -> 110.0475 | P35: Increasing | Q35: Normal
A36: General Upkeep & Services | B36: 0.01 | C36: Total Sales | D36: =B36*D25 -> 19.673352 | E36: =B36*E25 -> 22.13252 | F36: =B36*F25*1.1 -> 27.050858 | G36: =B36*G25*1.2 -> 32.46103 | H36: =B36*H25*1.2 -> 35.412033 | I36: =B36*I25*1.2 -> 35.412033 | J36: =B36*J25*1.2 -> 35.412033 | K36: =B36*K25*1.2 -> 35.412033 | L36: =B36*L25*1.2 -> 35.412033 | P36: Increasing | Q36: Normal
A37: Administration Expenses | B37: 0.0225 | C37: Total Sales | D37: =B37*D25 -> 44.265041 | E37: =B37*E25*1.1 -> 54.777988 | F37: =B37*F25*1.1 -> 60.864431 | G37: =B37*G25*1.15 -> 69.994096 | H37: =B37*H25*1.2 -> 79.677074 | I37: =B37*I25*1.25 -> 82.996952 | J37: =B37*J25*1.3 -> 86.31683 | K37: =B37*K25*1.35 -> 89.636708 | L37: =B37*L25*1.4 -> 92.956586 | P37: Increasing
A38: Management expenses | B38: 0.025 | C38: Total Sales | D38: =B38*D25 -> 49.183379 | E38: =B38*E25*1.1 -> 60.864431 | F38: =B38*F25*1.1 -> 67.627146 | G38: =B38*G25*1.25 -> 84.533932 | H38: =B38*H25*1.25 -> 92.218835 | I38: =B38*I25*1.25 -> 92.218835 | J38: =B38*J25*1.25 -> 92.218835 | K38: =B38*K25*1.25 -> 92.218835 | L38: =B38*L25*1.25 -> 92.218835 | P38: Increasing | Q38: Normal
A39: Advertisement & Sales Promotion | B39: 0.0125 | C39: Total Sales | D39: =B39*D25 -> 24.591689 | E39: =B39*E25*1.5 -> 41.498476 | F39: =B39*F25*2 -> 61.479224 | G39: =B39*G25*2.5 -> 84.533932 | H39: =B39*H25*2.75 -> 101.44072 | I39: =B39*I25*3.5 -> 129.10637 | J39: =B39*J25*3.75 -> 138.32825 | K39: =B39*K25*4 -> 147.55014 | L39: =B39*L25*4.25 -> 156.77202 | P39: Increasing
A40: Insurance Charges
A41: Building | B41: 0.0033 | D41: =B41*'CAPITAL COST'!C14 -> 9.5004913 | E41: =D41 -> 9.5004913 | F41: =E41 -> 9.5004913 | G41: =F41 -> 9.5004913 | H41: =G41 -> 9.5004913 | I41: =H41 -> 9.5004913 | J41: =I41 -> 9.5004913 | K41: =J41 -> 9.5004913 | L41: =K41 -> 9.5004913 | V41: =B41*depreciation!D128 -> 10.488325 | W41: =B41*'CAPITAL COST'!D14 -> 9.5004913
A42: Plant & Equipment | B42: 0.005 | D42: =B42*'CAPITAL COST'!D20+(ASSETS!I82-ASSETS!I78+('details of fixed assets '!F145/100000+'details of fixed assets '!F146/100000))*B42 -> 3.6821262 | E42: =D42 -> 3.6821262 | F42: =E42 -> 3.6821262 | G42: =F42 -> 3.6821262 | H42: =G42 -> 3.6821262 | I42: =H42 -> 3.6821262 | J42: =I42 -> 3.6821262 | K42: =J42 -> 3.6821262 | L42: =K42 -> 3.6821262 | W42: =B42*('CAPITAL COST'!D20+'CAPITAL COST'!D16) -> 4.2141962
A43: Furniture & Accessories | B43: 0.0025 | D43: =B43*(SUM('details of fixed assets '!F138:F144))/100000 -> 0.38145 | E43: =D43 -> 0.38145 | F43: =E43 -> 0.38145 | G43: =F43 -> 0.38145 | H43: =G43 -> 0.38145 | I43: =H43 -> 0.38145 | J43: =I43 -> 0.38145 | K43: =J43 -> 0.38145 | L43: =K43 -> 0.38145
A44: Inventory | B44: 0.002 | D44: =+' wORKING CAPITAL'!E15*$B$44 -> 0.024 | E44: =+' wORKING CAPITAL'!F15*$B$44 -> 0.023922285 | F44: =+' wORKING CAPITAL'!G15*$B$44 -> 0.026530071 | G44: =+' wORKING CAPITAL'!H15*$B$44 -> 0.029477856 | H44: =+' wORKING CAPITAL'!I15*$B$44 -> 0.03891077 | I44: =+' wORKING CAPITAL'!J15*$B$44 -> 0.049522799 | J44: =+' wORKING CAPITAL'!K15*$B$44 -> 0.061313941 | K44: =+' wORKING CAPITAL'!L15*$B$44 -> 0.074284198 | L44: =+' wORKING CAPITAL'!M15*$B$44 -> 0.070746855
A45: Brokerage & Commission | B45: 0.005 | C45: Total Sales | D45: =B45*D25 -> 9.8366758 | E45: =B45*E25 -> 11.06626 | F45: =B45*F25*1.25 -> 15.369806 | G45: =B45*G25*1.75 -> 23.669501 | H45: =B45*H25*2 -> 29.510027 | I45: =B45*I25*2.5 -> 36.887534 | J45: =B45*J25*3 -> 44.265041 | K45: =B45*K25*3.5 -> 51.642548 | L45: =B45*L25*3.6 -> 53.118049 | U45: =MIN(2,#REF!,#REF!,#REF!,#REF!,#REF!,#REF!,#REF!,#REF!) -> #REF!
A46: Interest on Term Loan | D46: =Interest!I58 -> 240.1125 | E46: =Interest!I70 -> 217.7875 | F46: =Interest!I82 -> 186.675 | G46: =Interest!I94 -> 147.25 | H46: =Interest!I106 -> 99.0375 | I46: =Interest!I118 -> 45.125 | J46: =Interest!I130 -> 2.375 | K46: =Interest!I142 -> 0 | L46: =Interest!I154 -> 0
A47: Interest on Working Capital Loan | D47: =' wORKING CAPITAL'!E29 -> 0 | E47: =' wORKING CAPITAL'!F29 -> 0 | F47: =' wORKING CAPITAL'!G29 -> 0 | G47: =' wORKING CAPITAL'!H29 -> 0 | H47: =' wORKING CAPITAL'!I29 -> 0 | I47: =' wORKING CAPITAL'!J29 -> 0 | J47: =' wORKING CAPITAL'!K29 -> 0 | K47: =' wORKING CAPITAL'!L29 -> 0 | L47: =' wORKING CAPITAL'!M29 -> 0
A49: Depreciation | D49: =depreciation!D139 -> 452.19406 | E49: =depreciation!E139 -> 452.19406 | F49: =depreciation!F139 -> 452.19406 | G49: =depreciation!G139 -> 452.19406 | H49: =depreciation!H139 -> 452.19406 | I49: =depreciation!I139 -> 452.19406 | J49: =depreciation!J139 -> 452.19406 | K49: =depreciation!K139 -> 452.19406 | L49: =depreciation!L139 -> 452.19406
A51: Total Operating Costs | D51: =SUM(D29:D50) -> 1494.6603 | E51: =SUM(E29:E50) -> 1675.1697 | F51: =SUM(F29:F50) -> 1832.2609 | G51: =SUM(G29:G50) -> 2012.579 | H51: =SUM(H29:H50) -> 2104.719 | I51: =SUM(I29:I50) -> 2130.8452 | J51: =SUM(J29:J50) -> 2118.9325 | K51: =SUM(K29:K50) -> 2143.424 | L51: =SUM(L29:L50) -> 2162.2479
A55: Gross Profit | D55: =(D25-D51)-(D25*0.05) -> 374.30812 | E55: =(E25-E51)-(E25*0.05) -> 427.41975 | F55: =(F25-F51)-(F25*0.05) -> 503.94956 | G55: =(G25-G51)-(G25*0.05) -> 557.25253 | H55: =(H25-H51)-(H25*0.05) -> 698.73358 | I55: =(I25-I51)-(I25*0.05) -> 672.6074 | J55: =(J25-J51)-(J25*0.05) -> 684.52012 | K55: =(K25-K51)-(K25*0.05) -> 660.0286 | L55: =(L25-L51)-(L25*0.05) -> 641.20474
A57: PBIT | D57: =D55+D47+D46 -> 614.42062 | E57: =E55+E47+E46 -> 645.20725 | F57: =F55+F47+F46 -> 690.62456 | G57: =G55+G47+G46 -> 704.50253 | H57: =H55+H47+H46 -> 797.77108 | I57: =I55+I47+I46 -> 717.7324 | J57: =J55+J47+J46 -> 686.89512 | K57: =K55+K47+K46 -> 660.0286 | L57: =L55+L47+L46 -> 641.20474
A58: Provision For Tax being MAT | D58: 0 | E58: 0 | F58: ='iNCOME tAX cOMPUTATION'!F19 -> 129.1504 | G58: ='iNCOME tAX cOMPUTATION'!G19 -> 160.17411 | H58: ='iNCOME tAX cOMPUTATION'!H19 -> 192.91195 | I58: ='iNCOME tAX cOMPUTATION'!I19 -> 225.86516 | J58: ='iNCOME tAX cOMPUTATION'!J19 -> 263.37452 | K58: ='iNCOME tAX cOMPUTATION'!K19 -> 297.14223 | L58: ='iNCOME tAX cOMPUTATION'!L19 -> #VALUE!
A59: Profit After Tax | D59: =D55-D58 -> 374.30812 | E59: =E55-E58 -> 427.41975 | F59: =F55-F58 -> 374.79916 | G59: =G55-G58 -> 397.07843 | H59: =H55-H58 -> 505.82163 | I59: =I55-I58 -> 446.74223 | J59: =J55-J58 -> 421.1456 | K59: =K55-K58 -> 362.88636 | L59: =L55-L58 -> #VALUE!
A60: Cummulative Reserve | D60: =D59 -> 374.30812 | E60: =D60+E59 -> 801.72787 | F60: =E60+F59 -> 1176.527 | G60: =F60+G59 -> 1573.6055 | H60: =G60+H59 -> 2079.4271 | I60: =H60+I59 -> 2526.1693 | J60: =I60+J59 -> 2947.3149 | K60: =J60+K59 -> 3310.2013 | L60: =K60+L59 -> #VALUE!
A61: Cash Profit | D61: =D55+D49 -> 826.50218 | E61: =E55+E49 -> 879.61381 | F61: =F55+F49 -> 956.14362 | G61: =G55+G49 -> 1009.4466 | H61: =H55+H49 -> 1150.9276 | I61: =I55+I49 -> 1124.8015 | J61: =J55+J49 -> 1136.7142 | K61: =K55+K49 -> 1112.2227 | L61: =L55+L49 -> 1093.3988
A62: % of Cash Profit | D62: =D61/D25*100 -> 42.011254 | E62: =E61/E25*100 -> 39.743047 | F62: =F61/F25*100 -> 38.880762 | G62: =G61/G25*100 -> 37.31662 | H62: =H61/H25*100 -> 39.001239 | I62: =I61/I25*100 -> 38.115907 | J62: =J61/J25*100 -> 38.519591 | K62: =K61/K25*100 -> 37.689652 | L62: =L61/L25*100 -> 37.051772
A63: % of PAT | D63: =D59/D25*100 -> 19.026149 | E63: =E59/E25*100 -> 19.311843 | F63: =F59/F25*100 -> 15.240887 | G63: =G59/G25*100 -> 14.678958 | H63: =H59/H25*100 -> 17.14067 | I63: =I59/I25*100 -> 15.138659 | J63: =J59/J25*100 -> 14.271271 | K63: =K59/K25*100 -> 12.297053 | L63: =L59/L25*100 -> #VALUE!
A64: Retained Profit | D64: =D59 -> 374.30812 | E64: =E59 -> 427.41975 | F64: =F59 -> 374.79916 | G64: =G59 -> 397.07843 | H64: =H59 -> 505.82163 | I64: =I59 -> 446.74223 | J64: =J59 -> 421.1456 | K64: =K59 -> 362.88636 | L64: =L59 -> #VALUE!
A66: DSCR
A67: Cash Profit & Intt On T L | D67: =(D59+D49+D46) -> 1066.6147 | E67: =(E59+E49+E46) -> 1097.4013 | F67: =(F59+F49+F46) -> 1013.6682 | G67: =(G59+G49+G46) -> 996.52248 | H67: =(H59+H49+H46) -> 1057.0532 | I67: =(I59+I49+I46) -> 944.06129 | J67: =(J59+J49+J46) -> 875.71465 | K67: =(K59+K49+K46) -> 815.08042 | L67: =(L59+L49+L46) -> #VALUE!
A68: TL & Intt | D68: =#REF! -> #REF! | E68: =#REF! -> #REF! | F68: =#REF! -> #REF! | G68: =#REF! -> #REF! | H68: =#REF! -> #REF! | I68: =#REF! -> #REF! | J68: =#REF! -> #REF! | K68: =#REF! -> #REF! | L68: =#REF! -> #REF!
D69: =D67/D68 -> #REF! | E69: =E67/E68 -> #REF! | F69: =F67/F68 -> #REF! | G69: =G67/G68 -> #REF! | H69: =H67/H68 -> #REF! | I69: =I67/I68 -> #REF! | J69: =J67/J68 -> #REF! | K69: =K67/K68 -> #REF! | L69: =L67/L68 -> #VALUE!
D71: =AVERAGE(D69:K69) -> #REF!
D118: =D55+D49 -> 826.50218 | E118: =E55+E49 -> 879.61381 | F118: =F55+F49 -> 956.14362 | G118: =G55+G49 -> 1009.4466 | H118: =H55+H49 -> 1150.9276 | I118: =I55+I49 -> 1124.8015 | J118: =J55+J49 -> 1136.7142 | K118: =K55+K49 -> 1112.2227 | L118: =L55+L49 -> 1093.3988
D120: =D118/D25*100 -> 42.011254 | E120: =E118/E25*100 -> 39.743047 | F120: =F118/F25*100 -> 38.880762 | G120: =G118/G25*100 -> 37.31662 | H120: =H118/H25*100 -> 39.001239 | I120: =I118/I25*100 -> 38.115907 | J120: =J118/J25*100 -> 38.519591 | K120: =K118/K25*100 -> 37.689652 | L120: =L118/L25*100 -> 37.051772
D122: =D49+D46+D55 -> 1066.6147 | E122: =E49+E46+E55 -> 1097.4013 | F122: =F49+F46+F55 -> 1142.8186 | G122: =G49+G46+G55 -> 1156.6966 | H122: =H49+H46+H55 -> 1249.9651 | I122: =I49+I46+I55 -> 1169.9265 | J122: =J49+J46+J55 -> 1139.0892 | K122: =K49+K46+K55 -> 1112.2227 | L122: =L49+L46+L55 -> 1093.3988
D124: =D122/D25*100 -> 54.216216 | E124: =E122/E25*100 -> 49.583205 | F124: =F122/F25*100 -> 46.471741 | G124: =G122/G25*100 -> 42.76007 | H124: =H122/H25*100 -> 42.357302 | I124: =I122/I25*100 -> 39.645048 | J124: =J122/J25*100 -> 38.600072 | K124: =K122/K25*100 -> 37.689652 | L124: =L122/L25*100 -> 37.051772
D126: =D46+D49 -> 692.30656 | E126: =E46+E49 -> 669.98156 | F126: =F46+F49 -> 638.86906 | G126: =G46+G49 -> 599.44406 | H126: =H46+H49 -> 551.23156 | I126: =I46+I49 -> 497.31906 | J126: =J46+J49 -> 454.56906 | K126: =K46+K49 -> 452.19406 | L126: =L46+L49 -> 452.19406

Sheet BEP ANAYSIS_IV
F2: (30)
E4: ANNEXURE V
E5: Break Even Analysis
F6: Rs. In Lakhs
B7: Year | D7: Basis | E7: Year 1 | F7: Year 2 | G7: Year 3 | H7: Year 4 | I7: Year 5 | J7: Year 6 | K7: Year 7 | L7: Year 8 | M7: Year 9
B9: Gross Revenue Receipt | E9: ='P L _Case_IV'!D25 -> 1967.3352 | F9: ='P L _Case_IV'!E25 -> 2213.252 | G9: ='P L _Case_IV'!F25 -> 2459.1689 | H9: ='P L _Case_IV'!G25 -> 2705.0858 | I9: ='P L _Case_IV'!H25 -> 2951.0027 | J9: ='P L _Case_IV'!I25 -> 2951.0027 | K9: ='P L _Case_IV'!J25 -> 2951.0027 | L9: ='P L _Case_IV'!K25 -> 2951.0027 | M9: ='P L _Case_IV'!L25 -> 2951.0027
B11: VARIABLE COSTS
B14: TOTAL VARIABLE COSTS | E14: ='P L _Case_IV'!D51+'P L _Case_IV'!D58-E20 -> #REF! | F14: ='P L _Case_IV'!E51+'P L _Case_IV'!E58-F20 -> #REF! | G14: ='P L _Case_IV'!F51+'P L _Case_IV'!F58-G20 -> #REF! | H14: ='P L _Case_IV'!G51+'P L _Case_IV'!G58-H20 -> #REF! | I14: ='P L _Case_IV'!H51+'P L _Case_IV'!H58-I20 -> #REF! | J14: ='P L _Case_IV'!I51+'P L _Case_IV'!I58-J20 -> #REF! | K14: ='P L _Case_IV'!J51+'P L _Case_IV'!J58-K20 -> #REF! | L14: ='P L _Case_IV'!K51+'P L _Case_IV'!K58-L20 -> #REF! | M14: ='P L _Case_IV'!L51+'P L _Case_IV'!L58-M20 -> #VALUE!
B16: CONTRIBUTION | E16: =E9-E14 -> #REF! | F16: =F9-F14 -> #REF! | G16: =G9-G14 -> #REF! | H16: =H9-H14 -> #REF! | I16: =I9-I14 -> #REF! | J16: =J9-J14 -> #REF! | K16: =K9-K14 -> #REF! | L16: =L9-L14 -> #REF! | M16: =M9-M14 -> #VALUE!
B18: FIXED COSTS
B20: TOTAL FIXED COSTS | E20: =#REF! -> #REF! | F20: =#REF! -> #REF! | G20: =#REF! -> #REF! | H20: =#REF! -> #REF! | I20: =#REF! -> #REF! | J20: =#REF! -> #REF! | K20: =#REF! -> #REF! | L20: =#REF! -> #REF! | M20: =#REF! -> #REF!
B22: P/V Ratio | E22: =E16/E9*100 -> #REF! | F22: =F16/F9*100 -> #REF! | G22: =G16/G9*100 -> #REF! | H22: =H16/H9*100 -> #REF! | I22: =I16/I9*100 -> #REF! | J22: =J16/J9*100 -> #REF! | K22: =K16/K9*100 -> #REF! | L22: =L16/L9*100 -> #REF! | M22: =M16/M9*100 -> #VALUE!
B23: Break Even Sales | E23: =+E20/E22*100 -> #REF! | F23: =+F20/F22*100 -> #REF! | G23: =+G20/G22*100 -> #REF! | H23: =+H20/H22*100 -> #REF! | I23: =+I20/I22*100 -> #REF! | J23: =+J20/J22*100 -> #REF! | K23: =+K20/K22*100 -> #REF! | L23: =+L20/L22*100 -> #REF! | M23: =+M20/M22*100 -> #REF!
B24: Break Even Point Room Occupancy Achieved | E24: =+E23/E9*100 -> #REF! | F24: =+F23/F9*100 -> #REF! | G24: =+G23/G9*100 -> #REF! | H24: =+H23/H9*100 -> #REF! | I24: =+I23/I9*100 -> #REF! | J24: =+J23/J9*100 -> #REF! | K24: =+K23/K9*100 -> #REF! | L24: =+L23/L9*100 -> #REF! | M24: =+M23/M9*100 -> #REF!
B25: Average Break Even Point Room Occupancy Achieved | E25: =AVERAGE(E24:L24) -> #REF!
B26: Break Even Point Room Capacity | E26: =E23/SALESPROJECTION!E81*100 -> #REF! | F26: =F23/SALESPROJECTION!F81*100 -> #REF! | G26: =G23/SALESPROJECTION!G81*100 -> #REF! | H26: =H23/SALESPROJECTION!H81*100 -> #REF! | I26: =I23/SALESPROJECTION!I81*100 -> #REF! | J26: =J23/SALESPROJECTION!J81*100 -> #REF! | K26: =K23/SALESPROJECTION!K81*100 -> #REF! | L26: =L23/SALESPROJECTION!L81*100 -> #REF! | M26: =M23/SALESPROJECTION!M81*100 -> #REF!
B27: Average Break Even Point Room Capacity | E27: =AVERAGE(E26:L26) -> #REF!
B28: Cash Break Even Point Room Capacity | E28: =(((E20-('P L _Case_II'!D49*0.75))/E22*100/SALESPROJECTION!E81*100)) -> #REF! | F28: =(((F20-('P L _Case_II'!E49*0.75))/F22*100/SALESPROJECTION!F81*100)) -> #REF! | G28: =(((G20-('P L _Case_II'!F49*0.75))/G22*100/SALESPROJECTION!G81*100)) -> #REF! | H28: =(((H20-('P L _Case_II'!G49*0.75))/H22*100/SALESPROJECTION!H81*100)) -> #REF! | I28: =(((I20-('P L _Case_II'!H49*0.75))/I22*100/SALESPROJECTION!I81*100)) -> #REF! | J28: =(((J20-('P L _Case_II'!I49*0.75))/J22*100/SALESPROJECTION!J81*100)) -> #REF! | K28: =(((K20-('P L _Case_II'!J49*0.75))/K22*100/SALESPROJECTION!K81*100)) -> #REF! | L28: =(((L20-('P L _Case_II'!K49*0.75))/L22*100/SALESPROJECTION!L81*100)) -> #REF! | M28: =(((M20-('P L _Case_II'!L49*0.75))/M22*100/SALESPROJECTION!M81*100)) -> #REF!
B29: Average Cash Break Even Point Room Capacity | E29: =AVERAGE(E28:L28) -> #REF!
E32: =E20+E14 -> #REF! | F32: =F20+F14 -> #REF! | G32: =G20+G14 -> #REF! | H32: =H20+H14 -> #REF! | I32: =I20+I14 -> #REF! | J32: =J20+J14 -> #REF! | K32: =K20+K14 -> #REF! | L32: =L20+L14 -> #REF! | M32: =M20+M14 -> #REF!
E33: =E32-'P L _Case_IV'!D51-'P L _Case_IV'!D58 -> #REF! | F33: =F32-'P L _Case_IV'!E51-'P L _Case_IV'!E58 -> #REF! | G33: =G32-'P L _Case_IV'!F51-'P L _Case_IV'!F58 -> #REF! | H33: =H32-'P L _Case_IV'!G51-'P L _Case_IV'!G58 -> #REF! | I33: =I32-'P L _Case_IV'!H51-'P L _Case_IV'!H58 -> #REF! | J33: =J32-'P L _Case_IV'!I51-'P L _Case_IV'!I58 -> #REF! | K33: =K32-'P L _Case_IV'!J51-'P L _Case_IV'!J58 -> #REF! | L33: =L32-'P L _Case_IV'!K51-'P L _Case_IV'!K58 -> #REF! | M33: =M32-'P L _Case_IV'!L51-'P L _Case_IV'!L58 -> #REF!

Sheet IRR_CASE_IV
F2: (34)
E4: ANNEXURE IX
D5: Internal Rate of Return
E6: Rs. In Lakhs
B8: Year | D8: Construction | E8: Year 1 | F8: Year 2 | G8: Year 3 | H8: Year 4 | I8: Year 5 | J8: Year 6 | K8: Year 7 | L8: Year 8 | M8: Year 9
B10: CASH INFLOW | Q10: 0.12266
B12: Profit After Tax | E12: ='P L _Case_IV'!D59 -> 275.94136 | F12: ='P L _Case_IV'!E59 -> 316.75715 | G12: ='P L _Case_IV'!F59 -> 380.99112 | H12: ='P L _Case_IV'!G59 -> 421.99824 | I12: ='P L _Case_IV'!H59 -> 396.85388 | J12: ='P L _Case_IV'!I59 -> 299.1921 | K12: ='P L _Case_IV'!J59 -> 273.59546 | L12: ='P L _Case_IV'!K59 -> 215.33623 | M12: ='P L _Case_IV'!L59 -> #VALUE!
B13: Depreciation | E13: ='P L '!D53 -> 452.19406 | F13: ='P L '!E53 -> 452.19406 | G13: ='P L '!F53 -> 452.19406 | H13: ='P L '!G53 -> 452.19406 | I13: ='P L '!H53 -> 452.19406 | J13: ='P L '!I53 -> 452.19406 | K13: ='P L '!J53 -> 452.19406 | L13: ='P L '!K53 -> 452.19406 | M13: ='P L '!L53 -> 452.19406
B14: Interest on Term Loan | E14: ='P L '!D50 -> 254.71875 | F14: ='P L '!E50 -> 240.1125 | G14: ='P L '!F50 -> 217.7875 | H14: ='P L '!G50 -> 186.675 | I14: ='P L '!H50 -> 147.25 | J14: ='P L '!I50 -> 99.0375 | K14: ='P L '!J50 -> 45.125 | L14: ='P L '!K50 -> 2.375 | M14: ='P L '!L50 -> 0
B15: Residual Value of Fixed Assets | L15: =0.5*'B S '!L13 -> 598.15591 | N15: *
B17: TOTAL CASH INFLOW | D17: =SUM(D10:D15) -> 0 | E17: =SUM(E10:E15) -> 982.85417 | F17: =SUM(F10:F15) -> 1009.0637 | G17: =SUM(G10:G15) -> 1050.9727 | H17: =SUM(H10:H15) -> 1060.8673 | I17: =SUM(I10:I15) -> 996.29794 | J17: =SUM(J10:J15) -> 850.42366 | K17: =SUM(K10:K15) -> 770.91452 | ... M17: =SUM(M10:M15) -> #VALUE!
B19: CASH OUTFLOWS
B21: Capital Expenditure | D21: ='CAPITAL COST'!D36+'CAPITAL COST'!D34 -> 4263.8643 | E21: 0 | F21: 0 | G21: 0 | H21: 0 | I21: 0 | J21: 0 | K21: 0 | L21: 0 | M21: 0
B23: TOTAL CASH OUTFLOW | D23: =SUM(D19:D22) -> 4263.8643 | E23: =SUM(E19:E22) -> 0 | F23: =SUM(F19:F22) -> 0 | G23: =SUM(G19:G22) -> 0 | H23: =SUM(H19:H22) -> 0 | I23: =SUM(I19:I22) -> 0 | J23: =SUM(J19:J22) -> 0 | K23: =SUM(K19:K22) -> 0 | ... M23: =SUM(M19:M22) -> 0
B25: NET CASH FLOW | D25: =D17-D23 -> -4263.8643 | E25: =E17-E23 -> 982.85417 | F25: =F17-F23 -> 1009.0637 | G25: =G17-G23 -> 1050.9727 | H25: =H17-H23 -> 1060.8673 | I25: =I17-I23 -> 996.29794 | J25: =J17-J23 -> 850.42366 | K25: =K17-K23 -> 770.91452 | ... M25: =M17-M23 -> #VALUE!
B27: Discounting Factor | D27: 1 | E27: 1 | F27: =1/(1+Q10) -> 0.89074163 | G27: =+F27/(1+$Q$10) -> 0.79342065 | H27: =+G27/(1+$Q$10) -> 0.70673281 | I27: =+H27/(1+$Q$10) -> 0.62951633 | J27: =+I27/(1+$Q$10) -> 0.56073641 | K27: =+J27/(1+$Q$10) -> 0.49947126 | L27: =+K27/(1+$Q$10) -> 0.44489985 | M27: =+L27/(1+$Q$10) -> 0.39629082
B28: Present Value | D28: =D25*D27 -> -4263.8643 | E28: =E25*E27 -> 982.85417 | F28: =F25*F27 -> 898.81505 | G28: =G25*G27 -> 833.86343 | H28: =H25*H27 -> 749.74972 | I28: =I25*I27 -> 627.18583 | J28: =J25*J27 -> 476.86351 | K28: =K25*K27 -> 385.04965 | ... M28: =M25*M27 -> #VALUE!
B31: Net Present Value (Rs.) | E31: =SUM(D28:L28) -> 1254.6773
B33: The Internal Rate of Return is | E33: =Q10 -> 0.12266
B36: * Residual value of fixed assets has been considered at 50% of Book WDV

Sheet P  L _Case_IV
D2: (28)
D4: ANNEXURE III
C5: Projected Profitability
J6: Rs. In Lacs
A8: Year | D8: 1 | E8: 2 | F8: 3 | G8: 4 | H8: 5 | I8: 6 | J8: 7 | K8: 8 | L8: 9
A10: Room Charges | D10: =SALESPROJECTION!E74 -> 3668.25 | E10: =SALESPROJECTION!F74 -> 3668.25 | F10: =SALESPROJECTION!G74 -> 3668.25 | G10: =SALESPROJECTION!H74 -> 3668.25 | H10: =SALESPROJECTION!I74 -> 3668.25 | I10: =SALESPROJECTION!J74 -> 3668.25 | J10: =SALESPROJECTION!K74 -> 3668.25 | K10: =SALESPROJECTION!L74 -> 3668.25 | L10: =SALESPROJECTION!M74 -> 3668.25
A11: F & B Sales | D11: =SALESPROJECTION!E75 -> 884.33569 | E11: =SALESPROJECTION!F75 -> 884.33569 | F11: =SALESPROJECTION!G75 -> 884.33569 | G11: =SALESPROJECTION!H75 -> 884.33569 | H11: =SALESPROJECTION!I75 -> 884.33569 | I11: =SALESPROJECTION!J75 -> 884.33569 | J11: =SALESPROJECTION!K75 -> 884.33569 | K11: =SALESPROJECTION!L75 -> 884.33569 | L11: =SALESPROJECTION!M75 -> 884.33569
A12: Banquet Hall Receipts | D12: =SALESPROJECTION!E76 -> 195 | E12: =SALESPROJECTION!F76 -> 195 | F12: =SALESPROJECTION!G76 -> 195 | G12: =SALESPROJECTION!H76 -> 195 | H12: =SALESPROJECTION!I76 -> 195 | I12: =SALESPROJECTION!J76 -> 195 | J12: =SALESPROJECTION!K76 -> 195 | K12: =SALESPROJECTION!L76 -> 195 | L12: =SALESPROJECTION!M76 -> 195
A13: Conference Hall Receipts | D13: =SALESPROJECTION!E79 -> 45 | E13: =SALESPROJECTION!F79 -> 45 | F13: =SALESPROJECTION!G79 -> 45 | G13: =SALESPROJECTION!H79 -> 45 | H13: =SALESPROJECTION!I79 -> 45 | I13: =SALESPROJECTION!J79 -> 45 | J13: =SALESPROJECTION!K79 -> 45 | K13: =SALESPROJECTION!L79 -> 45 | L13: =SALESPROJECTION!M79 -> 45
A14: Other Income | D14: =SALESPROJECTION!E80 -> 125.7522 | E14: =SALESPROJECTION!F80 -> 125.7522 | F14: =SALESPROJECTION!G80 -> 125.7522 | G14: =SALESPROJECTION!H80 -> 125.7522 | H14: =SALESPROJECTION!I80 -> 125.7522 | I14: =SALESPROJECTION!J80 -> 125.7522 | J14: =SALESPROJECTION!K80 -> 125.7522 | K14: =SALESPROJECTION!L80 -> 125.7522 | L14: =SALESPROJECTION!M80 -> 125.7522
A15: Gross Revenue Receipt | D15: =SUM(D10:D14) -> 4918.3379 | E15: =SUM(E10:E14) -> 4918.3379 | F15: =SUM(F10:F14) -> 4918.3379 | G15: =SUM(G10:G14) -> 4918.3379 | H15: =SUM(H10:H14) -> 4918.3379 | I15: =SUM(I10:I14) -> 4918.3379 | J15: =SUM(J10:J14) -> 4918.3379 | K15: =SUM(K10:K14) -> 4918.3379 | L15: =SUM(L10:L14) -> 4918.3379 | T15: =E15-SALESPROJECTION!F81 -> -111.75 | U15: =F15-SALESPROJECTION!G81 -> -111.75 | V15: =G15-SALESPROJECTION!H81 -> -111.75 | W15: =H15-SALESPROJECTION!I81 -> -111.75 | X15: =I15-SALESPROJECTION!J81 -> -111.75 | Y15: =J15-SALESPROJECTION!K81 -> -111.75
A16: Envisaged Occupancy | D16: =40% -> 0.4 | E16: =D16+0.05 -> 0.45 | F16: =E16+0.05 -> 0.5 | G16: =F16+0.05 -> 0.55 | H16: =G16+5% -> 0.6 | I16: =H16 -> 0.6 | J16: =I16 -> 0.6 | K16: =J16 -> 0.6 | L16: =K16 -> 0.6
A18: Projected Sales
A20: Room Sales | D20: =D16*D10 -> 1467.3 | E20: =E16*E10 -> 1650.7125 | F20: =F16*F10 -> 1834.125 | G20: =G16*G10 -> 2017.5375 | H20: =H16*H10 -> 2200.95 | I20: =I16*I10 -> 2200.95 | J20: =J16*J10 -> 2200.95 | K20: =K16*K10 -> 2200.95 | L20: =L16*L10 -> 2200.95
A21: F & B Sales | D21: =$D$16*D11 -> 353.73428 | E21: =$E$16*E11 -> 397.95106 | F21: =$F$16*F11 -> 442.16784 | G21: =$G$16*G11 -> 486.38463 | H21: =$H$16*H11 -> 530.60141 | I21: =$I$16*I11 -> 530.60141 | J21: =$J$16*J11 -> 530.60141 | K21: =$K$16*K11 -> 530.60141 | L21: =$K$16*L11 -> 530.60141
A22: Banquet Hall Receipts | D22: =$D$16*D12 -> 78 | E22: =$E$16*E12 -> 87.75 | F22: =$F$16*F12 -> 97.5 | G22: =$G$16*G12 -> 107.25 | H22: =$H$16*H12 -> 117 | I22: =$I$16*I12 -> 117 | J22: =$J$16*J12 -> 117 | K22: =$K$16*K12 -> 117 | L22: =$K$16*L12 -> 117
A23: Conference Hall Receipts | D23: =$D$16*D13 -> 18 | E23: =$E$16*E13 -> 20.25 | F23: =$F$16*F13 -> 22.5 | G23: =$G$16*G13 -> 24.75 | H23: =$H$16*H13 -> 27 | I23: =$I$16*I13 -> 27 | J23: =$J$16*J13 -> 27 | K23: =$K$16*K13 -> 27 | L23: =$K$16*L13 -> 27
A24: Other Income | D24: =D16*D14 -> 50.300879 | E24: =E16*E14 -> 56.588489 | F24: =F16*F14 -> 62.876099 | G24: =G16*G14 -> 69.163708 | H24: =H16*H14 -> 75.451318 | I24: =I16*I14 -> 75.451318 | J24: =J16*J14 -> 75.451318 | K24: =K16*K14 -> 75.451318 | L24: =L16*L14 -> 75.451318
A25: Total Projected Sales | D25: =SUM(D20:D24) -> 1967.3352 | E25: =SUM(E20:E24) -> 2213.252 | F25: =SUM(F20:F24) -> 2459.1689 | G25: =SUM(G20:G24) -> 2705.0858 | H25: =SUM(H20:H24) -> 2951.0027 | I25: =SUM(I20:I24) -> 2951.0027 | J25: =SUM(J20:J24) -> 2951.0027 | K25: =SUM(K20:K24) -> 2951.0027 | L25: =SUM(L20:L24) -> 2951.0027
A27: Revenue Expenses | B27: As | C27: of
A29: Food & Beverages Cost | B29: 0.4 | C29: F & B sales | D29: =ROUND(B29*D21,2) -> 141.49 | E29: =B29*E21 -> 159.18042 | F29: =B29*F21 -> 176.86714 | G29: =B29*G21 -> 194.55385 | H29: =B29*H21 -> 212.24057 | I29: =B29*I21 -> 212.24057 | J29: =$B$29*J21 -> 212.24057 | K29: =$B$29*K21 -> 212.24057 | L29: =$B$29*L21 -> 212.24057
A30: Banquet & Conference Hall Expenses | B30: 0.25 | C30: B & C Receipts | D30: =(D22+D23)*$B$30 -> 24 | E30: =(E22+E23)*$B$30 -> 27 | F30: =(F22+F23)*$B$30 -> 30 | G30: =(G22+G23)*$B$30 -> 33 | H30: =(H22+H23)*$B$30 -> 36 | I30: =(I22+I23)*$B$30 -> 36 | J30: =(J22+J23)*$B$30 -> 36 | K30: =(K22+K23)*$B$30 -> 36 | L30: =(L22+L23)*$B$30 -> 36
A31: Employee Related Expenses | B31: 0.09 | C31: Total Sales | D31: =B31*D25 -> 177.06016 | E31: =B31*E25*1.05 -> 209.15232 | F31: =B31*F25*1.1 -> 243.45773 | G31: =B31*G25*1.2 -> 292.14927 | H31: =B31*H25*1.2 -> 318.70829 | I31: =B31*I25*1.25 -> 331.98781 | J31: =$B$31*J25*1.3 -> 345.26732 | K31: =$B$31*K25*1.35 -> 358.54683 | L31: =$B$31*L25*1.4 -> 371.82634 | P31: Increasing
A32: Power, Fuel & Water Charges | B32: 0.075 | C32: Total Sales | D32: =ROUND(B32*D25,2) -> 147.55 | E32: =B32*E25 -> 165.9939 | F32: =B32*F25 -> 184.43767 | G32: =B32*G25 -> 202.88144 | H32: =B32*H25 -> 221.3252 | I32: =B32*I25 -> 221.3252 | J32: =$B$32*J25 -> 221.3252 | K32: =$B$32*K25 -> 221.3252 | L32: =$B$32*L25 -> 221.3252
A33: Repair & Maintenance | B33: 0.005 | C33: Assets | D33: =depreciation!D147*0.5% -> 19.058351 | E33: =depreciation!E147*1% -> 33.594762 | F33: =depreciation!F147*1.25% -> 37.528526 | G33: =depreciation!G147*2.5% -> 64.002201 | H33: =depreciation!H147*2.5% -> 55.69735 | I33: =depreciation!I147*3% -> 56.570998 | J33: =depreciation!J147*3.5% -> 54.197705 | K33: =depreciation!K147*4% -> 47.852472 | L33: =depreciation!L147*4.75% -> 39.383093 | P33: Increasing
A34: Discount on Room Rentals | B34: 0.05 | C34: Room Sales | D34: =D20*B34 -> 73.365 | E34: =E20*B34*1.5 -> 123.80344 | F34: =F20*B34*2 -> 183.4125 | G34: =G20*B34*2.15 -> 216.88528 | H34: =H20*B34*2.25 -> 247.60688 | I34: =I20*B34*2.5 -> 275.11875 | J34: =J20*$B$34*2.5 -> 275.11875 | K34: =K20*$B$34*2.5 -> 275.11875 | L34: =L20*$B$34*2.5 -> 275.11875 | P34: Increasing | Q34: Max 25%
A35: Room Upkeep Exp. | B35: 0.04 | C35: Room Sales | D35: =B35*D20 -> 58.692 | E35: =B35*E20*1.25 -> 82.535625 | F35: =B35*F20*1.25 -> 91.70625 | G35: =B35*G20*1.25 -> 100.87688 | H35: =B35*H20*1.25 -> 110.0475 | I35: =B35*I20*1.25 -> 110.0475 | J35: =B35*J20*1.25 -> 110.0475 | K35: =B35*K20*1.25 -> 110.0475 | L35: =B35*L20*1.25 -> 110.0475 | P35: Increasing | Q35: Normal
A36: General Upkeep & Services | B36: 0.01 | C36: Total Sales | D36: =B36*D25 -> 19.673352 | E36: =B36*E25 -> 22.13252 | F36: =B36*F25*1.1 -> 27.050858 | G36: =B36*G25*1.2 -> 32.46103 | H36: =B36*H25*1.2 -> 35.412033 | I36: =B36*I25*1.2 -> 35.412033 | J36: =B36*J25*1.2 -> 35.412033 | K36: =B36*K25*1.2 -> 35.412033 | L36: =B36*L25*1.2 -> 35.412033 | P36: Increasing | Q36: Normal
A37: Administration Expenses | B37: 0.0225 | C37: Total Sales | D37: =B37*D25 -> 44.265041 | E37: =B37*E25*1.1 -> 54.777988 | F37: =B37*F25*1.1 -> 60.864431 | G37: =B37*G25*1.15 -> 69.994096 | H37: =B37*H25*1.2 -> 79.677074 | I37: =B37*I25*1.25 -> 82.996952 | J37: =B37*J25*1.3 -> 86.31683 | K37: =B37*K25*1.35 -> 89.636708 | L37: =B37*L25*1.4 -> 92.956586 | P37: Increasing
A38: Management expenses | B38: 0.025 | C38: Total Sales | D38: =B38*D25 -> 49.183379 | E38: =B38*E25*1.1 -> 60.864431 | F38: =B38*F25*1.1 -> 67.627146 | G38: =B38*G25*1.25 -> 84.533932 | H38: =B38*H25*1.25 -> 92.218835 | I38: =B38*I25*1.25 -> 92.218835 | J38: =B38*J25*1.25 -> 92.218835 | K38: =B38*K25*1.25 -> 92.218835 | L38: =B38*L25*1.25 -> 92.218835 | P38: Increasing | Q38: Normal
A39: Advertisement & Sales Promotion | B39: 0.0125 | C39: Total Sales | D39: =B39*D25 -> 24.591689 | E39: =B39*E25*1.5 -> 41.498476 | F39: =B39*F25*2 -> 61.479224 | G39: =B39*G25*2.5 -> 84.533932 | H39: =B39*H25*2.75 -> 101.44072 | I39: =B39*I25*3.5 -> 129.10637 | J39: =B39*J25*3.75 -> 138.32825 | K39: =B39*K25*4 -> 147.55014 | L39: =B39*L25*4.25 -> 156.77202 | P39: Increasing
A40: Insurance Charges
A41: Building | B41: 0.0033 | D41: =B41*'CAPITAL COST'!C14 -> 9.5004913 | E41: =D41 -> 9.5004913 | F41: =E41 -> 9.5004913 | G41: =F41 -> 9.5004913 | H41: =G41 -> 9.5004913 | I41: =H41 -> 9.5004913 | J41: =I41 -> 9.5004913 | K41: =J41 -> 9.5004913 | L41: =K41 -> 9.5004913 | V41: =B41*depreciation!D128 -> 10.488325 | W41: =B41*'CAPITAL COST'!D14 -> 9.5004913
A42: Plant & Equipment | B42: 0.005 | D42: =B42*'CAPITAL COST'!D20+(ASSETS!I82-ASSETS!I78+('details of fixed assets '!F145/100000+'details of fixed assets '!F146/100000))*B42 -> 3.6821262 | E42: =D42 -> 3.6821262 | F42: =E42 -> 3.6821262 | G42: =F42 -> 3.6821262 | H42: =G42 -> 3.6821262 | I42: =H42 -> 3.6821262 | J42: =I42 -> 3.6821262 | K42: =J42 -> 3.6821262 | L42: =K42 -> 3.6821262 | W42: =B42*('CAPITAL COST'!D20+'CAPITAL COST'!D16) -> 4.2141962
A43: Furniture & Accessories | B43: 0.0025 | D43: =B43*(SUM('details of fixed assets '!F138:F144))/100000 -> 0.38145 | E43: =D43 -> 0.38145 | F43: =E43 -> 0.38145 | G43: =F43 -> 0.38145 | H43: =G43 -> 0.38145 | I43: =H43 -> 0.38145 | J43: =I43 -> 0.38145 | K43: =J43 -> 0.38145 | L43: =K43 -> 0.38145
A44: Inventory | B44: 0.002 | D44: =+' wORKING CAPITAL'!E15*$B$44 -> 0.024 | E44: =+' wORKING CAPITAL'!F15*$B$44 -> 0.023922285 | F44: =+' wORKING CAPITAL'!G15*$B$44 -> 0.026530071 | G44: =+' wORKING CAPITAL'!H15*$B$44 -> 0.029477856 | H44: =+' wORKING CAPITAL'!I15*$B$44 -> 0.03891077 | I44: =+' wORKING CAPITAL'!J15*$B$44 -> 0.049522799 | J44: =+' wORKING CAPITAL'!K15*$B$44 -> 0.061313941 | K44: =+' wORKING CAPITAL'!L15*$B$44 -> 0.074284198 | L44: =+' wORKING CAPITAL'!M15*$B$44 -> 0.070746855
A45: Brokerage & Commission | B45: 0.005 | C45: Total Sales | D45: =B45*D25 -> 9.8366758 | E45: =B45*E25 -> 11.06626 | F45: =B45*F25*1.25 -> 15.369806 | G45: =B45*G25*1.75 -> 23.669501 | H45: =B45*H25*2 -> 29.510027 | I45: =B45*I25*2.5 -> 36.887534 | J45: =B45*J25*3 -> 44.265041 | K45: =B45*K25*3.5 -> 51.642548 | L45: =B45*L25*3.6 -> 53.118049 | U45: =MIN(2,#REF!,#REF!,#REF!,#REF!,#REF!,#REF!,#REF!,#REF!) -> #REF!
A46: Interest on Term Loan | D46: =Interest!I58 -> 240.1125 | E46: =Interest!I70 -> 217.7875 | F46: =Interest!I82 -> 186.675 | G46: =Interest!I94 -> 147.25 | H46: =Interest!I106 -> 99.0375 | I46: =Interest!I118 -> 45.125 | J46: =Interest!I130 -> 2.375 | K46: =Interest!I142 -> 0 | L46: =Interest!I154 -> 0
A47: Interest on Working Capital Loan | D47: =' wORKING CAPITAL'!E29 -> 0 | E47: =' wORKING CAPITAL'!F29 -> 0 | F47: =' wORKING CAPITAL'!G29 -> 0 | G47: =' wORKING CAPITAL'!H29 -> 0 | H47: =' wORKING CAPITAL'!I29 -> 0 | I47: =' wORKING CAPITAL'!J29 -> 0 | J47: =' wORKING CAPITAL'!K29 -> 0 | K47: =' wORKING CAPITAL'!L29 -> 0 | L47: =' wORKING CAPITAL'!M29 -> 0
A49: Depreciation | D49: =depreciation!D139 -> 452.19406 | E49: =depreciation!E139 -> 452.19406 | F49: =depreciation!F139 -> 452.19406 | G49: =depreciation!G139 -> 452.19406 | H49: =depreciation!H139 -> 452.19406 | I49: =depreciation!I139 -> 452.19406 | J49: =depreciation!J139 -> 452.19406 | K49: =depreciation!K139 -> 452.19406 | L49: =depreciation!L139 -> 452.19406
A51: Total Operating Costs | D51: =SUM(D29:D50) -> 1494.6603 | E51: =SUM(E29:E50) -> 1675.1697 | F51: =SUM(F29:F50) -> 1832.2609 | G51: =SUM(G29:G50) -> 2012.579 | H51: =SUM(H29:H50) -> 2104.719 | I51: =SUM(I29:I50) -> 2130.8452 | J51: =SUM(J29:J50) -> 2118.9325 | K51: =SUM(K29:K50) -> 2143.424 | L51: =SUM(L29:L50) -> 2162.2479
A55: Gross Profit | D55: =(D25-D51)-(D25*0.1) -> 275.94136 | E55: =(E25-E51)-(E25*0.1) -> 316.75715 | F55: =(F25-F51)-(F25*0.1) -> 380.99112 | G55: =(G25-G51)-(G25*0.1) -> 421.99824 | H55: =(H25-H51)-(H25*0.1) -> 551.18344 | I55: =(I25-I51)-(I25*0.1) -> 525.05726 | J55: =(J25-J51)-(J25*0.1) -> 536.96998 | K55: =(K25-K51)-(K25*0.1) -> 512.47846 | L55: =(L25-L51)-(L25*0.1) -> 493.6546
A57: PBIT | D57: =D55+D47+D46 -> 516.05386 | E57: =E55+E47+E46 -> 534.54465 | F57: =F55+F47+F46 -> 567.66612 | G57: =G55+G47+G46 -> 569.24824 | H57: =H55+H47+H46 -> 650.22094 | I57: =I55+I47+I46 -> 570.18226 | J57: =J55+J47+J46 -> 539.34498 | K57: =K55+K47+K46 -> 512.47846 | L57: =L55+L47+L46 -> 493.6546
A58: Provision For Tax being MAT | D58: 0 | E58: 0 | F58: 0 | G58: 0 | H58: ='iNCOME tAX cOMPUTATION'!H19*0.8 -> 154.32956 | I58: ='iNCOME tAX cOMPUTATION'!I19 -> 225.86516 | J58: ='iNCOME tAX cOMPUTATION'!J19 -> 263.37452 | K58: ='iNCOME tAX cOMPUTATION'!K19 -> 297.14223 | L58: ='iNCOME tAX cOMPUTATION'!L19 -> #VALUE!
A59: Profit After Tax | D59: =D55-D58 -> 275.94136 | E59: =E55-E58 -> 316.75715 | F59: =F55-F58 -> 380.99112 | G59: =G55-G58 -> 421.99824 | H59: =H55-H58 -> 396.85388 | I59: =I55-I58 -> 299.1921 | J59: =J55-J58 -> 273.59546 | K59: =K55-K58 -> 215.33623 | L59: =L55-L58 -> #VALUE!
A60: Cummulative Reserve | D60: =D59 -> 275.94136 | E60: =D60+E59 -> 592.69851 | F60: =E60+F59 -> 973.68962 | G60: =F60+G59 -> 1395.6879 | H60: =G60+H59 -> 1792.5417 | I60: =H60+I59 -> 2091.7338 | J60: =I60+J59 -> 2365.3293 | K60: =J60+K59 -> 2580.6655 | L60: =K60+L59 -> #VALUE!
A61: Cash Profit | D61: =D55+D49 -> 728.13542 | E61: =E55+E49 -> 768.95121 | F61: =F55+F49 -> 833.18518 | G61: =G55+G49 -> 874.1923 | H61: =H55+H49 -> 1003.3775 | I61: =I55+I49 -> 977.25132 | J61: =J55+J49 -> 989.16404 | K61: =K55+K49 -> 964.67252 | L61: =L55+L49 -> 945.84866
A62: % of Cash Profit | D62: =D61/D25*100 -> 37.011254 | E62: =E61/E25*100 -> 34.743047 | F62: =F61/F25*100 -> 33.880762 | G62: =G61/G25*100 -> 32.31662 | H62: =H61/H25*100 -> 34.001239 | I62: =I61/I25*100 -> 33.115907 | J62: =J61/J25*100 -> 33.519591 | K62: =K61/K25*100 -> 32.689652 | L62: =L61/L25*100 -> 32.051772
A63: % of PAT | D63: =D59/D25*100 -> 14.026149 | E63: =E59/E25*100 -> 14.311843 | F63: =F59/F25*100 -> 15.492678 | G63: =G59/G25*100 -> 15.600179 | H63: =H59/H25*100 -> 13.448103 | I63: =I59/I25*100 -> 10.138659 | J63: =J59/J25*100 -> 9.2712709 | K63: =K59/K25*100 -> 7.2970528 | L63: =L59/L25*100 -> #VALUE!
A64: Retained Profit | D64: =D59 -> 275.94136 | E64: =E59 -> 316.75715 | F64: =F59 -> 380.99112 | G64: =G59 -> 421.99824 | H64: =H59 -> 396.85388 | I64: =I59 -> 299.1921 | J64: =J59 -> 273.59546 | K64: =K59 -> 215.33623 | L64: =L59 -> #VALUE!
A66: DSCR
A67: Cash Profit & Intt On T L | D67: =(D59+D49+D46) -> 968.24792 | E67: =(E59+E49+E46) -> 986.73871 | F67: =(F59+F49+F46) -> 1019.8602 | G67: =(G59+G49+G46) -> 1021.4423 | H67: =(H59+H49+H46) -> 948.08544 | I67: =(I59+I49+I46) -> 796.51116 | J67: =(J59+J49+J46) -> 728.16452 | K67: =(K59+K49+K46) -> 667.53029 | L67: =(L59+L49+L46) -> #VALUE!
A68: TL & Intt | D68: =#REF! -> #REF! | E68: =#REF! -> #REF! | F68: =#REF! -> #REF! | G68: =#REF! -> #REF! | H68: =#REF! -> #REF! | I68: =#REF! -> #REF! | J68: =#REF! -> #REF! | K68: =#REF! -> #REF! | L68: =#REF! -> #REF!
D69: =D67/D68 -> #REF! | E69: =E67/E68 -> #REF! | F69: =F67/F68 -> #REF! | G69: =G67/G68 -> #REF! | H69: =H67/H68 -> #REF! | I69: =I67/I68 -> #REF! | J69: =J67/J68 -> #REF! | K69: =K67/K68 -> #REF! | L69: =L67/L68 -> #VALUE!
D71: =AVERAGE(D69:K69) -> #REF!
D118: =D55+D49 -> 728.13542 | E118: =E55+E49 -> 768.95121 | F118: =F55+F49 -> 833.18518 | G118: =G55+G49 -> 874.1923 | H118: =H55+H49 -> 1003.3775 | I118: =I55+I49 -> 977.25132 | J118: =J55+J49 -> 989.16404 | K118: =K55+K49 -> 964.67252 | L118: =L55+L49 -> 945.84866
D120: =D118/D25*100 -> 37.011254 | E120: =E118/E25*100 -> 34.743047 | F120: =F118/F25*100 -> 33.880762 | G120: =G118/G25*100 -> 32.31662 | H120: =H118/H25*100 -> 34.001239 | I120: =I118/I25*100 -> 33.115907 | J120: =J118/J25*100 -> 33.519591 | K120: =K118/K25*100 -> 32.689652 | L120: =L118/L25*100 -> 32.051772
D122: =D49+D46+D55 -> 968.24792 | E122: =E49+E46+E55 -> 986.73871 | F122: =F49+F46+F55 -> 1019.8602 | G122: =G49+G46+G55 -> 1021.4423 | H122: =H49+H46+H55 -> 1102.415 | I122: =I49+I46+I55 -> 1022.3763 | J122: =J49+J46+J55 -> 991.53904 | K122: =K49+K46+K55 -> 964.67252 | L122: =L49+L46+L55 -> 945.84866
D124: =D122/D25*100 -> 49.216216 | E124: =E122/E25*100 -> 44.583205 | F124: =F122/F25*100 -> 41.471741 | G124: =G122/G25*100 -> 37.76007 | H124: =H122/H25*100 -> 37.357302 | I124: =I122/I25*100 -> 34.645048 | J124: =J122/J25*100 -> 33.600072 | K124: =K122/K25*100 -> 32.689652 | L124: =L122/L25*100 -> 32.051772
D126: =D46+D49 -> 692.30656 | E126: =E46+E49 -> 669.98156 | F126: =F46+F49 -> 638.86906 | G126: =G46+G49 -> 599.44406 | H126: =H46+H49 -> 551.23156 | I126: =I46+I49 -> 497.31906 | J126: =J46+J49 -> 454.56906 | K126: =K46+K49 -> 452.19406 | L126: =L46+L49 -> 452.19406

Sheet Pages
C2: LIST OF CONTENTS
B4: SL. NO. | C4: ITEMS | D4: PAGE(S)
B6: 1 | C6: Introduction | D6: 1
B7: 2 | C7: Hotel Industry of India | D7: 1 - 6
B8: 3 | C8: About Incentives & Subsidies | D8: 7 - 9
B9: 4 | C9: About the Partners | D9: 10
B10: 5 | C10: Demand Forecast | D10: 11 - 13
B11: 6 | C11: Marketing Strategy | D11: 13
B12: 7 | C12: Location Details | D12: 14
B13: 8 | C13: Utility & Services | D13: 14
B14: 9 | C14: Facilities | D14: 15 - 17
B15: 10 | C15: About Personnel & Procedures | D15: 18
B16: 11 | C16: Quality Assurance | D16: 18
B17: 12 | C17: About the Consultants | D17: 19
B18: 13 | C18: Financial Analysis | D18: 20-23
B19: 14 | C19: Project Execution & Implementation Schedule | D19: 24
B20: 15 | C20: SWOT Analysis | D20: 25
C22: LIST OF ANNEXURES
B24: SL. NO. | C24: ITEMS | D24: PAGE(S)
B26: I | C26: Estimated Project Cost & Projected Means Of Finance | D26: 26
B27: II | C27: Computation of Working Capital Requirement | D27: 27
B28: III | C28: Projected Profitability | D28: 28
B29: IV | C29: Projected Balance Sheet | D29: 29
B30: V | C30: Break Even Analysis | D30: 30
B31: VI | C31: Projected Cash Flow | D31: 31
B32: VII | C32: Pay Back Period | D32: 32
B33: VIII | C33: Debt Service Coverage Ratio | D33: 33
B34: IX | C34: BEP | D34: 34
B35: X | C35: Internal Rate of Return | D35: 35
B36: XI | C36: Financial Ratio | D36: 36
C38: LIST OF APPENDICES
C40: ITEMS
B41: SL. NO. | D41: PAGE(S)
B42: 1 | C42: Details of Plant & Machinery, Misc. Fixed Assets, Electrical Installations | D42: 37
B43: 2 | C43: Details of Preliminary & Preoperative Expenses | D43: 38
B44: 3 | C44: Projected Sales | D44: 39 - 40
B45: 4 | C45: Statement showing calculation of Interest & Repayment | D45: 41
B46: 5 | C46: Depreciation Schedule | D46: 42 - 43
C48: CMA DATA FORMS | D48: 45 - 50

Sheet AT GLANCE
D3: PROJECT AT GLANCE
B5: 1) | C5: NAME OF THE FIRM | F5: : | G5: OM ARHAM VENTURES
B8: 2) | C8: CONSTITUTION | F8: : | G8: PARTNERSHIP
B10: 3) | C10: NAME OF PARTNERS | F10: : | G10: MR. PANKAJ KUMAR JAIN
G11: MR. SANDEEP JAIN
G12: MR. PRAMOD KUMAR JAIN
G13: MR. VINAY DAGA
G14: MR. KETAN RAJKUMAR DAGA
B17: 4) | C17: LOCATION | F17: : | G17: =G5 -> OM ARHAM VENTURES
G19: ADMIN. OFF.: ROOM NO.1, GROUND FLOOR,
G20: ARHAM COLD STORAGE PVT. LTD., -
G21: PALASHBARI UPARHALLI- DHARAPUR ROAD,
G22: NEAR KAMRUP THANDA GHAR, VILLAGE -
G23: SORPARA, MOUZA- CHAYANI, BIJOYNAGAR,
G24: GUWAHATI, KAMRUP RURAL,
G25: ASSAM, PIN-781122
B28: 5) | C28: PROJECT COST | F28: : | G28: Total | J28: ='CAPITAL COST'!D28 -> 4285.8643
B30: 6) | C30: MEANS OF FINANCE | F30: : | G30: Partners' Capital | J30: ='CAPITAL COST'!D46 -> 1185.8643
G32: Unsecured Loans | J32: ='CAPITAL COST'!D48 -> 400
G34: Term Loan From Financial Institutions | J34: ='CAPITAL COST'!D50 -> 2700
G37: Working Capital Assistance | J37: =+'CAPITAL COST'!D54 -> 0
B41: 11) | C41: Power | F41: : | G41: 320KVA
B42: 12) | C42: Manpower | F42: : | G42: =Manpower!C18 -> 146
B43: 13) | C43: Capacity/Facilities (No. of rooms) | F43: : | G43: =SALESPROJECTION!D12 -> 195

Sheet PROJECT_COST
C5: (12)
C7: A N N E X U R E - "I"_
C9: CAPITAL COST OF THE PROJECT
C10: Sl. No. | D10: Particulars | E10: Built Up Area: | F10: Amt. (in Lac Rs.)
C12: 1 | D12: Cost of Civil Works | I12: =(30.76+25.92+22.48) -> 79.16
D13: Land & Site Development | F13: =(873547/100000)+(30.76+25.92+22.48) -> 87.89547
D15: Building | F15: =639.44789-8.73547 -> 630.71242
C17: 3. | D17: Plant & Machineries | F17: =[14]ASSETS!I17 -> 212.57036
C19: 4. | D19: Miscellaneous Fixed Assets | F19: =[14]ASSETS!I40 -> 532.10454
C21: 5. | D21: Electrical Installations | F21: =[14]ASSETS!I48 -> 202.4942
C23: 6. | D23: Preliminary & Pre-operative Expenses | F23: =(8785729/100000)+0.14 -> 87.99729
C25: 7. | D25: Provision for Contingency | F25: =(8785729/100000) -> 87.85729
F27: =SUM(F12:F26) -> 1841.6316 | I27: =79.16 -> 79.16
I28: =F27-I27 -> 1762.4716
C29: MEANS OF FINANCES
C30: Sl. No. | D30: Particulars | F30: Amt. (in Lac Rs.)
C32: 1. | D32: Promoters Contribution | F32: =+F36-F34 -> 641.63157
D33: (Incl. Unsecured Loans from Shareholders & Directors)
C34: 2 | D34: Term Loan assistance | F34: =1200 -> 1200
F36: =+F27 -> 1841.6316

Sheet CAPITAL COST
C2: =Pages!D26 -> 26
B4: ANNEXURE - I
B5: ESTIMATED PROJECT COST & PROJECTED MEANS OF FINANCE
D9: (Rs. in Lacs)
B10: PARTICULARS | C10: CAPITAL OUT FLOW | D10: CAPITAL COST | E10: % COMPOSITION | G10: No.of rooms | H10: No. | I10: 108 | L10: Total
B12: LAND COST (OWNED) | D12: =C12 -> 0
B14: CIVIL WORKS (INCLUDING MEP) | C14: =ASSETS!I9+ASSETS!I34+ASSETS!I86 -> 2878.9368 | D14: =C14 -> 2878.9368 | E14: =D14/$D$28 -> 0.6717284 | G14: Land Area | H14: sq.ft | I14: =2763.04*10.764 -> 29741.363
G15: Total Built Up Area | H15: sq.ft | I15: =14020.04*10.764 -> 150911.71 | J15: Civil Construction Cost/BUA | K15: Rs.sq.ft | L15: =D14/I15*10^7 -> 190769.61
B16: FURNITURE & FIXTURES | C16: =ASSETS!I26 -> 375.3 | D16: =C16 -> 375.3 | E16: =D16/$D$28 -> 0.087566935 | J16: Equipment cost/Room | K16: Rs.crore | L16: =D13/I10 -> 0
B18: MISC. FIXED ASSETS | C18: =ASSETS!I82 -> 140.5 | D18: =C18 -> 140.5 | E18: =D18/$D$28 -> 0.032782186
G19: Manpower per 100 rooms | H19: Total Manpower expected to be hired | I19: =[15]Manpower!F35 -> 0 | L19: =+I19/I10*100 -> 0
B20: PLANT & MACHINERY | C20: =ASSETS!I62 -> 467.53924 | D20: =C20 -> 467.53924 | E20: =D20/$D$28 -> 0.10908867
B22: PRELIMINARY & PREOPERATIVE EXPENSES | C22: ='PREOPERATIVE EXP'!D20/100000 -> 285.72 | D22: =C22 -> 285.72 | E22: =D22/$D$28 -> 0.066665667 | J22: Project Cost/Room | K22: Rs.crore/Room | L22: =(D28/100)/I10 -> 0.39683929
B24: MARGIN MONEY / INVSTT. FOR WORKING CAPITAL | C24: =' wORKING CAPITAL'!E28 -> 22 | D24: =C24 -> 22 | E24: =D24/$D$28 -> 0.0051331537
B26: CONTINGENCY | C26: =(C14+C16+C18+C20)*3% -> 115.86828 | D26: =C26 -> 115.86828 | E26: =D26/$D$28 -> 0.027034986
B28: TOTAL PROJECT COST | C28: =SUM(C11:C27) -> 4285.8643 | D28: =SUM(D11:D27) -> 4285.8643 | E28: =SUM(E14:E27) -> 1
B31: COST OF CAPITAL
B34: CAPITAL EXPENDITURE | D34: =D28-(SUM(D35:D39)) -> 3978.1443
B36: PRELIMINARY & PREOPERATIVE EXPENSES | D36: =C22 -> 285.72
B38: MARGIN MONEY / INVSTT. FOR WORKING CAPITAL | D38: =C24 -> 22
D40: =SUM(D33:D39) -> 4285.8643
B43: PROPOSED MEANS OF FINANCE
B46: PARTNERS' CAPITAL | D46: =D40-SUM(D49:D51)-D48 -> 1185.8643
B48: UNSECURED LOANS | D48: 400
B50: TERM LOAN FROM BANKS | D50: =2700 -> 2700
B52: TOTAL | D52: =SUM(D44:D51) -> 4285.8643
B54: W C LIMITS APPLIED | D54: =' wORKING CAPITAL'!E27 -> 0
B59: DIFF. | D59: =D40-D52 -> 0

Sheet  wORKING CAPITAL
F2: =Pages!D27 -> 27
D4: COMPUTATION OF WORKING CAPITAL REQUIREMENT
C6: ANNEXURE II
K8: ( Rs. In Lacs) | L8: ( Rs. In Lacs)
B9: Particulars | D9: Months/Year | E9: 1 | F9: 2 | G9: 3 | H9: 4 | I9: 5 | J9: 6 | K9: 7 | L9: 8 | M9: 9 | N9: 10
B11: CURRENT ASSETS
B12: Accounts Receivable | D12: 0.15 | E12: =ROUND('P L '!D29/12*$D$12,0) -> 25 | F12: ='P L '!E29/12*$D$12*1.1 -> 27.665483 | G12: ='P L '!F29/12*$D$12*1.1 -> 31.123669 | H12: ='P L '!G29/12*$D$12*1.1 -> 34.581854 | I12: ='P L '!H29/12*$D$12*1.2 -> 41.498225 | J12: ='P L '!I29/12*$D$12*1.4 -> 52.815923 | K12: ='P L '!J29/12*$D$12*1.6 -> 65.391143 | L12: ='P L '!K29/12*$D$12*1.8 -> 79.223884 | M12: ='P L '!L29/12*$D$12*2 -> 75.451318 | N12: ='P L '!M29/12*$D$12*2.02 -> 76.205831
B14: Inventory
B15: Provisions & Beverages | D15: 1 | E15: =ROUND('P L '!D33/12*$D$15,0) -> 12 | F15: ='P L '!E33/12*$D$15+0.17 -> 11.961143 | G15: ='P L '!F33/12*$D$15 -> 13.265035 | H15: ='P L '!G33/12*$D$15 -> 14.738928 | I15: ='P L '!H33/12*$D$15*1.2 -> 19.455385 | J15: ='P L '!I33/12*$D$15*1.4 -> 24.761399 | K15: ='P L '!J33/12*$D$15*1.6 -> 30.656971 | L15: ='P L '!K33/12*$D$15*1.8 -> 37.142099 | M15: ='P L '!L33/12*$D$15*2 -> 35.373427 | N15: ='P L '!M33/12*$D$15*2.02 -> 35.727162
B16: Crockery, cutlery, linen,
B17: Silver Ware,SS items
B19: TOTAL CURRENT ASSETS | E19: =E12+E15 -> 37 | F19: =F12+F15 -> 39.626626 | G19: =G12+G15 -> 44.388704 | H19: =H12+H15 -> 49.320782 | I19: =I12+I15 -> 60.95361 | J19: =J12+J15 -> 77.577322 | K19: =K12+K15 -> 96.048113 | L19: =L12+L15 -> 116.36598 | ... N19: =N12+N15 -> 111.93299
B21: CURRENT LIABILITIES
B22: Accounts Payable | D22: 0.25 | E22: =ROUND((SUM('P L '!D33:D43)-'P L '!D38-'P L '!D49)/12*$D$22,0)+1 -> 15 | F22: =(SUM('P L '!E33:E43)-'P L '!E38-'P L '!E49)/12*$D$22+1+0.34 -> 15.565957 | G22: =(SUM('P L '!F33:F43)-'P L '!F38-'P L '!F49)/12*$D$22+1 -> 18.159076 | H22: =(SUM('P L '!G33:G43)-'P L '!G38-'P L '!G49)/12*$D$22+1 -> 20.364244 | I22: =(SUM('P L '!H33:H43)-'P L '!H38-'P L '!H49)/12*$D$22*0.95+1 -> 21.471123 | J22: =(SUM('P L '!I33:I43)-'P L '!I38-'P L '!I49)/12*$D$22*0.925+1 -> 22.939285 | K22: =(SUM('P L '!J33:J43)-'P L '!J38-'P L '!J49)/12*$D$22*0.9+1+0.25 -> 24.39454 | L22: =(SUM('P L '!K33:K43)-'P L '!K38-'P L '!K49)/12*$D$22*0.9+1 -> 26.065211 | M22: =(SUM('P L '!L33:L43)-'P L '!L38-'P L '!L49)/12*$D$22*0.9+1 -> #VALUE! | N22: =(SUM('P L '!M33:M43)-'P L '!M38-'P L '!M49)/12*$D$22*0.9+1.02 -> #VALUE!
B24: WORKING CAPITAL
B25: Net Working Capital | E25: =E19-E22 -> 22 | F25: =F19-F22 -> 24.060669 | G25: =G19-G22 -> 26.229628 | H25: =H19-H22 -> 28.956538 | I25: =I19-I22 -> 39.482487 | J25: =J19-J22 -> 54.638037 | K25: =K19-K22 -> 71.653573 | L25: =L19-L22 -> 90.300772 | ... N25: =N19-N22 -> #VALUE!
B26: Increase in Working Capital | E26: =E25 -> 22 | F26: =F25-E25 -> 2.060669 | G26: =G25-F25 -> 2.1689588 | H26: =H25-G25 -> 2.7269105 | I26: =I25-H25 -> 10.525949 | J26: =J25-I25 -> 15.15555 | K26: =K25-J25 -> 17.015535 | L26: =L25-K25 -> 18.647199 | M26: =M25-L25 -> #VALUE! | N26: =N25-M25 -> #VALUE!
B27: Bank Finance | D27: 0.75 | E27: =ROUND(E25*$D$27,0)*0 -> 0 | F27: =E27 -> 0 | G27: =F27 -> 0 | H27: =G27 -> 0 | I27: =H27 -> 0 | J27: =I27 -> 0 | K27: =J27 -> 0 | L27: =K27 -> 0 | M27: =L27 -> 0 | N27: =M27 -> 0
B28: Margin money / Investment | E28: =E25-E27 -> 22 | F28: =F25-F27 -> 24.060669 | G28: =G25-G27 -> 26.229628 | H28: =H25-H27 -> 28.956538 | I28: =I25-I27 -> 39.482487 | J28: =J25-J27 -> 54.638037 | K28: =K25-K27 -> 71.653573 | L28: =L25-L27 -> 90.300772 | ... N28: =N25-N27 -> #VALUE!
B29: Interest on Working Capital | E29: =E27*14.5%*0.9 -> 0 | F29: =F27*14.5%*0.9 -> 0 | G29: =G27*14.5%*0.9 -> 0 | H29: =H27*14.5%*0.9 -> 0 | I29: =I27*14.5%*0.9 -> 0 | J29: =J27*14.5%*0.9 -> 0 | K29: =K27*14.5%*0.9 -> 0 | L29: =L27*14.5%*0.9 -> 0 | ... N29: =N27*14.5%*0.9 -> 0
B30: Increase in Inventory | E30: =E15 -> 12 | F30: =F15-E15 -> -0.0388575 | G30: =G15-F15 -> 1.3038928 | H30: =H15-G15 -> 1.4738928 | I30: =I15-H15 -> 4.716457 | J30: =J15-I15 -> 5.3060141 | K30: =K15-J15 -> 5.8955713 | L30: =L15-K15 -> 6.4851284 | M30: =M15-L15 -> -1.7686714 | N30: =N15-M15 -> 0.35373428
B31: Increase in Accounts Receivable | E31: =E12 -> 25 | F31: =F12-E12 -> 2.6654834 | G31: =G12-F12 -> 3.4581854 | H31: =H12-G12 -> 3.4581854 | I31: =I12-H12 -> 6.9163708 | J31: =J12-I12 -> 11.317698 | K31: =K12-J12 -> 12.57522 | L31: =L12-K12 -> 13.832742 | M31: =M12-L12 -> -3.7725659 | N31: =N12-M12 -> 0.75451318
B32: Increase in Accounts Payable | E32: =E22 -> 15 | F32: =F22-E22 -> 0.56595687 | G32: =G22-F22 -> 2.5931194 | H32: =H22-G22 -> 2.2051677 | I32: =I22-H22 -> 1.1068793 | J32: =J22-I22 -> 1.4681614 | K32: =K22-J22 -> 1.4552555 | L32: =L22-K22 -> 1.6706708 | M32: =M22-L22 -> #VALUE! | N32: =N22-M22 -> #VALUE!
B33: Increase in Working Capital Loan | E33: =E27 -> 0 | F33: =F27-E27 -> 0 | G33: =G27-F27 -> 0 | H33: =H27-G27 -> 0 | I33: =I27-H27 -> 0 | J33: =J27-I27 -> 0 | K33: =K27-J27 -> 0 | L33: =L27-K27 -> 0 | M33: =M27-L27 -> 0 | N33: =N27-M27 -> 0

Sheet BN_2
A4: Year | B4: =2015 -> 2015 | C4: =B4+1 -> 2016 | D4: =C4+1 -> 2017 | E4: =D4+1 -> 2018 | F4: =E4+1 -> 2019 | G4: =F4+1 -> 2020 | H4: =G4+1 -> 2021 | I4: =H4+1 -> 2022 | J4: =I4+1 -> 2023
A5: Capacity Operation | B5: ='P L '!D18 -> 0.4 | C5: ='P L '!E18 -> 0.4 | D5: ='P L '!F18 -> 0.45 | E5: ='P L '!G18 -> 0.5 | F5: ='P L '!H18 -> 0.55 | G5: ='P L '!I18 -> 0.6 | H5: ='P L '!J18 -> 0.65 | I5: ='P L '!K18 -> 0.7 | J5: ='P L '!L18 -> 0.6
A6: Room Sales | B6: 273.02 | C6: 307.1475 | D6: 341.275 | E6: 375.4025 | F6: 409.53 | G6: 409.53 | H6: 409.53 | I6: 409.53 | J6: 409.53
A7: F & B Sales | B7: 216.664 | C7: 243.747 | D7: 270.83 | E7: 297.913 | F7: 324.996 | G7: 324.996 | H7: 324.996 | I7: 324.996 | J7: 324.996
A8: Banquet Hall Receipts | B8: 58.4 | C8: 65.7 | D8: 73 | E8: 80.3 | F8: 87.6 | G8: 87.6 | H8: 87.6 | I8: 87.6 | J8: 87.6
A9: Conference Hall Receipts | B9: 43.8 | C9: 49.275 | D9: 54.75 | E9: 60.225 | F9: 65.7 | G9: 65.7 | H9: 65.7 | I9: 65.7 | J9: 65.7
A10: Total Projected Sales (Excl Other Income) | B10: =SUM(B6:B9) -> 591.884 | C10: =SUM(C6:C9) -> 665.8695 | D10: =SUM(D6:D9) -> 739.855 | E10: =SUM(E6:E9) -> 813.8405 | F10: =SUM(F6:F9) -> 887.826 | G10: =SUM(G6:G9) -> 887.826 | H10: =SUM(H6:H9) -> 887.826 | I10: =SUM(I6:I9) -> 887.826 | J10: =SUM(J6:J9) -> 887.826
B15: 31.03.15 | C15: 31.03.16 | D15: 31.03.17 | E15: 31.03.18 | F15: 31.03.19 | G15: 31.03.20 | H15: 31.03.21 | I15: 31.03.22 | J15: 31.03.23
A16: Paid up capital | B16: ='B S '!E26 -> 1185.8643 | C16: ='B S '!F26 -> 1185.8643 | D16: ='B S '!G26 -> 1185.8643 | E16: ='B S '!H26 -> 1185.8643 | F16: ='B S '!I26 -> 1185.8643 | G16: ='B S '!J26 -> 1185.8643 | H16: ='B S '!K26 -> 1185.8643 | I16: ='B S '!L26 -> 1185.8643 | J16: ='B S '!M26 -> 1185.8643
A17: Add: Capital Introduced
A18: Add: Accumulated Profit | B18: 0 | C18: 0 | D18: 0 | E18: 0 | F18: 0 | G18: 0 | H18: 0 | I18: 0 | J18: 0
A19: Add:Reserves and Surplus excluding revaluation reserves | B19: ='B S '!E27 -> 320.87118 | C19: ='B S '!F27 -> 641.53927 | D19: ='B S '!G27 -> 1019.1579 | E19: ='B S '!H27 -> 1487.4856 | F19: ='B S '!I27 -> 2051.5345 | G19: ='B S '!J27 -> 2711.9342 | H19: ='B S '!K27 -> 3482.0063 | I19: ='B S '!L27 -> 4350.8107 | J19: ='B S '!M27 -> #VALUE!
A20: Add:Deferred Tax Liability | B20: 0 | C20: 0 | D20: 0 | E20: 0 | F20: 0 | G20: 0 | H20: 0 | I20: 0 | J20: 0
A21: Less: Investment in subsidiary | B21: 0 | C21: 0 | D21: 0 | E21: 0 | F21: 0 | G21: 0 | H21: 0 | I21: 0 | J21: 0
A22: Less: Revaluation Reserve | B22: 0 | C22: 0 | D22: 0 | E22: 0 | F22: 0 | G22: 0 | H22: 0 | I22: 0 | J22: 0
A23: Less: Misc. expenditure not written off | B23: 0 | C23: 0 | D23: 0 | E23: 0 | F23: 0 | G23: 0 | H23: 0 | I23: 0 | J23: 0
A24: Less: Accumulated losses | B24: 0 | C24: 0 | D24: 0 | E24: 0 | F24: 0 | G24: 0 | H24: 0 | I24: 0 | J24: 0
A25: Less: Deferred Tax Asset | B25: 0 | C25: 0 | D25: 0 | E25: 0 | F25: 0 | G25: 0 | H25: 0 | I25: 0 | J25: 0
A26: TNW | B26: =B16+B19 -> 1506.7355 | C26: =C16+C19 -> 1827.4036 | D26: =D16+D19 -> 2205.0221 | E26: =E16+E19 -> 2673.3499 | F26: =F16+F19 -> 3237.3988 | G26: =G16+G19 -> 3897.7985 | H26: =H16+H19 -> 4667.8706 | I26: =I16+I19 -> 5536.675 | J26: =J16+J19 -> #VALUE!
A47: PBIT | B47: =#REF!/B10*100 -> #REF! | C47: =#REF!/C10*100 -> #REF! | D47: =#REF!/D10*100 -> #REF! | E47: =#REF!/E10*100 -> #REF! | F47: =#REF!/F10*100 -> #REF! | G47: =#REF!/G10*100 -> #REF! | H47: =#REF!/H10*100 -> #REF! | I47: =#REF!/I10*100 -> #REF!
A48: PBDIT | B48: =(#REF!+#REF!)/B10*100 -> #REF! | C48: =(#REF!+#REF!)/C10*100 -> #REF! | D48: =(#REF!+#REF!)/D10*100 -> #REF! | E48: =(#REF!+#REF!)/E10*100 -> #REF! | F48: =(#REF!+#REF!)/F10*100 -> #REF! | G48: =(#REF!+#REF!)/G10*100 -> #REF! | H48: =(#REF!+#REF!)/H10*100 -> #REF! | I48: =(#REF!+#REF!)/I10*100 -> #REF!
A49: PAT | B49: =#REF!/B10*100 -> #REF! | C49: =#REF!/C10*100 -> #REF! | D49: =#REF!/D10*100 -> #REF! | E49: =#REF!/E10*100 -> #REF! | F49: =#REF!/F10*100 -> #REF! | G49: =#REF!/G10*100 -> #REF! | H49: =#REF!/H10*100 -> #REF! | I49: =#REF!/I10*100 -> #REF!
A50: Cash Profit | B50: =(#REF!+#REF!)/B10*100 -> #REF! | C50: =(#REF!+#REF!)/C10*100 -> #REF! | D50: =(#REF!+#REF!)/D10*100 -> #REF! | E50: =(#REF!+#REF!)/E10*100 -> #REF! | F50: =(#REF!+#REF!)/F10*100 -> #REF! | G50: =(#REF!+#REF!)/G10*100 -> #REF! | H50: =(#REF!+#REF!)/H10*100 -> #REF! | I50: =(#REF!+#REF!)/I10*100 -> #REF!
B98: =#REF!+#REF! -> #REF! | C98: =#REF!+#REF! -> #REF! | D98: =#REF!+#REF! -> #REF! | E98: =#REF!+#REF! -> #REF! | F98: =#REF!+#REF! -> #REF! | G98: =#REF!+#REF! -> #REF! | H98: =#REF!+#REF! -> #REF! | I98: =#REF!+#REF! -> #REF! | J98: =#REF!+#REF! -> #REF!
B100: =B98/B10*100 -> #REF! | C100: =C98/C10*100 -> #REF! | D100: =D98/D10*100 -> #REF! | E100: =E98/E10*100 -> #REF! | F100: =F98/F10*100 -> #REF! | G100: =G98/G10*100 -> #REF! | H100: =H98/H10*100 -> #REF! | I100: =I98/I10*100 -> #REF! | J100: =J98/J10*100 -> #REF!
B102: =#REF!+#REF!+#REF! -> #REF! | C102: =#REF!+#REF!+#REF! -> #REF! | D102: =#REF!+#REF!+#REF! -> #REF! | E102: =#REF!+#REF!+#REF! -> #REF! | F102: =#REF!+#REF!+#REF! -> #REF! | G102: =#REF!+#REF!+#REF! -> #REF! | H102: =#REF!+#REF!+#REF! -> #REF! | I102: =#REF!+#REF!+#REF! -> #REF! | J102: =#REF!+#REF!+#REF! -> #REF!
B104: =B102/B10*100 -> #REF! | C104: =C102/C10*100 -> #REF! | D104: =D102/D10*100 -> #REF! | E104: =E102/E10*100 -> #REF! | F104: =F102/F10*100 -> #REF! | G104: =G102/G10*100 -> #REF! | H104: =H102/H10*100 -> #REF! | I104: =I102/I10*100 -> #REF! | J104: =J102/J10*100 -> #REF!
B106: =#REF!+#REF! -> #REF! | C106: =#REF!+#REF! -> #REF! | D106: =#REF!+#REF! -> #REF! | E106: =#REF!+#REF! -> #REF! | F106: =#REF!+#REF! -> #REF! | G106: =#REF!+#REF! -> #REF! | H106: =#REF!+#REF! -> #REF! | I106: =#REF!+#REF! -> #REF! | J106: =#REF!+#REF! -> #REF!

Sheet P  L 
D2: =Pages!D28 -> 28
D4: ANNEXURE III
C5: Projected Profitability
J6: Rs. In Lacs
A8: Year | D8: ='B S '!E8 -> Year1 | E8: ='B S '!F8 -> Year2 | F8: ='B S '!G8 -> Year3 | G8: ='B S '!H8 -> Year4 | H8: ='B S '!I8 -> Year5 | I8: ='B S '!J8 -> Year6 | J8: ='B S '!K8 -> Year7 | K8: ='B S '!L8 -> Year8 | ... M8: ='B S '!N8 -> Year10
A10: Room Charges | D10: =SALESPROJECTION!E74 -> 3668.25 | E10: =SALESPROJECTION!F74 -> 3668.25 | F10: =SALESPROJECTION!G74 -> 3668.25 | G10: =SALESPROJECTION!H74 -> 3668.25 | H10: =SALESPROJECTION!I74 -> 3668.25 | I10: =SALESPROJECTION!J74 -> 3668.25 | J10: =SALESPROJECTION!K74 -> 3668.25 | K10: =SALESPROJECTION!L74 -> 3668.25 | ... M10: =SALESPROJECTION!N74 -> 3668.25
A11: F & B Sales | D11: =SALESPROJECTION!E75 -> 884.33569 | E11: =SALESPROJECTION!F75 -> 884.33569 | F11: =SALESPROJECTION!G75 -> 884.33569 | G11: =SALESPROJECTION!H75 -> 884.33569 | H11: =SALESPROJECTION!I75 -> 884.33569 | I11: =SALESPROJECTION!J75 -> 884.33569 | J11: =SALESPROJECTION!K75 -> 884.33569 | K11: =SALESPROJECTION!L75 -> 884.33569 | ... M11: =SALESPROJECTION!N75 -> 884.33569
A12: Banquet Hall Receipts | D12: =SALESPROJECTION!E76 -> 195 | E12: =SALESPROJECTION!F76 -> 195 | F12: =SALESPROJECTION!G76 -> 195 | G12: =SALESPROJECTION!H76 -> 195 | H12: =SALESPROJECTION!I76 -> 195 | I12: =SALESPROJECTION!J76 -> 195 | J12: =SALESPROJECTION!K76 -> 195 | K12: =SALESPROJECTION!L76 -> 195 | ... M12: =SALESPROJECTION!N76 -> 195
A13: =SALESPROJECTION!A77 -> Fitness Centre | D13: =SALESPROJECTION!E77 -> 24 | E13: =SALESPROJECTION!F77 -> 24 | F13: =SALESPROJECTION!G77 -> 24 | G13: =SALESPROJECTION!H77 -> 24 | H13: =SALESPROJECTION!I77 -> 24 | I13: =SALESPROJECTION!J77 -> 24 | J13: =SALESPROJECTION!K77 -> 24 | K13: =SALESPROJECTION!L77 -> 24 | ... M13: =SALESPROJECTION!N77 -> 24
A14: =SALESPROJECTION!A78 -> Game Parlour | D14: =SALESPROJECTION!E78 -> 87.75 | E14: =SALESPROJECTION!F78 -> 87.75 | F14: =SALESPROJECTION!G78 -> 87.75 | G14: =SALESPROJECTION!H78 -> 87.75 | H14: =SALESPROJECTION!I78 -> 87.75 | I14: =SALESPROJECTION!J78 -> 87.75 | J14: =SALESPROJECTION!K78 -> 87.75 | K14: =SALESPROJECTION!L78 -> 87.75 | ... M14: =SALESPROJECTION!N78 -> 87.75
A15: Conference Hall Receipts | D15: =SALESPROJECTION!E79 -> 45 | E15: =SALESPROJECTION!F79 -> 45 | F15: =SALESPROJECTION!G79 -> 45 | G15: =SALESPROJECTION!H79 -> 45 | H15: =SALESPROJECTION!I79 -> 45 | I15: =SALESPROJECTION!J79 -> 45 | J15: =SALESPROJECTION!K79 -> 45 | K15: =SALESPROJECTION!L79 -> 45 | ... M15: =SALESPROJECTION!N79 -> 45
A16: Other Income | D16: =SALESPROJECTION!E80 -> 125.7522 | E16: =SALESPROJECTION!F80 -> 125.7522 | F16: =SALESPROJECTION!G80 -> 125.7522 | G16: =SALESPROJECTION!H80 -> 125.7522 | H16: =SALESPROJECTION!I80 -> 125.7522 | I16: =SALESPROJECTION!J80 -> 125.7522 | J16: =SALESPROJECTION!K80 -> 125.7522 | K16: =SALESPROJECTION!L80 -> 125.7522 | ... M16: =SALESPROJECTION!N80 -> 125.7522
A17: Gross Revenue Receipt | D17: =SUM(D10:D16) -> 5030.0879 | E17: =SUM(E10:E16) -> 5030.0879 | F17: =SUM(F10:F16) -> 5030.0879 | G17: =SUM(G10:G16) -> 5030.0879 | H17: =SUM(H10:H16) -> 5030.0879 | I17: =SUM(I10:I16) -> 5030.0879 | J17: =SUM(J10:J16) -> 5030.0879 | K17: =SUM(K10:K16) -> 5030.0879 | ... M17: =SUM(M10:M16) -> 5030.0879 | U17: =E17-SALESPROJECTION!F81 -> 0 | V17: =F17-SALESPROJECTION!G81 -> 0 | W17: =G17-SALESPROJECTION!H81 -> 0 | X17: =H17-SALESPROJECTION!I81 -> 0 | Y17: =I17-SALESPROJECTION!J81 -> 0 | Z17: =J17-SALESPROJECTION!K81 -> 0
A18: Envisaged Occupancy | D18: 0.4 | E18: =D18 -> 0.4 | F18: =E18+0.05 -> 0.45 | G18: =F18+0.05 -> 0.5 | H18: =G18+5% -> 0.55 | I18: =H18+5% -> 0.6 | J18: =I18+5% -> 0.65 | K18: =J18+5% -> 0.7 | L18: 0.6 | M18: 0.6
A20: Projected Sales
A22: Room Sales | D22: =D18*D10 -> 1467.3 | E22: =E18*E10 -> 1467.3 | F22: =F18*F10 -> 1650.7125 | G22: =G18*G10 -> 1834.125 | H22: =H18*H10 -> 2017.5375 | I22: =I18*I10 -> 2200.95 | J22: =J18*J10 -> 2384.3625 | K22: =K18*K10 -> 2567.775 | ... M22: =M18*M10 -> 2200.95
A23: F & B Sales | D23: =$D$18*D11 -> 353.73428 | E23: =$E$18*E11 -> 353.73428 | F23: =$F$18*F11 -> 397.95106 | G23: =$G$18*G11 -> 442.16784 | H23: =$H$18*H11 -> 486.38463 | I23: =$I$18*I11 -> 530.60141 | J23: =J18*J11 -> 574.8182 | K23: =K18*K11 -> 619.03498 | L23: =L18*L11 -> 530.60141 | M23: =M18*M11 -> 530.60141 | N23: =N18*N11 -> 0
A24: Banquet Hall Receipts | D24: =$D$18*D12 -> 78 | E24: =$E$18*E12 -> 78 | F24: =$F$18*F12 -> 87.75 | G24: =$G$18*G12 -> 97.5 | H24: =$H$18*H12 -> 107.25 | I24: =$I$18*I12 -> 117 | J24: =$J$18*J12 -> 126.75 | K24: =$K$18*K12 -> 136.5 | L24: =L12*L18 -> 117 | M24: =M12*M18 -> 117
A25: =A13 -> Fitness Centre | D25: =D13*D18 -> 9.6 | E25: =E13*E18 -> 9.6 | F25: =F13*F18 -> 10.8 | G25: =G13*G18 -> 12 | H25: =H13*H18 -> 13.2 | I25: =I13*I18 -> 14.4 | J25: =J13*J18 -> 15.6 | K25: =K13*K18 -> 16.8 | ... M25: =M13*M18 -> 14.4
A26: =A14 -> Game Parlour | D26: =D14*D18 -> 35.1 | E26: =E14*E18 -> 35.1 | F26: =F14*F18 -> 39.4875 | G26: =G14*G18 -> 43.875 | H26: =H14*H18 -> 48.2625 | I26: =I14*I18 -> 52.65 | J26: =J14*J18 -> 57.0375 | K26: =K14*K18 -> 61.425 | ... M26: =M14*M18 -> 52.65
A27: Conference Hall Receipts | D27: =$D$18*D15 -> 18 | E27: =$E$18*E15 -> 18 | F27: =$F$18*F15 -> 20.25 | G27: =$G$18*G15 -> 22.5 | H27: =$H$18*H15 -> 24.75 | I27: =$I$18*I15 -> 27 | J27: =$J$18*J15 -> 29.25 | K27: =$K$18*K15 -> 31.5 | L27: =L15*L18 -> 27 | M27: =M15*M18 -> 27
A28: Other Income | D28: =D18*D16 -> 50.300879 | E28: =E18*E16 -> 50.300879 | F28: =F18*F16 -> 56.588489 | G28: =G18*G16 -> 62.876099 | H28: =H18*H16 -> 69.163708 | I28: =I18*I16 -> 75.451318 | J28: =J18*J16 -> 81.738928 | K28: =K18*K16 -> 88.026538 | ... M28: =M18*M16 -> 75.451318
A29: Total Projected Sales | D29: =SUM(D22:D28) -> 2012.0352 | E29: =SUM(E22:E28) -> 2012.0352 | F29: =SUM(F22:F28) -> 2263.5395 | G29: =SUM(G22:G28) -> 2515.0439 | H29: =SUM(H22:H28) -> 2766.5483 | I29: =SUM(I22:I28) -> 3018.0527 | J29: =SUM(J22:J28) -> 3269.5571 | K29: =SUM(K22:K28) -> 3521.0615 | ... M29: =SUM(M22:M28) -> 3018.0527
A31: Revenue Expenses | B31: As | C31: of
A33: Food & Beverages Cost | B33: 0.4 | C33: F & B sales | D33: =ROUND(B33*D23,2) -> 141.49 | E33: =B33*E23 -> 141.49371 | F33: =B33*F23 -> 159.18042 | G33: =B33*G23 -> 176.86714 | H33: =B33*H23 -> 194.55385 | I33: =B33*I23 -> 212.24057 | J33: =$B$33*J23 -> 229.92728 | K33: =$B$33*K23 -> 247.61399 | L33: =$B$33*L23 -> 212.24056 | M33: =$B$33*M23 -> 212.24056 | P33: =#REF! -> #REF!
A34: Banquet & Conference Hall Expenses | B34: 0.225 | C34: B & C Receipts | D34: =(D24+D27)*$B$34 -> 21.6 | E34: =(E24+E27)*$B$34 -> 21.6 | F34: =(F24+F27)*$B$34 -> 24.3 | G34: =(G24+G27)*$B$34 -> 27 | H34: =(H24+H27)*$B$34 -> 29.7 | I34: =(I24+I27)*$B$34 -> 32.4 | J34: =(J24+J27)*$B$34 -> 35.1 | K34: =(K24+K27)*$B$34 -> 37.8 | ... M34: =(M24+M27)*$B$34 -> 32.4 | P34: =#REF! -> #REF!
A35: Employee Related Expenses | B35: =Manpower!A3 -> APPENDIX 7: | D35: =Manpower!D18/100000 -> 121.68 | E35: =D35 -> 121.68 | F35: =E35*1.05 -> 127.764 | G35: =F35*1.05 -> 134.1522 | H35: =G35*1.05 -> 140.85981 | I35: =H35*1.1 -> 154.94579 | J35: =I35*1.1 -> 170.44037 | K35: =J35*1.1 -> 187.48441 | L35: =$B$35*L29*1.35 -> #VALUE! | M35: =$B$35*M29*1.34 -> #VALUE! | Q35: Increasing
A36: Power, Fuel & Water Charges | B36: ='power cost'!F4 -> APPENDIX - 6 | D36: ='power cost'!E36 -> 182.9846 | E36: ='power cost'!F36 -> 182.9846 | F36: ='power cost'!G36 -> 205.8555 | G36: ='power cost'!H36 -> 228.7264 | H36: ='power cost'!I36 -> 251.5973 | I36: ='power cost'!J36 -> 274.4682 | J36: ='power cost'!K36 -> 297.3391 | K36: ='power cost'!L36 -> 320.21 | ... M36: ='power cost'!N36 -> 0
A37: Repair & Maintenance | B37: 0.0075 | C37: Assets | D37: =depreciation!D147*0.75% -> 28.587527 | E37: =depreciation!E147*0.75% -> 25.196071 | F37: =depreciation!F147*1% -> 30.022821 | G37: =depreciation!G147*1.25% -> 32.001101 | H37: =depreciation!H147*2% -> 44.55788 | I37: =depreciation!I147*2.75% -> 51.856748 | J37: =depreciation!J147*3% -> 46.455176 | K37: =depreciation!K147*3.25% -> 38.880134 | L37: =depreciation!L147*3.25% -> 26.946327 | M37: =depreciation!M147*3.35% -> 16.479444 | Q37: Increasing
A38: Discount on Room Rentals | B38: 0.025 | C38: Room Sales | D38: =D22*B38 -> 36.6825 | E38: =E22*B38*1.5 -> 55.02375 | F38: =F22*B38*2 -> 82.535625 | G38: =G22*B38*2.15 -> 98.584219 | H38: =H22*B38*2.25 -> 113.48648 | I38: =I22*B38*2.5 -> 137.55938 | J38: =J22*$B$38*2.5 -> 149.02266 | K38: =K22*$B$38*2.5 -> 160.48594 | L38: =L22*$B$38*2.5 -> 137.55937 | M38: =M22*$B$38*2.5 -> 137.55937 | Q38: Increasing | R38: Max 25%
A39: Room Upkeep Exp. | B39: 0.03 | C39: Room Sales | D39: =B39*D22 -> 44.019 | E39: =B39*E22 -> 44.019 | F39: =B39*F22*1.15 -> 56.949581 | G39: =B39*G22*1.2 -> 66.0285 | H39: =B39*H22*1.25 -> 75.657656 | I39: =B39*I22*1.25 -> 82.535625 | J39: =B39*J22*1.25 -> 89.413594 | K39: =B39*K22*1.25 -> 96.291563 | L39: =B39*L22*1.25 -> 82.535625 | M39: =B39*M22*1.25 -> 82.535625 | Q39: Increasing | R39: Normal
A40: General Upkeep & Services | B40: 0.01 | C40: Total Sales | D40: =B40*D29 -> 20.120352 | E40: =B40*E29 -> 20.120352 | F40: =B40*F29*1.1 -> 24.898935 | G40: =B40*G29*1.15 -> 28.923005 | H40: =B40*H29*1.2 -> 33.19858 | I40: =B40*I29*1.2 -> 36.216633 | J40: =B40*J29*1.2 -> 39.234685 | K40: =B40*K29*1.2 -> 42.252738 | L40: =B40*L29*1.2 -> 36.216633 | M40: =B40*M29*1.2 -> 36.216633 | Q40: Increasing | R40: Normal
A41: Administration Expenses | B41: 0.03 | C41: Total Sales | D41: =B41*D29 -> 60.361055 | E41: =B41*E29 -> 60.361055 | F41: =B41*F29*1.1 -> 74.696805 | G41: =B41*G29*1.15 -> 86.769016 | H41: =B41*H29*1.2 -> 99.59574 | I41: =B41*I29*1.2 -> 108.6499 | J41: =B41*J29*1.25 -> 122.60839 | K41: =B41*K29*1.25 -> 132.03981 | L41: =B41*L29*1.25 -> 113.17698 | M41: =B41*M29*1.25 -> 113.17698 | Q41: Increasing
A42: Management expenses | B42: 0.0175 | C42: Total Sales | D42: =B42*D29 -> 35.210615 | E42: =B42*E29 -> 35.210615 | F42: =B42*F29*1.1 -> 43.573136 | G42: =B42*G29*1.2 -> 52.815923 | H42: =B42*H29*1.2 -> 58.097515 | I42: =B42*I29*1.22 -> 64.435426 | J42: =B42*J29*1.22 -> 69.805045 | K42: =B42*K29*1.23 -> 75.790849 | L42: =B42*L29*1.23 -> 64.963585 | M42: =B42*M29*1.23 -> 64.963585 | Q42: Increasing | R42: Normal
A43: Advertisement & Sales Promotion | B43: 0.02 | C43: Total Sales | D43: =B43*D29 -> 40.240703 | E43: =B43*E29 -> 40.240703 | F43: =B43*F29*2 -> 90.541582 | G43: =B43*G29*2.25 -> 113.17698 | H43: =B43*H29*2.3 -> 127.26122 | I43: =B43*I29*2.4 -> 144.86653 | J43: =B43*J29*2.5 -> 163.47786 | K43: =B43*K29*2.75 -> 193.65838 | L43: =B43*L29*2.85 -> 172.02901 | M43: =B43*M29*2.9 -> 175.04706 | Q43: Increasing
A44: Insurance Charges
A45: Building | B45: 0.0033 | D45: =B45*'CAPITAL COST'!C14 -> 9.5004913 | E45: =D45 -> 9.5004913 | F45: =E45 -> 9.5004913 | G45: =F45 -> 9.5004913 | H45: =G45 -> 9.5004913 | I45: =H45 -> 9.5004913 | J45: =I45 -> 9.5004913 | K45: =J45 -> 9.5004913 | L45: =K45 -> 9.5004913 | M45: =L45 -> 9.5004913 | W45: =B45*depreciation!D128 -> 10.488325 | X45: =B45*'CAPITAL COST'!D14 -> 9.5004913
A46: Plant & Equipment | B46: 0.005 | D46: =B46*'CAPITAL COST'!D20+(ASSETS!I82-ASSETS!I78+('details of fixed assets '!F145/100000+'details of fixed assets '!F146/100000))*B46 -> 3.6821262 | E46: =D46 -> 3.6821262 | F46: =E46 -> 3.6821262 | G46: =F46 -> 3.6821262 | H46: =G46 -> 3.6821262 | I46: =H46 -> 3.6821262 | J46: =I46 -> 3.6821262 | K46: =J46 -> 3.6821262 | L46: =K46 -> 3.6821262 | M46: =L46 -> 3.6821262 | X46: =B46*('CAPITAL COST'!D20+'CAPITAL COST'!D16) -> 4.2141962
A47: Furniture & Accessories | B47: 0.0025 | D47: =B47*(SUM('details of fixed assets '!F138:F144))/100000 -> 0.38145 | E47: =D47 -> 0.38145 | F47: =E47 -> 0.38145 | G47: =F47 -> 0.38145 | H47: =G47 -> 0.38145 | I47: =H47 -> 0.38145 | J47: =I47 -> 0.38145 | K47: =J47 -> 0.38145 | L47: =K47 -> 0.38145 | M47: =L47 -> 0.38145
A48: Inventory | B48: 0.002 | D48: =+' wORKING CAPITAL'!E15*$B$48 -> 0.024 | E48: =+' wORKING CAPITAL'!F15*$B$48 -> 0.023922285 | F48: =+' wORKING CAPITAL'!G15*$B$48 -> 0.026530071 | G48: =+' wORKING CAPITAL'!H15*$B$48 -> 0.029477856 | H48: =+' wORKING CAPITAL'!I15*$B$48 -> 0.03891077 | I48: =+' wORKING CAPITAL'!J15*$B$48 -> 0.049522799 | J48: =+' wORKING CAPITAL'!K15*$B$48 -> 0.061313941 | K48: =+' wORKING CAPITAL'!L15*$B$48 -> 0.074284198 | ... M48: =+' wORKING CAPITAL'!N15*$B$48 -> 0.071454324
A49: Brokerage & Commission | B49: 0.005 | C49: Total Sales | D49: =B49*D29 -> 10.060176 | E49: =B49*E29 -> 10.060176 | F49: =B49*F29*1.25 -> 14.147122 | G49: =B49*G29*1.35 -> 16.976547 | H49: =B49*H29*1.5 -> 20.749113 | I49: =B49*I29*1.6 -> 24.144422 | J49: =B49*J29*1.8 -> 29.426014 | K49: =B49*K29*2 -> 35.210615 | L49: =B49*L29*3.5 -> 52.815923 | M49: =B49*M29*3.5 -> 52.815923 | V49: =MIN(2,#REF!,#REF!,#REF!,#REF!,#REF!,#REF!,#REF!,#REF!) -> #REF!
A50: Interest on Term Loan | D50: =Interest!I46 -> 254.71875 | E50: =Interest!I58 -> 240.1125 | F50: =Interest!I70 -> 217.7875 | G50: =Interest!I82 -> 186.675 | H50: =Interest!I94 -> 147.25 | I50: =Interest!I106 -> 99.0375 | J50: =Interest!I118 -> 45.125 | K50: =Interest!I130 -> 2.375 | L50: =Interest!I142 -> 0 | M50: =Interest!I150 -> 0
A51: Interest on Working Capital Loan | D51: =' wORKING CAPITAL'!E29 -> 0 | E51: =' wORKING CAPITAL'!F29 -> 0 | F51: =' wORKING CAPITAL'!G29 -> 0 | G51: =' wORKING CAPITAL'!H29 -> 0 | H51: =' wORKING CAPITAL'!I29 -> 0 | I51: =' wORKING CAPITAL'!J29 -> 0 | J51: =' wORKING CAPITAL'!K29 -> 0 | K51: =' wORKING CAPITAL'!L29 -> 0 | ... M51: =' wORKING CAPITAL'!N29 -> 0 | O51: wc loan
A53: Depreciation | D53: =depreciation!D53 -> 452.19406 | E53: =depreciation!E53 -> 452.19406 | F53: =depreciation!F53 -> 452.19406 | G53: =depreciation!G53 -> 452.19406 | H53: =depreciation!H53 -> 452.19406 | I53: =depreciation!I53 -> 452.19406 | J53: =depreciation!J53 -> 452.19406 | K53: =depreciation!K53 -> 452.19406 | ... M53: =depreciation!M53 -> 452.19406
A55: Total Operating Costs | D55: =SUM(D33:D54) -> 1463.5374 | E55: =SUM(E33:E54) -> 1463.8846 | F55: =SUM(F33:F54) -> 1618.0377 | G55: =SUM(G33:G54) -> 1714.4836 | H55: =SUM(H33:H54) -> 1802.3622 | I55: =SUM(I33:I54) -> 1889.1644 | J55: =SUM(J33:J54) -> 1953.1946 | K55: =SUM(K33:K54) -> 2035.9258 | ... M55: =SUM(M33:M54) -> #VALUE!
A59: Profit Before Tax | D59: =D29-D55 -> 548.49775 | E59: =E29-E55 -> 548.15057 | F59: =F29-F55 -> 645.50186 | G59: =G29-G55 -> 800.56031 | H59: =H29-H55 -> 964.18615 | I59: =I29-I55 -> 1128.8884 | J59: =J29-J55 -> 1316.3625 | K59: =K29-K55 -> 1485.1357 | ... M59: =M29-M55 -> #VALUE!
D60: =#REF! -> #REF!
A61: PBIT | D61: =D59+D51+D50 -> 803.2165 | E61: =E59+E51+E50 -> 788.26307 | F61: =F59+F51+F50 -> 863.28936 | G61: =G59+G51+G50 -> 987.23531 | H61: =H59+H51+H50 -> 1111.4361 | I61: =I59+I51+I50 -> 1227.9259 | J61: =J59+J51+J50 -> 1361.4875 | K61: =K59+K51+K50 -> 1487.5107 | ... M61: =M59+M51+M50 -> #VALUE!
A62: Provision For Tax being MAT | D62: =D59*0.35 -> 191.97421 | E62: =E59*0.35 -> 191.8527 | F62: =F59*0.35 -> 225.92565 | G62: =G59*0.35 -> 280.19611 | H62: =H59*0.35 -> 337.46515 | I62: =I59*0.35 -> 395.11093 | J62: =J59*0.35 -> 460.72688 | K62: =K59*0.35 -> 519.79749 | ... M62: =M59*0.35 -> #VALUE! | P62: =D62/D59*100 -> 35 | Q62: =E62/E59*100 -> 35 | R62: =F62/F59*100 -> 35 | S62: =G62/G59*100 -> 35 | T62: =H62/H59*100 -> 35 | U62: =I62/I59*100 -> 35 | V62: =J62/J59*100 -> 35 | W62: =K62/K59*100 -> 35
A63: Profit After Tax | D63: =D59-D62 -> 356.52354 | E63: =E59-E62 -> 356.29787 | F63: =F59-F62 -> 419.57621 | G63: =G59-G62 -> 520.3642 | H63: =H59-H62 -> 626.72099 | I63: =I59-I62 -> 733.77744 | J63: =J59-J62 -> 855.63564 | K63: =K59-K62 -> 965.33819 | ... M63: =M59-M62 -> #VALUE!
A64: Drawings | D64: =D63*10% -> 35.652354 | E64: =E63*10% -> 35.629787 | F64: =F63*10% -> 41.957621 | G64: =G63*10% -> 52.03642 | H64: =H63*10% -> 62.672099 | I64: =I63*10% -> 73.377744 | J64: =J63*10% -> 85.563564 | K64: =K63*10% -> 96.533819 | L64: =L63*0.175 -> #VALUE! | M64: =M63*0.175 -> #VALUE!
A65: Cumulative Reserve | D65: =D63-D64 -> 320.87118 | E65: =D65+E63-E64 -> 641.53927 | F65: =E65+F63-F64 -> 1019.1579 | G65: =F65+G63-G64 -> 1487.4856 | H65: =G65+H63-H64 -> 2051.5345 | I65: =H65+I63-I64 -> 2711.9342 | J65: =I65+J63-J64 -> 3482.0063 | K65: =J65+K63-K64 -> 4350.8107 | L65: =K65+L63-L64 -> #VALUE! | M65: =L65+M63-M64 -> #VALUE!
A66: Cash Profit | D66: =D59+D53-D62 -> 808.7176 | E66: =E59+E53-E62 -> 808.49193 | F66: =F59+F53-F62 -> 871.77027 | G66: =G59+G53-G62 -> 972.55826 | H66: =H59+H53-H62 -> 1078.9151 | I66: =I59+I53-I62 -> 1185.9715 | J66: =J59+J53-J62 -> 1307.8297 | K66: =K59+K53-K62 -> 1417.5323 | L66: =L59+L53 -> #VALUE! | M66: =M59+M53 -> #VALUE!
A67: % of Cash Profit | D67: =D66/D29*100 -> 40.194009 | E67: =E66/E29*100 -> 40.182794 | F67: =F66/F29*100 -> 38.513587 | G67: =G66/G29*100 -> 38.669633 | H67: =H66/H29*100 -> 38.998598 | I67: =I66/I29*100 -> 39.295917 | J67: =J66/J29*100 -> 40.000209 | K67: =K66/K29*100 -> 40.258662 | ... M67: =M66/M29*100 -> #VALUE!
A68: % of PAT | D68: =D63/D29*100 -> 17.719548 | E68: =E63/E29*100 -> 17.708332 | F68: =F63/F29*100 -> 18.536288 | G68: =G63/G29*100 -> 20.690064 | H68: =H63/H29*100 -> 22.653535 | I68: =I63/I29*100 -> 24.312943 | J68: =J63/J29*100 -> 26.169772 | K68: =K63/K29*100 -> 27.416113 | ... M68: =M63/M29*100 -> #VALUE!
A69: Retained Profit | D69: =D63 -> 356.52354 | E69: =E63 -> 356.29787 | F69: =F63 -> 419.57621 | G69: =G63 -> 520.3642 | H69: =H63 -> 626.72099 | I69: =I63 -> 733.77744 | J69: =J63 -> 855.63564 | K69: =K63 -> 965.33819 | ... M69: =M63 -> #VALUE!
D73: =D63/D29 -> 0.17719548 | E73: =E63/E29 -> 0.17708332 | F73: =F63/F29 -> 0.18536288 | G73: =G63/G29 -> 0.20690064 | H73: =H63/H29 -> 0.22653535 | I73: =I63/I29 -> 0.24312943 | J73: =J63/J29 -> 0.26169772 | K73: =K63/K29 -> 0.27416113 | ... M73: =M63/M29 -> #VALUE!
A111: PBIT | D111: =D61/D29*100 -> 39.9206 | E111: =E61/E29*100 -> 39.177401 | F111: =F61/F29*100 -> 38.138912 | G111: =G61/G29*100 -> 39.253203 | H111: =H61/H29*100 -> 40.174109 | I111: =I61/I29*100 -> 40.686031 | J111: =J61/J29*100 -> 41.641344 | K111: =K61/K29*100 -> 42.246086
A112: PBDIT | D112: =(D61+D53)/D29*100 -> 62.395061 | E112: =(E61+E53)/E29*100 -> 61.651862 | F112: =(F61+F53)/F29*100 -> 58.116211 | G112: =(G61+G53)/G29*100 -> 57.232772 | H112: =(H61+H53)/H29*100 -> 56.519172 | I112: =(I61+I53)/I29*100 -> 55.669005 | J112: =(J61+J53)/J29*100 -> 55.471781 | K112: =(K61+K53)/K29*100 -> 55.088635
A113: PAT | D113: =D63/D29*100 -> 17.719548 | E113: =E63/E29*100 -> 17.708332 | F113: =F63/F29*100 -> 18.536288 | G113: =G63/G29*100 -> 20.690064 | H113: =H63/H29*100 -> 22.653535 | I113: =I63/I29*100 -> 24.312943 | J113: =J63/J29*100 -> 26.169772 | K113: =K63/K29*100 -> 27.416113
A114: Cash Profit | D114: =(D63+D53)/D29*100 -> 40.194009 | E114: =(E63+E53)/E29*100 -> 40.182794 | F114: =(F63+F53)/F29*100 -> 38.513587 | G114: =(G63+G53)/G29*100 -> 38.669633 | H114: =(H63+H53)/H29*100 -> 38.998598 | I114: =(I63+I53)/I29*100 -> 39.295917 | J114: =(J63+J53)/J29*100 -> 40.000209 | K114: =(K63+K53)/K29*100 -> 40.258662
D162: =D59+D53 -> 1000.6918 | E162: =E59+E53 -> 1000.3446 | F162: =F59+F53 -> 1097.6959 | G162: =G59+G53 -> 1252.7544 | H162: =H59+H53 -> 1416.3802 | I162: =I59+I53 -> 1581.0824 | J162: =J59+J53 -> 1768.5566 | K162: =K59+K53 -> 1937.3297 | ... M162: =M59+M53 -> #VALUE!
D164: =D162/D29*100 -> 49.735304 | E164: =E162/E29*100 -> 49.718049 | F164: =F162/F29*100 -> 48.494665 | G164: =G162/G29*100 -> 49.810437 | H164: =H162/H29*100 -> 51.196655 | I164: =I162/I29*100 -> 52.387502 | J164: =J162/J29*100 -> 54.091625 | K164: =K162/K29*100 -> 55.021184 | ... M164: =M162/M29*100 -> #VALUE!
D166: =D53+D50+D59 -> 1255.4106 | E166: =E53+E50+E59 -> 1240.4571 | F166: =F53+F50+F59 -> 1315.4834 | G166: =G53+G50+G59 -> 1439.4294 | H166: =H53+H50+H59 -> 1563.6302 | I166: =I53+I50+I59 -> 1680.1199 | J166: =J53+J50+J59 -> 1813.6816 | K166: =K53+K50+K59 -> 1939.7047 | ... M166: =M53+M50+M59 -> #VALUE!
D168: =D166/D29*100 -> 62.395061 | E168: =E166/E29*100 -> 61.651862 | F168: =F166/F29*100 -> 58.116211 | G168: =G166/G29*100 -> 57.232772 | H168: =H166/H29*100 -> 56.519172 | I168: =I166/I29*100 -> 55.669005 | J168: =J166/J29*100 -> 55.471781 | K168: =K166/K29*100 -> 55.088635 | ... M168: =M166/M29*100 -> #VALUE!
D170: =D50+D53 -> 706.91281 | E170: =E50+E53 -> 692.30656 | F170: =F50+F53 -> 669.98156 | G170: =G50+G53 -> 638.86906 | H170: =H50+H53 -> 599.44406 | I170: =I50+I53 -> 551.23156 | J170: =J50+J53 -> 497.31906 | K170: =K50+K53 -> 454.56906 | ... M170: =M50+M53 -> 452.19406

Sheet B  S 
F2: =Pages!D29 -> 29
C4: ANNEXURE IV
C5: Projected Balance Sheet
L6: Rs. In Lakhs
B8: Year | D8: Construction Year 2 | E8: Year1 | F8: Year2 | G8: Year3 | H8: Year4 | I8: Year5 | J8: Year6 | K8: Year7 | L8: Year8 | M8: Year9 | N8: Year10
B10: ASSETS
B11: Fixed Assets (Gross Block) | D11: =depreciation!D137 -> 4263.8643 | E11: =D11+SUM('CASH FLOW'!E24:E28) -> 4263.8643 | F11: =E11+SUM('CASH FLOW'!F24:F28) -> 4263.8643 | G11: =F11+SUM('CASH FLOW'!G24:G28) -> 4358.8643 | H11: =G11+SUM('CASH FLOW'!H24:H28) -> 4368.8643 | I11: =H11+SUM('CASH FLOW'!I24:I28) -> 4488.8643 | J11: =I11+SUM('CASH FLOW'!J24:J28) -> 4598.8643 | K11: =J11+SUM('CASH FLOW'!K24:K28) -> 4713.8643 | L11: =K11+SUM('CASH FLOW'!L24:L28) -> 4813.8643 | ... N11: =M11+SUM('CASH FLOW'!N24:N28) -> 5013.8643 | Q11: =F11-E11 -> 0 | R11: =G11-F11 -> 95 | S11: =H11-G11 -> 10 | T11: =I11-H11 -> 120 | U11: =J11-I11 -> 110 | V11: =K11-J11 -> 115 | W11: =L11-K11 -> 100
B12: Less: Accumulated Depreciation | D12: 0 | E12: =depreciation!D139 -> 452.19406 | F12: =E12+depreciation!E139 -> 904.38812 | G12: =F12+depreciation!F139 -> 1356.5822 | H12: =G12+depreciation!G139 -> 1808.7762 | I12: =H12+depreciation!H139 -> 2260.9703 | J12: =I12+depreciation!I139 -> 2713.1644 | K12: =J12+depreciation!J139 -> 3165.3584 | L12: =K12+depreciation!K139 -> 3617.5525 | M12: =L12+depreciation!L139 -> 4069.7465 | N12: =M12+depreciation!M139 -> 4521.9406 | Q12: =Q11-SUM('CASH FLOW'!F24:F28) -> 0 | R12: =R11-SUM('CASH FLOW'!G24:G28) -> 0 | S12: =S11-SUM('CASH FLOW'!H24:H28) -> 0 | T12: =T11-SUM('CASH FLOW'!I24:I28) -> 0 | U12: =U11-SUM('CASH FLOW'!J24:J28) -> 0 | V12: =V11-SUM('CASH FLOW'!K24:K28) -> 0 | W12: =W11-SUM('CASH FLOW'!L24:L28) -> 0
B13: Fixed Assets ( W D V ) | D13: =D11-D12 -> 4263.8643 | E13: =E11-E12 -> 3811.6702 | F13: =F11-F12 -> 3359.4762 | G13: =G11-G12 -> 3002.2821 | H13: =H11-H12 -> 2560.088 | I13: =I11-I12 -> 2227.894 | J13: =J11-J12 -> 1885.6999 | K13: =K11-K12 -> 1548.5059 | ... N13: =N11-N12 -> 491.92369 | Q13: =M13-depreciation!L116 -> -1257.8326
B15: Current Assets
B16: Cash & Bank Balances | D16: ='CASH FLOW'!D45 -> 115.86828 | E16: ='CASH FLOW'!E45 -> 630.93352 | F16: ='CASH FLOW'!F45 -> 1022.485 | G16: ='CASH FLOW'!G45 -> 1155.8787 | H16: ='CASH FLOW'!H45 -> 1304.4236 | I16: ='CASH FLOW'!I45 -> 1430.8906 | J16: ='CASH FLOW'!J45 -> 1515.0788 | K16: ='CASH FLOW'!K45 -> 1654.8794 | ... N16: ='CASH FLOW'!N45 -> #VALUE! | Q16: Current Assets | R16: =SUM(E16:E18) -> 777.93352 | S16: =SUM(F16:F18) -> 1272.1116 | T16: =SUM(G16:G18) -> 1560.2674 | U16: =SUM(H16:H18) -> 1913.7444 | V16: =SUM(I16:I18) -> 2151.8442 | W16: =SUM(J16:J18) -> 2352.6562 | X16: =SUM(K16:K18) -> 2610.9275 | Y16: =SUM(L16:L18) -> 3443.3866
B17: Inventory & Receivables | D17: 0 | E17: =' wORKING CAPITAL'!E19 -> 37 | F17: =' wORKING CAPITAL'!F19 -> 39.626626 | G17: =' wORKING CAPITAL'!G19 -> 44.388704 | H17: =' wORKING CAPITAL'!H19 -> 49.320782 | I17: =' wORKING CAPITAL'!I19 -> 60.95361 | J17: =' wORKING CAPITAL'!J19 -> 77.577322 | K17: =' wORKING CAPITAL'!K19 -> 96.048113 | L17: =' wORKING CAPITAL'!L19 -> 116.36598 | ... N17: =' wORKING CAPITAL'!N19 -> 111.93299 | Q17: Current Liability | R17: =SUM(E31:E33) -> 197 | S17: =SUM(F31:F33) -> 318.31596 | T17: =SUM(G31:G33) -> 381.65908 | U17: =SUM(H31:H33) -> 504.61424 | V17: =SUM(I31:I33) -> 566.47112 | W17: =SUM(J31:J33) -> 628.68928 | X17: =SUM(K31:K33) -> 30.89454 | Y17: =SUM(L31:L33) -> 33.315211
B18: Other Current Assets | D18: 0 | E18: 110 | F18: =E18+100 -> 210 | G18: =F18+150 -> 360 | H18: =G18+200 -> 560 | I18: =H18+100 -> 660 | J18: =I18+100 -> 760 | K18: =J18+100 -> 860 | L18: =K18+200 -> 1060 | M18: =L18+5 -> 1065 | N18: =M18+5 -> 1070 | R18: =R16/R17 -> 3.9489011 | S18: =S16/S17 -> 3.9963803 | T18: =T16/T17 -> 4.0881181 | U18: =U16/U17 -> 3.7924899 | V18: =V16/V17 -> 3.798683 | W18: =W16/W17 -> 3.7421604 | X18: =X16/X17 -> 84.510969 | Y18: =Y16/Y17 -> 103.35779
B19: Loans & Advances / Non Current Assets | D19: 0 | E19: 60 | F19: =E19+100 -> 160 | G19: =F19+150 -> 310 | H19: =G19+200 -> 510 | I19: =H19+100 -> 610 | J19: =I19+200 -> 810 | K19: =J19+200 -> 1010 | L19: =K19+200 -> 1210 | M19: 375 | N19: 375
B22: TOTAL ASSETS | D22: =SUM(D13:D21) -> 4379.7326 | E22: =SUM(E13:E21) -> 4649.6038 | F22: =SUM(F13:F21) -> 4791.5878 | G22: =SUM(G13:G21) -> 4872.5495 | H22: =SUM(H13:H21) -> 4983.8325 | I22: =SUM(I13:I21) -> 4989.7382 | J22: =SUM(J13:J21) -> 5048.3561 | K22: =SUM(K13:K21) -> 5169.4334 | ... N22: =SUM(N13:N21) -> #VALUE!
B24: LIABILITIES
B26: Partners' Capital | D26: ='CAPITAL COST'!D46-'CAPITAL COST'!D38 -> 1163.8643 | E26: =D26+'CAPITAL COST'!D38 -> 1185.8643 | F26: =E26 -> 1185.8643 | G26: =F26 -> 1185.8643 | H26: =G26 -> 1185.8643 | I26: =H26 -> 1185.8643 | J26: =I26 -> 1185.8643 | K26: =J26 -> 1185.8643 | L26: =K26 -> 1185.8643 | M26: =L26 -> 1185.8643 | N26: =M26 -> 1185.8643
B27: Reserves & Surplus | D27: 0 | E27: ='P L '!D65 -> 320.87118 | F27: ='P L '!E65 -> 641.53927 | G27: ='P L '!F65 -> 1019.1579 | H27: ='P L '!G65 -> 1487.4856 | I27: ='P L '!H65 -> 2051.5345 | J27: ='P L '!I65 -> 2711.9342 | K27: ='P L '!J65 -> 3482.0063 | L27: ='P L '!K65 -> 4350.8107 | ... N27: ='P L '!M65 -> #VALUE!
B28: Secured Term Loan | D28: =Interest!C47 -> 2700 | E28: =Interest!G53-E31 -> 2430 | F28: =Interest!G65-F31 -> 2130 | G28: =Interest!G77-G31 -> 1770 | H28: =Interest!G89-H31 -> 1290 | I28: =Interest!G101-I31 -> 750 | J28: =Interest!G113-J31 -> 150 | K28: =Interest!G125-K31 -> 150 | L28: =Interest!G137-L31 -> 0 | M28: 0 | N28: 0
B29: Unsecured Loans | D29: ='CAPITAL COST'!D48 -> 400 | E29: =D29 -> 400 | F29: =E29 -> 400 | G29: =F29 -> 400 | H29: =G29 -> 400 | I29: =H29*0.8 -> 320 | J29: =I29*0.8 -> 256 | K29: =J29*0.8 -> 204.8 | L29: =K29*0.8 -> 163.84 | M29: =L29*0.8 -> 131.072 | N29: =M29*0.8 -> 104.8576
B30: Working Capital Loan | D30: 0 | E30: =' wORKING CAPITAL'!E27 -> 0 | F30: =' wORKING CAPITAL'!F27 -> 0 | G30: =' wORKING CAPITAL'!G27 -> 0 | H30: =' wORKING CAPITAL'!H27 -> 0 | I30: =' wORKING CAPITAL'!I27 -> 0 | J30: =' wORKING CAPITAL'!J27 -> 0 | K30: =' wORKING CAPITAL'!K27 -> 0 | L30: =' wORKING CAPITAL'!L27 -> 0 | ... N30: =' wORKING CAPITAL'!N27 -> 0
B31: Instalments Repayable Within one Yr | D31: 0 | E31: ='CASH FLOW'!F34 -> 180 | F31: ='CASH FLOW'!G34 -> 300 | G31: ='CASH FLOW'!H34 -> 360 | H31: ='CASH FLOW'!I34 -> 480 | I31: ='CASH FLOW'!J34 -> 540 | J31: ='CASH FLOW'!K34 -> 600 | K31: 0 | L31: ='CASH FLOW'!M34 -> 0 | M31: ='CASH FLOW'!N34 -> 0 | N31: ='CASH FLOW'!O34 -> 0
B32: Current Liabilities | D32: 0 | E32: =' wORKING CAPITAL'!E22 -> 15 | F32: =' wORKING CAPITAL'!F22 -> 15.565957 | G32: =' wORKING CAPITAL'!G22 -> 18.159076 | H32: =' wORKING CAPITAL'!H22 -> 20.364244 | I32: =' wORKING CAPITAL'!I22 -> 21.471123 | J32: =' wORKING CAPITAL'!J22 -> 22.939285 | K32: =' wORKING CAPITAL'!K22 -> 24.39454 | L32: =' wORKING CAPITAL'!L22 -> 26.065211 | ... N32: =' wORKING CAPITAL'!N22 -> #VALUE!
B33: Other Current Liabilities | D33: 0 | E33: 2 | F33: =E33+0.75 -> 2.75 | G33: =F33+0.75 -> 3.5 | H33: =G33+0.75 -> 4.25 | I33: =H33+0.75 -> 5 | J33: =I33+0.75 -> 5.75 | K33: =J33+0.75 -> 6.5 | L33: =K33+0.75 -> 7.25 | M33: =L33+0.75 -> 8 | N33: =M33+0.75 -> 8.75
B35: TOTAL LIABILITIES | D35: =SUM(D24:D34) -> 4263.8643 | E35: =SUM(E24:E34) -> 4533.7355 | F35: =SUM(F24:F34) -> 4675.7195 | G35: =SUM(G24:G34) -> 4756.6812 | H35: =SUM(H24:H34) -> 4867.9642 | I35: =SUM(I24:I34) -> 4873.8699 | J35: =SUM(J24:J34) -> 4932.4878 | K35: =SUM(K24:K34) -> 5053.5651 | ... N35: =SUM(N24:N34) -> #VALUE! | Q35: =D22-D35 -> 115.86828 | R35: =E22-E35 -> 115.86828 | S35: =F22-F35 -> 115.86828 | T35: =G22-G35 -> 115.86828 | U35: =H22-H35 -> 115.86828 | V35: =I22-I35 -> 115.86828 | W35: =J22-J35 -> 115.86828 | X35: =K22-K35 -> 115.86828
D37: ='CASH FLOW'!D44 -> 115.86828 | E37: ='CASH FLOW'!E44 -> 515.06524 | F37: ='CASH FLOW'!F44 -> 391.55148 | G37: ='CASH FLOW'!G44 -> 133.39369 | H37: ='CASH FLOW'!H44 -> 148.54493 | I37: ='CASH FLOW'!I44 -> 126.46701 | J37: ='CASH FLOW'!J44 -> 84.188204 | K37: ='CASH FLOW'!K44 -> 139.8006 | ... N37: ='CASH FLOW'!N44 -> #VALUE!
E38: =E26+E27 -> 1506.7355 | F38: =F26+F27 -> 1827.4036 | G38: =G26+G27 -> 2205.0221 | H38: =H26+H27 -> 2673.3499 | I38: =I26+I27 -> 3237.3988 | J38: =J26+J27 -> 3897.7985 | K38: =K26+K27 -> 4667.8706 | L38: =L26+L27 -> 5536.675 | ... N38: =N26+N27 -> #VALUE!
D40: =BS_ANLYSIS!J172 -> #REF! | E40: =BS_ANLYSIS!K172 -> #REF! | F40: =BS_ANLYSIS!L172 -> #REF! | G40: =BS_ANLYSIS!M172 -> #REF! | H40: =BS_ANLYSIS!N172 -> #REF! | I40: =BS_ANLYSIS!O172 -> #REF! | J40: =BS_ANLYSIS!P172 -> #REF! | K40: =BS_ANLYSIS!Q172 -> #REF! | ... N40: =BS_ANLYSIS!T172 -> 0
M41: =M26+M27 -> #VALUE! | N41: =N26+N27 -> #VALUE!
D42: =D22-D35 -> 115.86828 | E42: =E22-E35 -> 115.86828 | F42: =F22-F35 -> 115.86828 | G42: =G22-G35 -> 115.86828 | H42: =H22-H35 -> 115.86828 | I42: =I22-I35 -> 115.86828 | J42: =J22-J35 -> 115.86828 | K42: =K22-K35 -> 115.86828 | ... N42: =N22-N35 -> #VALUE!
B45: Difference | D45: =D22-D35 -> 115.86828 | E45: =E22-E35 -> 115.86828 | F45: =F22-F35 -> 115.86828 | G45: =G22-G35 -> 115.86828 | H45: =H22-H35 -> 115.86828 | I45: =I22-I35 -> 115.86828 | J45: =J22-J35 -> 115.86828 | K45: =K22-K35 -> 115.86828 | ... N45: =N22-N35 -> #VALUE!
G46: =G45-F45 -> -9.094947e-13 | H46: =H45-G45 -> 9.094947e-13 | I46: =I45-H45 -> -9.094947e-13 | J46: =J45-I45 -> 9.094947e-13 | K46: =K45-J45 -> -9.094947e-13 | L46: =L45-K45 -> 0

Sheet Finanacials
A4: Particulars | B4: FY 2017-18 | C4: FY 2018-19 | D4: FY-2019-20 | E4: FY-2020-21 | F4: FY-2021-22 | G4: FY-2022-23 | H4: FY-2023-24 | I4: FY-2024-25
A6: Sales | B6: ='P L '!D29 -> 2012.0352 | C6: ='P L '!E29 -> 2012.0352 | D6: ='P L '!F29 -> 2263.5395 | E6: ='P L '!G29 -> 2515.0439 | F6: ='P L '!H29 -> 2766.5483 | G6: ='P L '!I29 -> 3018.0527 | H6: ='P L '!J29 -> 3269.5571 | I6: ='P L '!K29 -> 3521.0615
A7: Other Income
A8: PBDIT | B8: ='P L '!D61+'P L '!D53 -> 1255.4106 | C8: ='P L '!E61+'P L '!E53 -> 1240.4571 | D8: ='P L '!F61+'P L '!F53 -> 1315.4834 | E8: ='P L '!G61+'P L '!G53 -> 1439.4294 | F8: ='P L '!H61+'P L '!H53 -> 1563.6302 | G8: ='P L '!I61+'P L '!I53 -> 1680.1199 | H8: ='P L '!J61+'P L '!J53 -> 1813.6816 | I8: ='P L '!K61+'P L '!K53 -> 1939.7047
A9: PBT | B9: ='P L '!D59 -> 548.49775 | C9: ='P L '!E59 -> 548.15057 | D9: ='P L '!F59 -> 645.50186 | E9: ='P L '!G59 -> 800.56031 | F9: ='P L '!H59 -> 964.18615 | G9: ='P L '!I59 -> 1128.8884 | H9: ='P L '!J59 -> 1316.3625 | I9: ='P L '!K59 -> 1485.1357
A10: PAT | B10: ='P L '!D63 -> 356.52354 | C10: ='P L '!E63 -> 356.29787 | D10: ='P L '!F63 -> 419.57621 | E10: ='P L '!G63 -> 520.3642 | F10: ='P L '!H63 -> 626.72099 | G10: ='P L '!I63 -> 733.77744 | H10: ='P L '!J63 -> 855.63564 | I10: ='P L '!K63 -> 965.33819
A11: Partners Capital | B11: ='B S '!D26 -> 1163.8643 | C11: ='B S '!E26 -> 1185.8643 | D11: ='B S '!F26 -> 1185.8643 | E11: ='B S '!G26 -> 1185.8643 | F11: ='B S '!H26 -> 1185.8643 | G11: ='B S '!I26 -> 1185.8643 | H11: ='B S '!J26 -> 1185.8643 | I11: ='B S '!K26 -> 1185.8643
A12: TNW | B12: ='B S '!D26+'B S '!D27 -> 1163.8643 | C12: ='B S '!E26+'B S '!E27 -> 1506.7355 | D12: ='B S '!F26+'B S '!F27 -> 1827.4036 | E12: ='B S '!G26+'B S '!G27 -> 2205.0221 | F12: ='B S '!H26+'B S '!H27 -> 2673.3499 | G12: ='B S '!I26+'B S '!I27 -> 3237.3988 | H12: ='B S '!J26+'B S '!J27 -> 3897.7985 | I12: ='B S '!K26+'B S '!K27 -> 4667.8706
A13: Investment in group company | B13: - | C13: - | D13: - | E13: - | F13: - | G13: - | H13: - | I13: -
A14: Effective TNW | B14: =B12 -> 1163.8643 | C14: =C12 -> 1506.7355 | D14: =D12 -> 1827.4036 | E14: =E12 -> 2205.0221 | F14: =F12 -> 2673.3499 | G14: =G12 -> 3237.3988 | H14: =H12 -> 3897.7985 | I14: =I12 -> 4667.8706
A15: Term Liabilities | B15: ='B S '!E28+'B S '!E29 -> 2830 | C15: ='B S '!F28+'B S '!F29 -> 2530 | D15: ='B S '!G28+'B S '!G29 -> 2170 | E15: ='B S '!H28+'B S '!H29 -> 1690 | F15: ='B S '!I28+'B S '!I29 -> 1070 | G15: ='B S '!J28+'B S '!J29 -> 406 | H15: ='B S '!K28+'B S '!K29 -> 354.8 | I15: ='B S '!L28+'B S '!L29 -> 163.84
A16: Gross Block | B16: ='B S '!E11 -> 4263.8643 | C16: ='B S '!F11 -> 4263.8643 | D16: ='B S '!G11 -> 4358.8643 | E16: ='B S '!H11 -> 4368.8643 | F16: ='B S '!I11 -> 4488.8643 | G16: ='B S '!J11 -> 4598.8643 | H16: ='B S '!K11 -> 4713.8643 | I16: ='B S '!L11 -> 4813.8643
A17: Net Block | B17: ='B S '!E13 -> 3811.6702 | C17: ='B S '!F13 -> 3359.4762 | D17: ='B S '!G13 -> 3002.2821 | E17: ='B S '!H13 -> 2560.088 | F17: ='B S '!I13 -> 2227.894 | G17: ='B S '!J13 -> 1885.6999 | H17: ='B S '!K13 -> 1548.5059 | I17: ='B S '!L13 -> 1196.3118
A18: Current Assets | B18: ='B S '!R16 -> 777.93352 | C18: ='B S '!S16 -> 1272.1116 | D18: ='B S '!T16 -> 1560.2674 | E18: ='B S '!U16 -> 1913.7444 | F18: ='B S '!V16 -> 2151.8442 | G18: ='B S '!W16 -> 2352.6562 | H18: ='B S '!X16 -> 2610.9275 | I18: ='B S '!Y16 -> 3443.3866
A19: Current Liabilities | B19: ='B S '!R17 -> 197 | C19: ='B S '!S17 -> 318.31596 | D19: ='B S '!T17 -> 381.65908 | E19: ='B S '!U17 -> 504.61424 | F19: ='B S '!V17 -> 566.47112 | G19: ='B S '!W17 -> 628.68928 | H19: ='B S '!X17 -> 30.89454 | I19: ='B S '!Y17 -> 33.315211
A20: Current Ratio | B20: =B18/B19 -> 3.9489011 | C20: =C18/C19 -> 3.9963803 | D20: =D18/D19 -> 4.0881181 | E20: =E18/E19 -> 3.7924899 | F20: =F18/F19 -> 3.798683 | G20: =G18/G19 -> 3.7421604 | H20: =H18/H19 -> 84.510969 | I20: =I18/I19 -> 103.35779
A21: TOL/TNW | B21: =(B15+B19)/B12 -> 2.6008187 | C21: =(C15+C19)/C12 -> 1.8903889 | D21: =(D15+D19)/D12 -> 1.3963304 | E21: =(E15+E19)/E12 -> 0.99527991 | F21: =(F15+F19)/F12 -> 0.61214251 | G21: =(G15+G19)/G12 -> 0.31960513 | H21: =(H15+H19)/H12 -> 0.098951893 | I21: =(I15+I19)/I12 -> 0.042236649
A22: DER | B22: =B15/B14 -> 2.431555 | C22: =C15/C14 -> 1.6791269 | D22: =D15/D14 -> 1.1874772 | E22: =E15/E14 -> 0.76643221 | F22: =F15/F14 -> 0.40024689 | G22: =G15/G14 -> 0.12540932 | H22: =H15/H14 -> 0.091025741 | I22: =I15/I14 -> 0.035099516

Sheet CASH FLOW
E2: =Pages!D31 -> 31
E4: ANNEXURE VI
E5: Projected Cash Flow
L6: Rs. In Lakhs
B7: Year | D7: Construction | E7: Year 1 | F7: Year 2 | G7: Year 3 | H7: Year 4 | I7: Year 5 | J7: Year 6 | K7: Year 7 | L7: Year 8 | M7: Year 9 | N7: Year 10
B9: CASH INFLOW
B11: Promoters Contribution/Investment Subsidy | D11: ='CAPITAL COST'!D46-'CAPITAL COST'!D38 -> 1163.8643 | E11: ='CAPITAL COST'!D38 -> 22 | F11: 0 | G11: 0 | H11: 0 | I11: 0 | J11: 0 | K11: 0 | L11: 0 | M11: 0 | N11: 0
B12: Profit before Interest & Taxes But After Depreciation | D12: 0 | E12: ='P L '!D61 -> 803.2165 | F12: ='P L '!E61 -> 788.26307 | G12: ='P L '!F61 -> 863.28936 | H12: ='P L '!G61 -> 987.23531 | I12: ='P L '!H61 -> 1111.4361 | J12: ='P L '!I61 -> 1227.9259 | K12: ='P L '!J61 -> 1361.4875 | L12: ='P L '!K61 -> 1487.5107 | ... N12: ='P L '!M61 -> #VALUE!
B13: Depreciation | D13: 0 | E13: ='P L '!D53 -> 452.19406 | F13: ='P L '!E53 -> 452.19406 | G13: ='P L '!F53 -> 452.19406 | H13: ='P L '!G53 -> 452.19406 | I13: ='P L '!H53 -> 452.19406 | J13: ='P L '!I53 -> 452.19406 | K13: ='P L '!J53 -> 452.19406 | L13: ='P L '!K53 -> 452.19406 | ... N13: ='P L '!M53 -> 452.19406
B14: Amortizations | D14: 0 | E14: =+'P L '!D52 -> 0 | F14: =+'P L '!E52 -> 0 | G14: =+'P L '!F52 -> 0 | H14: =+'P L '!G52 -> 0 | I14: =+'P L '!H52 -> 0 | J14: =+'P L '!I52 -> 0 | K14: =+'P L '!J52 -> 0 | L14: =+'P L '!K52 -> 0 | ... N14: =+'P L '!M52 -> 0
B15: Increase in Term Loan | D15: ='CAPITAL COST'!D50 -> 2700 | E15: 0 | F15: 0 | G15: 0 | H15: 0 | I15: 0 | J15: 0 | K15: 0 | L15: 0 | M15: 0 | N15: 0
B16: Increase in Unsecured Loans | D16: ='B S '!D29 -> 400 | E16: 0 | F16: 0 | G16: 0 | H16: 0 | I16: 0 | J16: 0 | K16: 0 | L16: 0 | M16: 0 | N16: 0
B17: Increase in Working Capital Loan | D17: 0 | E17: =' wORKING CAPITAL'!E33 -> 0 | F17: =' wORKING CAPITAL'!F33 -> 0 | G17: =' wORKING CAPITAL'!G33 -> 0 | H17: =' wORKING CAPITAL'!H33 -> 0 | I17: =' wORKING CAPITAL'!I33 -> 0 | J17: =' wORKING CAPITAL'!J33 -> 0 | K17: =' wORKING CAPITAL'!K33 -> 0 | L17: =' wORKING CAPITAL'!L33 -> 0 | ... N17: =' wORKING CAPITAL'!N33 -> 0
B18: Increase in Current Liabilities | D18: 0 | E18: =' wORKING CAPITAL'!E32+'B S '!E33 -> 17 | F18: =' wORKING CAPITAL'!F32+'B S '!F33-'B S '!E33 -> 1.3159569 | G18: =' wORKING CAPITAL'!G32+'B S '!G33-'B S '!F33 -> 3.3431194 | H18: =' wORKING CAPITAL'!H32+'B S '!H33-'B S '!G33 -> 2.9551677 | I18: =' wORKING CAPITAL'!I32+'B S '!I33-'B S '!H33 -> 1.8568793 | J18: =' wORKING CAPITAL'!J32+'B S '!J33-'B S '!I33 -> 2.2181614 | K18: =' wORKING CAPITAL'!K32+'B S '!K33-'B S '!J33 -> 2.2052555 | L18: =' wORKING CAPITAL'!L32+'B S '!L33-'B S '!K33 -> 2.4206708 | M18: =' wORKING CAPITAL'!M32+'B S '!M33-'B S '!L33 -> #VALUE! | N18: =' wORKING CAPITAL'!N32+'B S '!N33-'B S '!M33 -> #VALUE!
B20: TOTAL INFLOWS | D20: =SUM(D9:D19) -> 4263.8643 | E20: =SUM(E9:E19) -> 1294.4106 | F20: =SUM(F9:F19) -> 1241.7731 | G20: =SUM(G9:G19) -> 1318.8265 | H20: =SUM(H9:H19) -> 1442.3845 | I20: =SUM(I9:I19) -> 1565.4871 | J20: =SUM(J9:J19) -> 1682.3381 | K20: =SUM(K9:K19) -> 1815.8868 | ... N20: =SUM(N9:N19) -> #VALUE!
B22: CASH OUTFLOWS
B24: Land Cost & Development | D24: ='CAPITAL COST'!D12 -> 0 | E24: 0 | F24: 0 | G24: 0 | H24: 0 | I24: 0 | J24: 0 | K24: 0 | L24: 0 | M24: 0 | N24: 0
B25: Building & Civil Works | D25: ='CAPITAL COST'!D14 -> 2878.9368 | E25: 0 | F25: 0 | G25: 50 | H25: 0 | I25: 60 | J25: 50 | K25: 55 | L25: 45 | M25: 40 | N25: 50
B26: Furniture & Accessories | D26: ='CAPITAL COST'!D16 -> 375.3 | E26: 0 | F26: 0 | G26: 35 | H26: 0 | I26: 45 | J26: 45 | K26: 45 | L26: 40 | M26: 35 | N26: 45
B27: Electical Installation | D27: ='CAPITAL COST'!D18 -> 140.5 | E27: 0 | F27: 0 | G27: 0 | H27: 0 | I27: 0 | J27: 0 | K27: 0 | L27: 0 | M27: 0 | N27: 0
B28: Plant & Machinery | D28: ='CAPITAL COST'!D20 -> 467.53924 | E28: 0 | F28: 0 | G28: 10 | H28: 10 | I28: 15 | J28: 15 | K28: 15 | L28: 15 | M28: 10 | N28: 20
B29: Preliminary & Capital Issue Expenses | D29: ='CAPITAL COST'!D22 -> 285.72 | E29: 0 | F29: 0 | G29: 0 | H29: 0 | I29: 0 | J29: 0 | K29: 0 | L29: 0 | M29: 0 | N29: 0
B30: Increase In Inventory | D30: 0 | E30: =' wORKING CAPITAL'!E30 -> 12 | F30: =' wORKING CAPITAL'!F30 -> -0.0388575 | G30: =' wORKING CAPITAL'!G30 -> 1.3038928 | H30: =' wORKING CAPITAL'!H30 -> 1.4738928 | I30: =' wORKING CAPITAL'!I30 -> 4.716457 | J30: =' wORKING CAPITAL'!J30 -> 5.3060141 | K30: =' wORKING CAPITAL'!K30 -> 5.8955713 | L30: =' wORKING CAPITAL'!L30 -> 6.4851284 | ... N30: =' wORKING CAPITAL'!N30 -> 0.35373428
B31: Increase in Receivables | D31: 0 | E31: =' wORKING CAPITAL'!E31 -> 25 | F31: =' wORKING CAPITAL'!F31 -> 2.6654834 | G31: =' wORKING CAPITAL'!G31 -> 3.4581854 | H31: =' wORKING CAPITAL'!H31 -> 3.4581854 | I31: =' wORKING CAPITAL'!I31 -> 6.9163708 | J31: =' wORKING CAPITAL'!J31 -> 11.317698 | K31: =' wORKING CAPITAL'!K31 -> 12.57522 | L31: =' wORKING CAPITAL'!L31 -> 13.832742 | ... N31: =' wORKING CAPITAL'!N31 -> 0.75451318
B32: Increase in Other Current Assets | D32: 0 | E32: ='B S '!E18 -> 110 | F32: ='B S '!F18-'B S '!E18 -> 100 | G32: ='B S '!G18-'B S '!F18 -> 150 | H32: ='B S '!H18-'B S '!G18 -> 200 | I32: ='B S '!I18-'B S '!H18 -> 100 | J32: ='B S '!J18-'B S '!I18 -> 100 | K32: ='B S '!K18-'B S '!J18 -> 100 | L32: ='B S '!L18-'B S '!K18 -> 200 | M32: ='B S '!M18-'B S '!L18 -> 5 | N32: ='B S '!N18-'B S '!M18 -> 5
B33: Increase in NCA / L&A | D33: 0 | E33: ='B S '!E19 -> 60 | F33: ='B S '!F19-'B S '!E19 -> 100 | G33: ='B S '!G19-'B S '!F19 -> 150 | H33: ='B S '!H19-'B S '!G19 -> 200 | I33: ='B S '!I19-'B S '!H19 -> 100 | J33: ='B S '!J19-'B S '!I19 -> 200 | K33: ='B S '!K19-'B S '!J19 -> 200 | L33: ='B S '!L19-'B S '!K19 -> 200 | M33: ='B S '!M19-'B S '!L19 -> -835 | N33: ='B S '!N19-'B S '!M19 -> 0
B34: Repayment of Term Loan | D34: 0 | E34: =Interest!J46 -> 90 | F34: =Interest!J58 -> 180 | G34: =Interest!J70 -> 300 | H34: =Interest!J82 -> 360 | I34: =Interest!J94 -> 480 | J34: =Interest!J106 -> 540 | K34: =Interest!J118 -> 600 | L34: =Interest!J130 -> 150 | M34: =Interest!J142 -> 0 | N34: =Interest!J150 -> 0
B35: Repayment of Unsecured Loans | D35: 0 | E35: 0 | F35: ='B S '!E29-'B S '!F29 -> 0 | G35: ='B S '!F29-'B S '!G29 -> 0 | H35: ='B S '!G29-'B S '!H29 -> 0 | I35: ='B S '!H29-'B S '!I29 -> 80 | J35: ='B S '!I29-'B S '!J29 -> 64 | K35: ='B S '!J29-'B S '!K29 -> 51.2 | L35: ='B S '!K29-'B S '!L29 -> 40.96 | M35: ='B S '!L29-'B S '!M29 -> 32.768 | N35: ='B S '!M29-'B S '!N29 -> 26.2144
B36: Interest on Term Loan | D36: 0 | E36: ='P L '!D50 -> 254.71875 | F36: ='P L '!E50 -> 240.1125 | G36: ='P L '!F50 -> 217.7875 | H36: ='P L '!G50 -> 186.675 | I36: ='P L '!H50 -> 147.25 | J36: ='P L '!I50 -> 99.0375 | K36: ='P L '!J50 -> 45.125 | L36: ='P L '!K50 -> 2.375 | ... N36: ='P L '!M50 -> 0
B37: Interest on Working Capital | D37: 0 | E37: ='P L '!D51 -> 0 | F37: ='P L '!E51 -> 0 | G37: ='P L '!F51 -> 0 | H37: ='P L '!G51 -> 0 | I37: ='P L '!H51 -> 0 | J37: ='P L '!I51 -> 0 | K37: ='P L '!J51 -> 0 | L37: ='P L '!K51 -> 0 | ... N37: ='P L '!M51 -> 0
B38: Provision for Tax | D38: 0 | E38: ='P L '!D62 -> 191.97421 | F38: ='P L '!E62 -> 191.8527 | G38: ='P L '!F62 -> 225.92565 | H38: ='P L '!G62 -> 280.19611 | I38: ='P L '!H62 -> 337.46515 | J38: ='P L '!I62 -> 395.11093 | K38: ='P L '!J62 -> 460.72688 | L38: ='P L '!K62 -> 519.79749 | ... N38: ='P L '!M62 -> #VALUE!
B39: Drawings | D39: =0 -> 0 | E39: ='P L '!D64 -> 35.652354 | F39: ='P L '!E64 -> 35.629787 | G39: ='P L '!F64 -> 41.957621 | H39: ='P L '!G64 -> 52.03642 | I39: ='P L '!H64 -> 62.672099 | J39: ='P L '!I64 -> 73.377744 | K39: ='P L '!J64 -> 85.563564 | L39: ='P L '!K64 -> 96.533819 | ... N39: ='P L '!M64 -> #VALUE!
B41: TOTAL OUTFLOWS | D41: =SUM(D21:D40) -> 4147.996 | E41: =SUM(E21:E40) -> 779.34532 | F41: =SUM(F21:F40) -> 850.22161 | G41: =SUM(G21:G40) -> 1185.4328 | H41: =SUM(H21:H40) -> 1293.8396 | I41: =SUM(I21:I40) -> 1439.0201 | J41: =SUM(J21:J40) -> 1598.1499 | K41: =SUM(K21:K40) -> 1676.0862 | ... N41: =SUM(N21:N40) -> #VALUE!
B43: Opening Balance | D43: 0 | E43: =D45 -> 115.86828 | F43: =E45 -> 630.93352 | G43: =F45 -> 1022.485 | H43: =G45 -> 1155.8787 | I43: =H45 -> 1304.4236 | J43: =I45 -> 1430.8906 | K43: =J45 -> 1515.0788 | L43: =K45 -> 1654.8794 | ... N43: =M45 -> #VALUE!
B44: Surplus /Deficit for the year | D44: =D20-D41 -> 115.86828 | E44: =E20-E41 -> 515.06524 | F44: =F20-F41 -> 391.55148 | G44: =G20-G41 -> 133.39369 | H44: =H20-H41 -> 148.54493 | I44: =I20-I41 -> 126.46701 | J44: =J20-J41 -> 84.188204 | K44: =K20-K41 -> 139.8006 | ... N44: =N20-N41 -> #VALUE!
B45: Closing Balance | D45: =D43+D44 -> 115.86828 | E45: =E43+E44 -> 630.93352 | F45: =F43+F44 -> 1022.485 | G45: =G43+G44 -> 1155.8787 | H45: =H43+H44 -> 1304.4236 | I45: =I43+I44 -> 1430.8906 | J45: =J43+J44 -> 1515.0788 | K45: =K43+K44 -> 1654.8794 | ... N45: =N43+N44 -> #VALUE!
E52: ='B S '!E16 -> 630.93352 | F52: ='B S '!F16 -> 1022.485 | G52: ='B S '!G16 -> 1155.8787 | H52: ='B S '!H16 -> 1304.4236 | I52: ='B S '!I16 -> 1430.8906 | J52: ='B S '!J16 -> 1515.0788 | K52: ='B S '!K16 -> 1654.8794 | L52: ='B S '!L16 -> 2267.0207 | ... N52: ='B S '!N16 -> #VALUE!

Sheet ASSETS
E2: =Pages!D42 -> 37
E4: APPENDIX- I
I5: (Rs. in Lacs)
A6: (i) | B6: CIVIL WORKS (INCLUDING SANITARY INSTALLATIONS)
B7: ( Considered as per estimate)
B9: (a) Civil Works (As Per Estimate) | I9: =F21/10^5 -> 2423.5358 | J9: 2423.54
B10: Sl.No | C10: Floor | D10: Area (In sqm.) | E10: Rate Rs/Sqm | F10: Amount in Rs
B11: 1 | C11: Basement Floor | D11: 3110 | E11: 20502.776 | F11: =D11*E11 -> 63763633
B12: =B11+1 -> 2 | C12: Ground Floor | D12: 3014 | E12: 12200.774 | F12: =D12*E12 -> 36773133
B13: =B12+1 -> 3 | C13: First Floor | D13: 1039 | E13: 12198.307 | F13: =D13*E13 -> 12674041
B14: =B13+1 -> 4 | C14: Second Floor | D14: 1892.8 | E14: 12202.908 | F14: =D14*E14 -> 23097664
B15: =B14+1 -> 5 | C15: Third Floor | D15: 1430.91 | E15: 12197.34 | F15: =D15*E15 -> 17453295
B16: =B15+1 -> 6 | C16: Fourth Floor | D16: 1365 | E16: 12343.414 | F16: =D16*E16 -> 16848760
B17: =B16+1 -> 7 | C17: Fifth Floor | D17: 1430 | E17: 12355.443 | F17: =D17*E17 -> 17668283
B18: =B17+1 -> 8 | C18: Sixth Floor | D18: 1430 | E18: 12355.443 | F18: =D18*E18 -> 17668283
B19: =B18+1 -> 9 | C19: Seventh Floor | D19: 1430 | E19: 12355.443 | F19: =D19*E19 -> 17668283
B20: =B19+1 -> 10 | C20: Eighth Floor | D20: 1430 | E20: 13103.637 | F20: =D20*E20 -> 18738201
C21: Total | D21: =SUM(D11:D20) -> 17571.71 | F21: =SUM(F11:F20) -> 2.4235358e+08
B24: Plumbing Works | I24: 0
B25: Centering, Shuttering, Strutting, propping etc | I25: 0
B26: Interior Civil Works (As Per Estimate) | I26: =F32/10^5 -> 375.3 | J26: 314.4 | K26: =I26-J26 -> 60.9
B27: (B) | C27: Extra Items | P27: =61000 -> 61000
B28: 1 | C28: For Interior work including all material and making
C29: (Flase ceiling, Furniture, Electrical & Ac system)
C30: 97650 Sqft@ 600 Rs/ Sqft | F30: =58590000 -> 58590000
C31: Less : AC as per Quotation included Below | F31: =I60*100000 -> 21060000
C32: 97650 Sqft@ 600 Rs/ Sqft | F32: =F30-F31 -> 37530000
B34: Service | I34: =(F38+F42)/10^5 -> 291.6 | J34: 375.67 | K34: =I34-J34 -> -84.07
B35: (C) | C35: For Internal water Supply @ 5% civil work | F35: =12117678.83*0 -> 0 | G35: as per Quotation included Below
C36: For Sanitary installation @ 8% of civil work | F36: =19388286.13*0 -> 0 | G36: as per Quotation included Below
C37: For Fire Fighting (2.5% of civil cost) | F37: =6058839.41*0 -> 0 | G37: as per Quotation included Below
F38: =SUM(F35:F37) -> 0
B39: ( C) | C39: (As PerSupplier-Ashi Associates)
C40: Plumbing ,Sanitary , Rain Water Harvesting Work | F40: =Details!F37 -> 23660000
C41: Fire Fighting Work | F41: =Details!F42 -> 5500000
F42: =SUM(F40:F41) -> 29160000
I47: =SUM(I9:I39) -> 3090.4358 | J47: =SUM(J9:J39) -> 3113.61 | K47: =I47-J47 -> -23.174234 | L47: =I47+I62+I92+I82 -> 3862.276 | M47: =J47+J62+J92+J82 -> 4185.91
A49: (II) | B49: DETAILS OF PLANT & MACHINERIES
B50: ( Considered as per estimate)
B52: Volvo Penta Genset | I52: 0
A54: (a) | B54: Elevator (Supplier - Kone Elevator India Pvt. Ltd.) | I54: =Details!G52/10^5 -> 120.29996 | J54: 120.3 | K54: =I54-J54 -> -3.84e-05
A55: (b) | B55: Kitchen Equipments (Supplier- Vsg Equipment) | I55: =Details!G130/10^5 -> 110.67928 | J55: 177.92 | K55: =I55-J55 -> -67.24072
A57: (c) | B57: Wastewater Engineering Services (Supplier - Aquasolution) | I57: =Details!E149/10^5 -> 25.96 | J57: 25.96 | K57: =I57-J57 -> 0
A59: (d) | B59: Lift (Taken as per Quotation Above) | I59: =Details!E151/10^5*0 -> 0 | J59: 0
A60: (e) | B60: Air Conditioning (Supplier-Ashi Associates) | I60: =Details!F160/10^5 -> 210.6 | J60: 271.5 | K60: =I60-J60 -> -60.9
I62: =I52+I55+I57+I54+I59+I60 -> 467.53924 | J62: =J52+J55+J57+J54+J59+J60 -> 595.68
A64: (III) | B64: DETAILS OF MISCELLANEOUS FIXED ASSETS / FURNITURES & FIXTURES
B65: ( Considered as per estimate)
M66: =I67+I69+I57+I54+I55-72+3675.2 -> 3860.1392
A67: (a) | B67: LED TV (Sky Vision) | I67: =Details!G171/10^5*0 -> 0 | J67: 110 | K67: =I67-J67 -> -110
A69: (b) | B69: Volvo Penta Genset (Inframech Power Solutions Private Limited) | I69: =Details!F179/10^5*0 -> 0 | J69: 148.5 | K69: =I69-J69 -> -148.5
A71: (c) | B71: BPL LED 55" UD5310 (Including GST) (Sky Vision) (Supplier-Ashi Associates) | I71: =((25781.25*150)*128%)/10^5 -> 49.5 | J71: 0 | K71: =I71-J71 -> 49.5
A72: (d) | B72: 750 KVA at 0.8 pf 415V 50Hz 3-ø(Genset) | I72: =Details!F187/10^5 -> 91 | J72: 0 | K72: =I72-J72 -> 91
B74: CCTV system | I74: 0
B76: Fitness Equipments | I76: 0
B78: Furniture & Other Interior Works | I78: 0
I80: 0
I82: =SUM(I67:I80) -> 140.5 | J82: =SUM(J67:J80) -> 258.5 | K82: =I82-J82 -> -118
A84: (IV) | B84: ELECTRIFICATIONS & ELECTRICAL INSTALLATIONS
B85: ( Considered as per estimate)
A86: (a) | B86: External & Internal Electrification (Supplier-Ashi Associates) | I86: =F89/10^5 -> 163.801 | J86: 218.12 | K86: =I86-J86 -> -54.319
B88: Electrical Work | F88: =Details!F222 -> 16380100
F89: =SUM(F88:F88) -> 16380100
A90: (b) | B90: For Electrification @9% of Civil works(As Per Estimate) Reduced due to Quotation above | I90: =Details!F234/10^5*0 -> 0
I92: =SUM(I86:I91) -> 163.801 | J92: =SUM(J86:J91) -> 218.12 | K92: =I92-J92 -> -54.319

Sheet details of fixed assets  
C2: (37)
C4: APPENDIX 2
C5: COMPUTATION OF FURNITURE AND OTHER ACCESSORIES COST
B7: Estimate for Other Items
A9: I | B9: Furniture/ accessories for 1 no. guest room with double bed
A10: a | B10: Furniture for 42 twin occupancy rooms | C10: Qnty. | D10: Unit | E10: Rate | F10: Amount
E11: ( in Rs.) | F11: ( in Rs.)
A12: 1 | B12: Bed(3'' 1/2 '' x 6" 1/2") | C12: 12 | D12: Each | E12: 15000 | F12: =C12*E12 -> 180000
A13: =A12+1 -> 2 | B13: Bed(6'' x 6" 1/2") | C13: 34 | D13: Each | E13: =25000 -> 25000 | F13: =C13*E13 -> 850000
A14: =A13+1 -> 3 | B14: Dfolding Bed(Extra Bed) | C14: 20 | D14: Each | E14: 2500 | F14: =C14*E14 -> 50000
A15: =A14+1 -> 4 | B15: Panel - Leather & Laminate | C15: 40 | D15: Each | E15: 55000 | F15: =C15*E15 -> 2200000
A16: =A15+1 -> 5 | B16: Sofa ( 2 Seater) | C16: 40 | D16: Each | E16: 15000 | F16: =C16*E16 -> 600000
A17: =A16+1 -> 6 | B17: Sofa ( 3 Seater) | C17: 9 | D17: Each | E17: 25000 | F17: =C17*E17 -> 225000
A18: =A17+1 -> 7 | B18: Chair | C18: 40 | D18: Each | E18: 6000 | F18: =C18*E18 -> 240000
A19: =A18+1 -> 8 | B19: Coffee Table | C19: 40 | D19: Each | E19: 7000 | F19: =C19*E19 -> 280000
A20: =A19+1 -> 9 | B20: Side Table | C20: 80 | D20: Each | E20: 8500 | F20: =C20*E20 -> 680000
A21: =A20+1 -> 10 | B21: Cupboard | C21: 40 | D21: Each | E21: 30000 | F21: =C21*E21 -> 1200000
A22: =A21+1 -> 11 | B22: Study Table / Dress | C22: 40 | D22: Each | E22: 15000 | F22: =C22*E22 -> 600000
A23: =A22+1 -> 12 | B23: Mirror | C23: 40 | D23: Each | E23: 5000 | F23: =C23*E23 -> 200000
A24: =A23+1 -> 13 | B24: Curtains / Blinds | C24: 40 | D24: Each | E24: 15000 | F24: =C24*E24 -> 600000
A25: =A24+1 -> 14 | B25: Mattress (3" 1/2" x 6" 1/2") | C25: 12 | D25: Each | E25: 10000 | F25: =C25*E25 -> 120000
A26: =A25+1 -> 15 | B26: Mattress (6" x 6" 1/2") | C26: 34 | D26: Each | E26: =20000 -> 20000 | F26: =C26*E26 -> 680000
A27: =A26+1 -> 16 | B27: Pillows / Cushions (2 per bed) | C27: 160 | D27: Each | E27: 700 | F27: =C27*E27 -> 112000 | I27: =42*4 -> 168
A28: =A27+1 -> 17 | B28: Blanket | C28: 160 | D28: Each | E28: 5000 | F28: =C28*E28 -> 800000
A29: =A28+1 -> 18 | B29: Plasma TV | C29: 50 | D29: Each | E29: 35000 | F29: =C29*E29 -> 1750000
A30: =A29+1 -> 19 | B30: Refrigerator | C30: 40 | D30: Each | E30: 10000 | F30: =C30*E30 -> 400000
A31: =A30+1 -> 20 | B31: Electric Kettle | C31: 40 | D31: Each | E31: 2000 | F31: =C31*E31 -> 80000
A32: =A31+1 -> 21 | B32: Linen | C32: 240 | D32: Each | E32: 1500 | F32: =C32*E32 -> 360000 | I32: =42*6 -> 252
E34: Total= | F34: =SUM(F12:F33) -> 12207000
A36: b | B36: Conference | C36: Qnty. | D36: unit | E36: Rate | F36: Amount
A37: 1 | B37: Conference Table | C37: 2 | D37: Each | E37: 100000 | F37: =C37*E37 -> 200000
A38: 2 | B38: Chairs | C38: 55 | D38: Each | E38: 6000 | F38: =C38*E38 -> 330000
E40: Total= | F40: =SUM(F37:F39) -> 530000
A42: c | B42: Banquet Hall | C42: Qnty. | D42: unit | E42: Rate | F42: Amount
A43: 1 | B43: Service Counter | C43: 1 | D43: Each | E43: 50000 | F43: =C43*E43 -> 50000
A44: 2 | B44: Banquet Chairs | C44: 175 | D44: Each | E44: 4000 | F44: =C44*E44 -> 700000
A45: 3 | B45: Banquet Tables | C45: 20 | D45: Each | E45: 5000 | F45: =C45*E45 -> 100000
E46: Total= | F46: =SUM(F43:F45) -> 850000
A48: d | B48: Grand Total= a+b+c= | F48: =F34+F40+F46 -> 13587000
A51: II | B51: Furniture/ accessories for the restaurant | C51: Qnty. | D51: Unit | E51: Rate | F51: Amount
E52: ( in Rs.) | F52: ( in Rs.)
A53: 1 | B53: Service Counter | C53: 1 | D53: Each | E53: 300000 | F53: =C53*E53 -> 300000
A54: 2 | B54: Sofa | C54: 24 | D54: Each | E54: 6000 | F54: =C54*E54 -> 144000
A55: 3 | B55: chairs | C55: 40 | D55: Each | E55: 6000 | F55: =C55*E55 -> 240000
A56: 4 | B56: Table | C56: 14 | D56: Each | E56: 8000 | F56: =C56*E56 -> 112000
E58: Total= | F58: =SUM(F53:F57) -> 796000
A60: III | B60: Furniture/ accessories for the bar | C60: Qnty. | D60: Unit | E60: Rate | F60: Amount
E61: ( in Rs.) | F61: ( in Rs.)
A62: 1 | B62: Bar Counter | C62: 1 | D62: Each | E62: 150000 | F62: =C62*E62 -> 150000
A63: 2 | B63: Bar stool | C63: 6 | D63: Each | E63: 4500 | F63: =C63*E63 -> 27000
A64: 3 | B64: Sofa | C64: 12 | D64: Each | E64: 6000 | F64: =C64*E64 -> 72000
A65: 4 | B65: Chairs | C65: 16 | D65: Each | E65: 6000 | F65: =C65*E65 -> 96000
A66: 5 | B66: Table | C66: 9 | D66: Each | E66: 7000 | F66: =C66*E66 -> 63000
E67: Total= | F67: =SUM(F62:F66) -> 408000
C69: (38)
A71: IV | B71: Furniture/ accessories for the Reception | C71: Qnty. | D71: Unit | E71: Rate | F71: Amount
E72: ( in Rs.) | F72: ( in Rs.)
A73: 1 | B73: Reception Table | C73: 1 | D73: Each | E73: 20000 | F73: 200000
A74: 2 | B74: Sofa | C74: 10 | D74: Each | E74: 8500 | F74: =C74*E74 -> 85000
A75: 3 | B75: Chairs | C75: 2 | D75: Each | E75: 6500 | F75: =C75*E75 -> 13000
A76: 4 | B76: Coffee Table | C76: 3 | D76: Each | E76: 7000 | F76: =C76*E76 -> 21000
E78: Total= | F78: =SUM(F73:F76) -> 319000
A80: IV | B80: Furniture/ accessories for the Tea Lounge | C80: Qnty. | D80: Unit | E80: Rate | F80: Amount
E81: ( in Rs.) | F81: ( in Rs.)
A82: 1 | B82: Chairs | C82: 20 | D82: Each | E82: 6000 | F82: =C82*E82 -> 120000
A83: 2 | B83: Coffee Table | C83: 4 | D83: Each | E83: 7000 | F83: =C83*E83 -> 28000
E85: Total= | F85: =SUM(F82:F83) -> 148000
A87: V | B87: Utensils | C87: Qnty. | D87: Unit | E87: Rate | F87: Amount
E88: ( in Rs.) | F88: ( in Rs.)
B89: Crockery
A90: 1 | B90: Restaurant | C90: 192 | D90: Each | E90: 1200 | F90: =C90*E90 -> 230400
A91: 2 | B91: Bar | C91: 102 | D91: Each | E91: 700 | F91: =C91*E91 -> 71400
A92: 3 | B92: Banquet | C92: 525 | D92: Each | E92: 600 | F92: =C92*E92 -> 315000
A93: 4 | B93: Conference / Party Hall | C93: 90 | D93: Each | E93: 600 | F93: =C93*E93 -> 54000
A94: 5 | B94: Rooms | C94: 126 | D94: Each | E94: 500 | F94: =C94*E94 -> 63000
B95: Glassware
A96: 1 | B96: Restaurant | C96: 192 | D96: Each | E96: 500 | F96: =C96*E96 -> 96000
A97: 2 | B97: Bar | C97: 102 | D97: Each | E97: 500 | F97: =C97*E97 -> 51000
A98: 3 | B98: Banquet | C98: 525 | D98: Each | E98: 200 | F98: =C98*E98 -> 105000
A99: 4 | B99: Conference / Party Hall | C99: 90 | D99: Each | E99: 200 | F99: =C99*E99 -> 18000
A100: 5 | B100: Rooms | C100: 126 | D100: Each | E100: 200 | F100: =C100*E100 -> 25200
B101: Cutlery
A102: 1 | B102: Restaurant | C102: 192 | D102: Each | E102: 500 | F102: =C102*E102 -> 96000
A103: 2 | B103: Bar | C103: 102 | D103: Each | E103: 200 | F103: =C103*E103 -> 20400
A104: 3 | B104: Banquet | C104: 525 | D104: Each | E104: 200 | F104: =C104*E104 -> 105000
A105: 4 | B105: Conference / Party Hall | C105: 90 | D105: Each | E105: 200 | F105: =C105*E105 -> 18000
A106: 5 | B106: Rooms | C106: 126 | D106: Each | E106: 200 | F106: =C106*E106 -> 25200
B107: Serving Dishes
A108: 1 | B108: Bowls / Dishes | C108: 100 | D108: Each | E108: 1500 | F108: =C108*E108 -> 150000
A109: 2 | B109: Serving Cutlery | C109: 100 | D109: Each | E109: 1000 | F109: =C109*E109 -> 100000
A110: 3 | B110: Trays | C110: 100 | D110: Each | E110: 800 | F110: =C110*E110 -> 80000
B111: Others
A112: 1 | B112: Kitchen Equipment | C112: 1 | D112: Each | E112: 1000000 | F112: =C112*E112 -> 1000000
A113: 2 | B113: Built-in Deep Freezer | C113: 1 | D113: Each | E113: 400000 | F113: =C113*E113 -> 400000
A114: 3 | B114: Bar Equipment | C114: 1 | D114: Each | E114: 250000 | F114: =C114*E114 -> 250000
A115: 4 | B115: Serving Equipment | C115: 9 | D115: Each | E115: 30000 | F115: =C115*E115 -> 270000
E117: Total= | F117: =SUM(F90:F116) -> 3543600
A119: VI | B119: Utilities | C119: Qnty. | D119: Unit | E119: Rate | F119: Amount
E120: ( in Rs.) | F120: ( in Rs.)
A121: 1 | B121: Laundry Equipment | C121: 4 | D121: Each | E121: 200000 | F121: =C121*E121 -> 800000
...

Sheet PREOPERATIVE EXP
C2: =Pages!D43 -> 38
C4: APPENDIX 2
C5: PRELIMINARY & PREOPERATIVE EXPENSES
D6: (Amt. in Rs.)
B7: B. | C7: PRELIMINARY & PRE-OPERATIVE EXPENSES
C9: Deposits- ASEB ,Sales Tax,Telephone,Customs,etc | D9: 1100000
C10: Establishment Expenses | D10: 500000
C11: Rent ,Rates & Taxes | D11: 150000
C12: Travelling & Conveyance Expenses | D12: 300000
C13: Interest during Construction Period | D13: =ROUND(Interest!I34*100000,-3) -> 23117000 | H13: =87.85729+0.07 -> 87.92729
C14: Initial Promotion Campaign | D14: 750000 | H14: =D20/100000 -> 285.72
C15: Consultancy & Project management fees | D15: 750000 | H15: =H14-87.75 -> 197.97 | I15: =H13-H15 -> -110.04271
C16: Sundry Expenses | D16: 555000 | F16: ='CAPITAL COST'!D28 -> 4285.8643
C17: Up-front fees | D17: =+'CAPITAL COST'!D50*100000*0.005 -> 1350000
H18: =D20-7503768 -> 21068232
F19: =D20-D13 -> 5455000
C20: TOTAL | D20: =SUM(D9:D19) -> 28572000
F21: ='CAPITAL COST'!E40*100000 -> 0

Sheet SALESPROJECTION
E2: 39
A4: APPENDIX 3
A5: PROJECTED SALES
A6: ROOM CONFIGURATION & SALES
A9: MAXIMUM POSSIBLE RECEIPT
A10: GUEST ROOM CATEGORY | D10: ROOMS FOR SALE | E10: NO.OF GUEST PER ROOM PER NIGHT | F10: TOTAL GUEST/PER NIGHT | G10: AVERAGE TARIFF (in Rs.) | H10: TOTAL GUEST PER ANNUM | I10: TOTAL ROOM SALES(Rs. In Lacs)
D12: =D14+D15+D16+D17 -> 195
A13: Double Bed Room
A15: Deluxe Rooms | D15: 190 | E15: 2 | F15: =E15*D15 -> 380 | G15: 5000 | H15: =D15*365 -> 69350 | I15: =G15*D15*365/100000 -> 3467.5
A16: Executive Suite Rooms | D16: 4 | E16: 2 | F16: =E16*D16 -> 8 | G16: 10000 | H16: =D16*365 -> 1460 | I16: =G16*D16*365/100000 -> 146
A17: Presidential Suite | D17: 1 | E17: 2 | F17: =E17*D17 -> 2 | G17: 15000 | H17: =D17*365 -> 365 | I17: =G17*D17*365/100000 -> 54.75
A25: ROOM SALES | F25: =SUM(F14:F24) -> 390 | H25: =SUM(H12:H24) -> 71175 | I25: =SUM(I12:I24) -> 3668.25
A26: N.B.: The average room rent has been considered keeping it lower than the prevailing competitive rates in surrounding areas for similar facilities
A32: CUSTOMER CONFIGURATIONS
F33: Breakfast | G33: Lunch | H33: Coffee Shop cum Bakery | I33: Dinner | J33: Bar | K33: =L45 -> Spa & Saloon
A34: Hotel guests | F34: 0.15 | G34: 0.2 | H34: 0.2 | I34: 0.4 | J34: 0.5 | K34: 0.1
A35: Number of Hotel guests/day | F35: =ROUND(F34*F25,0) -> 59 | G35: =ROUND(G34*F25,0) -> 78 | H35: =ROUND(H34*$F$25,0) -> 78 | I35: =ROUND(I34*$F$25,0) -> 156 | J35: =ROUND(J34*$F$25,0) -> 195 | K35: =ROUND(K34*$F$25,0) -> 39
A36: Outside Visiter | F36: 1.25 | G36: 1.5 | H36: 2 | I36: 1.5 | J36: 1.5 | K36: 1
A37: Number of Outside Visitor/day | F37: =F36*F35 -> 73.75 | G37: =G36*G35 -> 117 | H37: =H36*H35 -> 156 | I37: =ROUND(I36*I35,0) -> 234 | J37: =ROUND(J36*J35,0) -> 293 | K37: =K36*K35 -> 39
A38: Total No. Of Visitor/day | F38: =F35+F37 -> 132.75 | G38: =G35+G37 -> 195 | H38: =H35+H37 -> 234 | I38: =I35+I37 -> 390 | J38: =J35+J37 -> 488 | K38: =K35+K37 -> 78
A40: Average Revenue/guest | K40: in Rupees
A41: Hotel guests | F41: =200/2 -> 100 | G41: =300/2 -> 150 | H41: =150/2 -> 75 | I41: =400/2 -> 200 | J41: =300/2 -> 150 | K41: =500/4 -> 125
A42: Outside Visitors | F42: =250/2 -> 125 | G42: =350/2 -> 175 | H42: =200/2 -> 100 | I42: =450/2 -> 225 | J42: =350/2 -> 175 | K42: =550/5 -> 110
A45: Yearly Sales :Lakhs Rs. | G45: Breakfast | H45: Lunch | I45: =H33 -> Coffee Shop cum Bakery | J45: Dinner | K45: Bar | L45: Spa & Saloon | O45: Total
A46: Hotel guests | G46: =F35*F41*365/100000 -> 21.535 | H46: =G35*G41*365/100000 -> 42.705 | I46: =H35*H41*365/100000 -> 21.3525 | J46: =I35*I41*365/100000 -> 113.88 | K46: =J35*J41*365/100000 -> 106.7625 | L46: =K35*K41*365/100000 -> 17.79375 | O46: =SUM(G46:N46) -> 324.02875
A47: Outside Visitors | G47: =F37*F42*365/100000 -> 33.648438 | H47: =G37*G42*365/100000 -> 74.73375 | I47: =H37*H42*365/100000 -> 56.94 | J47: =I37*I42*365/100000 -> 192.1725 | K47: =J37*J42*365/100000 -> 187.15375 | L47: =K37*K42*365/100000 -> 15.6585 | O47: =SUM(G47:N47) -> 560.30694
A49: TOTAL F & B SALES | G49: =SUM(G46:G48) -> 55.183437 | H49: =SUM(H46:H48) -> 117.43875 | I49: =SUM(I46:I48) -> 78.2925 | J49: =SUM(J46:J48) -> 306.0525 | K49: =SUM(K46:K48) -> 293.91625 | L49: =SUM(L46:L48) -> 33.45225 | O49: =SUM(O46:O48) -> 884.33569
E52: 40
E54: APPENDIX 3 contd….
A56: OVERALL REVENUE PROJECTION
A58: Room Sales | E58: =I25 -> 3668.25
A59: F & B Sales | E59: =O49 -> 884.33569
A60: Banquet Hall Receipts | E60: =500*130*300/100000 -> 195
A61: Fitness Centre | E61: =8000*300/100000 -> 24
A62: Game Parlour | E62: =(F25*0.15*500*300)/100000 -> 87.75
A63: Conference Hall Receipts | E63: =30*500*300/100000 -> 45
A65: Sub Total | E65: =SUM(E57:E63) -> 4904.3357
A67: Other Sales 2.5% of Total (Includes Laundry, etc) | E67: =E65/97.5*2.5 -> 125.7522
A69: Total Revenue | E69: =E65+E67 -> 5030.0879
A71: Capacity Considered | E71: ='P L '!D18 -> 0.4 | F71: ='P L '!E18 -> 0.4 | G71: ='P L '!F18 -> 0.45 | H71: ='P L '!G18 -> 0.5 | I71: ='P L '!H18 -> 0.55 | J71: ='P L '!I18 -> 0.6 | K71: ='P L '!J18 -> 0.65 | L71: ='P L '!K18 -> 0.7 | ... N71: ='P L '!M18 -> 0.6
A72: Year | E72: 1 | F72: 2 | G72: 3 | H72: 4 | I72: 5 | J72: 6 | K72: 7 | L72: 8 | M72: 9 | N72: 10
A74: Room Sales | C74: =E74/$E$81 -> 0.72926161 | E74: =E58 -> 3668.25 | F74: =E74*(1+D74) -> 3668.25 | G74: =F74*(1+D74) -> 3668.25 | H74: =G74*(1+D74) -> 3668.25 | I74: =H74*(1+D74) -> 3668.25 | J74: =I74*(1+D74) -> 3668.25 | K74: =J74*(1+D74) -> 3668.25 | L74: =K74*(1+D74) -> 3668.25 | M74: =L74 -> 3668.25 | N74: =M74 -> 3668.25
A75: F & B Sales | C75: =E75/$E$81 -> 0.17580919 | E75: =E59 -> 884.33569 | F75: =E75*(1+D75) -> 884.33569 | G75: =F75*(1+D75) -> 884.33569 | H75: =G75*(1+D75) -> 884.33569 | I75: =H75*(1+D75) -> 884.33569 | J75: =I75*(1+D75) -> 884.33569 | K75: =J75*(1+D75) -> 884.33569 | L75: =K75*(1+D75) -> 884.33569 | M75: =L75 -> 884.33569 | N75: =M75 -> 884.33569
A76: Banquet Hall Receipts | C76: =E76/$E$81 -> 0.038766718 | E76: =E60 -> 195 | F76: =E76*(1+D76) -> 195 | G76: =F76*(1+D76) -> 195 | H76: =G76*(1+D76) -> 195 | I76: =H76*(1+D76) -> 195 | J76: =I76*(1+D76) -> 195 | K76: =J76*(1+D76) -> 195 | L76: =K76*(1+D76) -> 195 | M76: =L76 -> 195 | N76: =M76 -> 195
A77: =A61 -> Fitness Centre | C77: =E77/$E$81 -> 0.0047712884 | E77: =E61 -> 24 | F77: =E77*(1+D77) -> 24 | G77: =F77*(1+D77) -> 24 | H77: =G77*(1+D77) -> 24 | I77: =H77*(1+D77) -> 24 | J77: =I77*(1+D77) -> 24 | K77: =J77*(1+D77) -> 24 | L77: =K77*(1+D77) -> 24 | M77: =L77 -> 24 | N77: =M77 -> 24
A78: =A62 -> Game Parlour | C78: =E78/$E$81 -> 0.017445023 | E78: =E62 -> 87.75 | F78: =E78*(1+D78) -> 87.75 | G78: =F78*(1+D78) -> 87.75 | H78: =G78*(1+D78) -> 87.75 | I78: =H78*(1+D78) -> 87.75 | J78: =I78*(1+D78) -> 87.75 | K78: =J78*(1+D78) -> 87.75 | L78: =K78*(1+D78) -> 87.75 | M78: =L78 -> 87.75 | N78: =M78 -> 87.75
A79: Conference Hall Receipts | C79: =E79/$E$81 -> 0.0089461658 | E79: =E63 -> 45 | F79: =E79*(1+D79) -> 45 | G79: =F79*(1+D79) -> 45 | H79: =G79*(1+D79) -> 45 | I79: =H79*(1+D79) -> 45 | J79: =I79*(1+D79) -> 45 | K79: =J79*(1+D79) -> 45 | L79: =K79*(1+D79) -> 45 | M79: =L79 -> 45 | N79: =M79 -> 45
A80: Other Income | C80: =E80/$E$81 -> 0.025 | E80: =+E67 -> 125.7522 | F80: =E80*(1+D80) -> 125.7522 | G80: =F80*(1+D80) -> 125.7522 | H80: =G80*(1+D80) -> 125.7522 | I80: =H80*(1+D80) -> 125.7522 | J80: =I80*(1+D80) -> 125.7522 | K80: =J80*(1+D80) -> 125.7522 | L80: =K80*(1+D80) -> 125.7522 | M80: =L80 -> 125.7522 | N80: =M80 -> 125.7522
A81: Total | C81: =SUM(C74:C80) -> 1 | E81: =SUM(E74:E80) -> 5030.0879 | F81: =SUM(F74:F80) -> 5030.0879 | G81: =SUM(G74:G80) -> 5030.0879 | H81: =SUM(H74:H80) -> 5030.0879 | I81: =SUM(I74:I80) -> 5030.0879 | J81: =SUM(J74:J80) -> 5030.0879 | K81: =SUM(K74:K80) -> 5030.0879 | L81: =SUM(L74:L80) -> 5030.0879 | ... N81: =SUM(N74:N80) -> 5030.0879
A83: N.B.: No Increase / Growth of revenue has been considered

Sheet Interest
E4: =Pages!D45 -> 41
A6: APPENDIX 4
O7: 1 | P7: Apr
B8: Statement Showing Calculation of Interest & Repayment Schedule | O8: 2 | P8: May
O10: 3 | P10: June
B11: Months | C11: Principal | D11: Interest | E11: Principal Repayment | F11: Total Repayment | G11: Balance | L11: Moratorium | M11: Implementation | N11: Door to door | O11: 4 | P11: July
A12: Year 0 | B12: 4 | C12: 0 | D12: =C12*0.135/12 -> 0 | E12: 0 | F12: =D12+E12 -> 0 | G12: =C12-E12 -> 0 | N12: =N13+1 -> 123 | O12: 5 | P12: August
B13: =+B12+1 -> 5 | C13: 0 | D13: =C13*0.135/12 -> 0 | E13: 0 | F13: =D13+E13 -> 0 | G13: =C13-E13 -> 0 | N13: =N14+1 -> 122 | O13: 6 | P13: September
B14: =+B13+1 -> 6 | C14: =C13 -> 0 | D14: =C14*0.135/12 -> 0 | E14: 0 | F14: =D14+E14 -> 0 | G14: =C14-E14 -> 0 | N14: =N15+1 -> 121 | O14: 7 | P14: October
B15: =+B14+1 -> 7 | C15: =C14 -> 0 | D15: =C15*0.135/12 -> 0 | E15: 0 | F15: =D15+E15 -> 0 | G15: =C15-E15 -> 0 | N15: =N17+1 -> 120
M17: 0 | N17: =N31+1 -> 119
A18: 2025-26 | B18: April | C18: 0 | D18: =C18*0.095/12 -> 0 | E18: 0 | F18: =D18+E18 -> 0 | G18: =C18-E18 -> 0
B19: May | C19: =G18 -> 0 | D19: =C19*0.095/12 -> 0 | E19: 0 | F19: =D19+E19 -> 0 | G19: =C19-E19 -> 0
B20: June | C20: =G19 -> 0 | D20: =C20*0.095/12 -> 0 | E20: 0 | F20: =D20+E20 -> 0 | G20: =C20-E20 -> 0
B21: July | C21: 200 | D21: =C21*0.095/12 -> 1.5833333 | E21: 0 | F21: =D21+E21 -> 1.5833333 | G21: =C21-E21 -> 200
B22: August | C22: =G21+200 -> 400 | D22: =C22*0.095/12 -> 3.1666667 | E22: 0 | F22: =D22+E22 -> 3.1666667 | G22: =C22-E22 -> 400
B23: September | C23: =G22 -> 400 | D23: =C23*0.095/12 -> 3.1666667 | E23: 0 | F23: =D23+E23 -> 3.1666667 | G23: =C23-E23 -> 400
B24: October | C24: =G23+200 -> 600 | D24: =C24*0.095/12 -> 4.75 | E24: 0 | F24: =D24+E24 -> 4.75 | G24: =C24-E24 -> 600
B25: November | C25: =G24 -> 600 | D25: =C25*0.095/12 -> 4.75 | E25: 0 | F25: =D25+E25 -> 4.75 | G25: =C25-E25 -> 600
B26: December | C26: =G25+200 -> 800 | D26: =C26*0.095/12 -> 6.3333333 | E26: 0 | F26: =D26+E26 -> 6.3333333 | G26: =C26-E26 -> 800
B27: January | C27: =G26 -> 800 | D27: =C27*0.095/12 -> 6.3333333 | E27: 0 | F27: =D27+E27 -> 6.3333333 | G27: =C27-E27 -> 800
B28: February | C28: =G27 -> 800 | D28: =C28*0.095/12 -> 6.3333333 | E28: 0 | F28: =D28+E28 -> 6.3333333 | G28: =C28-E28 -> 800
B29: March | C29: =G28+200 -> 1000 | D29: =C29*0.095/12 -> 7.9166667 | E29: 0 | F29: =D29+E29 -> 7.9166667 | G29: =C29-E29 -> 1000
A30: 2026-27 | B30: April | C30: =G29 -> 1000 | D30: =C30*0.095/12 -> 7.9166667 | E30: 0 | F30: =D30+E30 -> 7.9166667 | G30: =C30-E30 -> 1000
B31: May | C31: =C30 -> 1000 | D31: =C31*0.095/12 -> 7.9166667 | E31: 0 | F31: =D31+E31 -> 7.9166667 | G31: =C31-E31 -> 1000 | M31: =M17+1 -> 1 | N31: =N32+1 -> 118
B32: June | C32: =C31+500 -> 1500 | D32: =C32*0.095/12 -> 11.875 | E32: 0 | F32: =D32+E32 -> 11.875 | G32: =C32-E32 -> 1500 | M32: =M31+1 -> 2 | N32: =N33+1 -> 117
B33: July | C33: =C32 -> 1500 | D33: =C33*0.095/12 -> 11.875 | E33: 0 | F33: =D33+E33 -> 11.875 | G33: =C33-E33 -> 1500 | I33: Yearly Int | J33: Yearly P rep | K33: Total Rep | M33: =M32+1 -> 3 | N33: =N34+1 -> 116
B34: August | C34: =C33 -> 1500 | D34: =C34*0.095/12 -> 11.875 | E34: 0 | F34: =D34+E34 -> 11.875 | G34: =C34-E34 -> 1500 | I34: =SUM(D12:D41) -> 231.16667 | J34: =SUM(E12:E40) -> 0 | K34: =SUM(F12:F40) -> 209.79167 | M34: =M33+1 -> 4 | N34: =N35+1 -> 115
B35: September | C35: =C34+500 -> 2000 | D35: =C35*0.095/12 -> 15.833333 | E35: 0 | F35: =D35+E35 -> 15.833333 | G35: =C35-E35 -> 2000 | I35: Construction Period | M35: =M34+1 -> 5 | N35: =N36+1 -> 114
B36: October | C36: =C35 -> 2000 | D36: =C36*0.095/12 -> 15.833333 | E36: 0 | F36: =D36+E36 -> 15.833333 | G36: =C36-E36 -> 2000 | M36: =M35+1 -> 6 | N36: =N37+1 -> 113
B37: November | C37: =C36+500 -> 2500 | D37: =C37*0.095/12 -> 19.791667 | E37: 0 | F37: =D37+E37 -> 19.791667 | G37: =C37-E37 -> 2500 | M37: =M36+1 -> 7 | N37: =N38+1 -> 112
B38: December | C38: =C37 -> 2500 | D38: =C38*0.095/12 -> 19.791667 | E38: 0 | F38: =D38+E38 -> 19.791667 | G38: =C38-E38 -> 2500 | M38: =M37+1 -> 8 | N38: =N39+1 -> 111
B39: January | C39: =C38+200 -> 2700 | D39: =C39*0.095/12 -> 21.375 | E39: 0 | F39: =D39+E39 -> 21.375 | G39: =C39-E39 -> 2700 | M39: =M38+1 -> 9 | N39: =N40+1 -> 110
B40: February | C40: =C39 -> 2700 | D40: =C40*0.095/12 -> 21.375 | E40: 0 | F40: =D40+E40 -> 21.375 | G40: =C40-E40 -> 2700 | M40: =M39+1 -> 10 | N40: =N41+1 -> 109
B41: March | C41: =C40 -> 2700 | D41: =C41*0.095/12 -> 21.375 | E41: 0 | F41: =D41+E41 -> 21.375 | G41: =C41-E41 -> 2700 | M41: =M40+1 -> 11 | N41: =N42+1 -> 108
A42: 2027-28 | B42: April | C42: =C41 -> 2700 | D42: =C42*0.095/12 -> 21.375 | E42: 0 | F42: =D42+E42 -> 21.375 | G42: =C42-E42 -> 2700 | M42: =M41+1 -> 12 | N42: =N43+1 -> 107
B43: May | C43: =C42 -> 2700 | D43: =C43*0.095/12 -> 21.375 | E43: 0 | F43: =D43+E43 -> 21.375 | G43: =C43-E43 -> 2700 | M43: =M42+1 -> 13 | N43: =N44+1 -> 106
B44: June | C44: =C43 -> 2700 | D44: =C44*0.095/12 -> 21.375 | E44: 0 | F44: =D44+E44 -> 21.375 | G44: =C44-E44 -> 2700 | M44: =M43+1 -> 14 | N44: =N45+1 -> 105
B45: July | C45: =C44 -> 2700 | D45: =C45*0.095/12 -> 21.375 | E45: 0 | F45: =D45+E45 -> 21.375 | G45: =C45-E45 -> 2700 | I45: Yearly Int | J45: Yearly P rep | K45: Total Rep | M45: =M44+1 -> 15 | N45: =N46+1 -> 104
B46: August | C46: =C45 -> 2700 | D46: =C46*0.095/12 -> 21.375 | E46: 0 | F46: =D46+E46 -> 21.375 | G46: =C46-E46 -> 2700 | I46: =SUM(D42:D53) -> 254.71875 | J46: =SUM(E42:E53) -> 90 | K46: =SUM(F42:F53) -> 344.71875 | M46: =M45+1 -> 16 | N46: =N47+1 -> 103
B47: September | C47: =C46 -> 2700 | D47: =C47*0.095/12 -> 21.375 | E47: 0 | F47: =D47+E47 -> 21.375 | G47: =C47-E47 -> 2700 | M47: =M46+1 -> 17 | N47: =N48+1 -> 102
B48: October | C48: =C47 -> 2700 | D48: =C48*0.095/12 -> 21.375 | E48: 15 | F48: =D48+E48 -> 36.375 | G48: =C48-E48 -> 2685 | M48: =M47+1 -> 18 | N48: =N49+1 -> 101
B49: November | C49: =G48 -> 2685 | D49: =C49*0.095/12 -> 21.25625 | E49: =E48 -> 15 | F49: =D49+E49 -> 36.25625 | G49: =C49-E49 -> 2670 | M49: =M48+1 -> 19 | N49: =N50+1 -> 100
B50: December | C50: =G49 -> 2670 | D50: =C50*0.095/12 -> 21.1375 | E50: =E49 -> 15 | F50: =D50+E50 -> 36.1375 | G50: =C50-E50 -> 2655 | M50: =M49+1 -> 20 | N50: =N51+1 -> 99
B51: January | C51: =G50 -> 2655 | D51: =C51*0.095/12 -> 21.01875 | E51: =E50 -> 15 | F51: =D51+E51 -> 36.01875 | G51: =C51-E51 -> 2640 | M51: =M50+1 -> 21 | N51: =N52+1 -> 98
B52: February | C52: =G51 -> 2640 | D52: =C52*0.095/12 -> 20.9 | E52: =E51 -> 15 | F52: =D52+E52 -> 35.9 | G52: =C52-E52 -> 2625 | M52: =M51+1 -> 22 | N52: =N53+1 -> 97
B53: March | C53: =G52 -> 2625 | D53: =C53*0.095/12 -> 20.78125 | E53: =E52 -> 15 | F53: =D53+E53 -> 35.78125 | G53: =C53-E53 -> 2610 | L53: =1 -> 1 | N53: =N54+1 -> 96
A54: 2028-29 | B54: April | C54: =G53 -> 2610 | D54: =C54*0.095/12 -> 20.6625 | E54: =E53 -> 15 | F54: =D54+E54 -> 35.6625 | G54: =C54-E54 -> 2595 | L54: =L53+1 -> 2 | N54: =N55+1 -> 95
B55: May | C55: =G54 -> 2595 | D55: =C55*0.095/12 -> 20.54375 | E55: =E54 -> 15 | F55: =D55+E55 -> 35.54375 | G55: =C55-E55 -> 2580 | L55: =L54+1 -> 3 | N55: =N56+1 -> 94
B56: June | C56: =G55 -> 2580 | D56: =C56*0.095/12 -> 20.425 | E56: =E55 -> 15 | F56: =D56+E56 -> 35.425 | G56: =C56-E56 -> 2565 | L56: =L55+1 -> 4 | N56: =N57+1 -> 93
B57: July | C57: =G56 -> 2565 | D57: =C57*0.095/12 -> 20.30625 | E57: =E56 -> 15 | F57: =D57+E57 -> 35.30625 | G57: =C57-E57 -> 2550 | I57: Yearly Int | J57: Yearly P rep | K57: Total Rep | L57: =L56+1 -> 5 | N57: =N58+1 -> 92
B58: August | C58: =G57 -> 2550 | D58: =C58*0.095/12 -> 20.1875 | E58: =E57 -> 15 | F58: =D58+E58 -> 35.1875 | G58: =C58-E58 -> 2535 | I58: =SUM(D54:D65) -> 240.1125 | J58: =SUM(E54:E65) -> 180 | K58: =SUM(F54:F65) -> 420.1125 | L58: =L57+1 -> 6 | N58: =N59+1 -> 91
B59: September | C59: =G58 -> 2535 | D59: =C59*0.095/12 -> 20.06875 | E59: =E58 -> 15 | F59: =D59+E59 -> 35.06875 | G59: =C59-E59 -> 2520 | L59: =L58+1 -> 7 | N59: =N60+1 -> 90
B60: October | C60: =G59 -> 2520 | D60: =C60*0.095/12 -> 19.95 | E60: =E59 -> 15 | F60: =D60+E60 -> 34.95 | G60: =C60-E60 -> 2505 | L60: =L59+1 -> 8 | N60: =N61+1 -> 89
B61: November | C61: =G60 -> 2505 | D61: =C61*0.095/12 -> 19.83125 | E61: =E60 -> 15 | F61: =D61+E61 -> 34.83125 | G61: =C61-E61 -> 2490 | L61: =L60+1 -> 9 | N61: =N62+1 -> 88
B62: December | C62: =G61 -> 2490 | D62: =C62*0.095/12 -> 19.7125 | E62: =E61 -> 15 | F62: =D62+E62 -> 34.7125 | G62: =C62-E62 -> 2475 | L62: =L61+1 -> 10 | N62: =N63+1 -> 87
B63: January | C63: =G62 -> 2475 | D63: =C63*0.095/12 -> 19.59375 | E63: =E62 -> 15 | F63: =D63+E63 -> 34.59375 | G63: =C63-E63 -> 2460 | L63: =L62+1 -> 11 | N63: =N64+1 -> 86
B64: February | C64: =G63 -> 2460 | D64: =C64*0.095/12 -> 19.475 | E64: =E63 -> 15 | F64: =D64+E64 -> 34.475 | G64: =C64-E64 -> 2445 | L64: =L63+1 -> 12 | N64: =N65+1 -> 85
B65: March | C65: =G64 -> 2445 | D65: =C65*0.095/12 -> 19.35625 | E65: =E64 -> 15 | F65: =D65+E65 -> 34.35625 | G65: =C65-E65 -> 2430 | N65: =N66+1 -> 84
A66: 2029-30 | B66: April | C66: =G65 -> 2430 | D66: =C66*0.095/12 -> 19.2375 | E66: =E65+10 -> 25 | F66: =D66+E66 -> 44.2375 | G66: =C66-E66 -> 2405 | N66: =N67+1 -> 83
B67: May | C67: =G66 -> 2405 | D67: =C67*0.095/12 -> 19.039583 | E67: =E66 -> 25 | F67: =D67+E67 -> 44.039583 | G67: =C67-E67 -> 2380 | N67: =N68+1 -> 82
B68: June | C68: =G67 -> 2380 | D68: =C68*0.095/12 -> 18.841667 | E68: =E67 -> 25 | F68: =D68+E68 -> 43.841667 | G68: =C68-E68 -> 2355 | N68: =N69+1 -> 81
B69: July | C69: =G68 -> 2355 | D69: =C69*0.095/12 -> 18.64375 | E69: =E68 -> 25 | F69: =D69+E69 -> 43.64375 | G69: =C69-E69 -> 2330 | N69: =N70+1 -> 80
B70: August | C70: =G69 -> 2330 | D70: =C70*0.095/12 -> 18.445833 | E70: =E69 -> 25 | F70: =D70+E70 -> 43.445833 | G70: =C70-E70 -> 2305 | I70: =SUM(D66:D77) -> 217.7875 | J70: =SUM(E66:E77) -> 300 | K70: =SUM(F66:F77) -> 517.7875 | N70: =N71+1 -> 79
B71: September | C71: =G70 -> 2305 | D71: =C71*0.095/12 -> 18.247917 | E71: =E70 -> 25 | F71: =D71+E71 -> 43.247917 | G71: =C71-E71 -> 2280 | N71: =N72+1 -> 78
B72: October | C72: =G71 -> 2280 | D72: =C72*0.095/12 -> 18.05 | E72: =E71 -> 25 | F72: =D72+E72 -> 43.05 | G72: =C72-E72 -> 2255 | N72: =N73+1 -> 77
B73: November | C73: =G72 -> 2255 | D73: =C73*0.095/12 -> 17.852083 | E73: =E72 -> 25 | F73: =D73+E73 -> 42.852083 | G73: =C73-E73 -> 2230 | N73: =N74+1 -> 76
B74: December | C74: =G73 -> 2230 | D74: =C74*0.095/12 -> 17.654167 | E74: =E73 -> 25 | F74: =D74+E74 -> 42.654167 | G74: =C74-E74 -> 2205 | N74: =N75+1 -> 75
B75: January | C75: =G74 -> 2205 | D75: =C75*0.095/12 -> 17.45625 | E75: =E74 -> 25 | F75: =D75+E75 -> 42.45625 | G75: =C75-E75 -> 2180 | N75: =N76+1 -> 74
B76: February | C76: =G75 -> 2180 | D76: =C76*0.095/12 -> 17.258333 | E76: =E75 -> 25 | F76: =D76+E76 -> 42.258333 | G76: =C76-E76 -> 2155 | N76: =N77+1 -> 73
B77: March | C77: =G76 -> 2155 | D77: =C77*0.095/12 -> 17.060417 | E77: =E76 -> 25 | F77: =D77+E77 -> 42.060417 | G77: =C77-E77 -> 2130 | N77: =N78+1 -> 72
A78: 2030-31 | B78: April | C78: =G77 -> 2130 | D78: =C78*0.095/12 -> 16.8625 | E78: =E77+5 -> 30 | F78: =D78+E78 -> 46.8625 | G78: =C78-E78 -> 2100 | N78: =N79+1 -> 71
B79: May | C79: =G78 -> 2100 | D79: =C79*0.095/12 -> 16.625 | E79: =E78 -> 30 | F79: =D79+E79 -> 46.625 | G79: =C79-E79 -> 2070 | N79: =N80+1 -> 70
B80: June | C80: =G79 -> 2070 | D80: =C80*0.095/12 -> 16.3875 | E80: =E79 -> 30 | F80: =D80+E80 -> 46.3875 | G80: =C80-E80 -> 2040 | N80: =N81+1 -> 69
B81: July | C81: =G80 -> 2040 | D81: =C81*0.095/12 -> 16.15 | E81: =E80 -> 30 | F81: =D81+E81 -> 46.15 | G81: =C81-E81 -> 2010 | N81: =N82+1 -> 68
B82: August | C82: =G81 -> 2010 | D82: =C82*0.095/12 -> 15.9125 | E82: =E81 -> 30 | F82: =D82+E82 -> 45.9125 | G82: =C82-E82 -> 1980 | I82: =SUM(D78:D89) -> 186.675 | J82: =SUM(E78:E89) -> 360 | K82: =SUM(F78:F89) -> 546.675 | N82: =N83+1 -> 67
B83: September | C83: =G82 -> 1980 | D83: =C83*0.095/12 -> 15.675 | E83: =E82 -> 30 | F83: =D83+E83 -> 45.675 | G83: =C83-E83 -> 1950 | N83: =N84+1 -> 66
B84: October | C84: =G83 -> 1950 | D84: =C84*0.095/12 -> 15.4375 | E84: =E83 -> 30 | F84: =D84+E84 -> 45.4375 | G84: =C84-E84 -> 1920 | N84: =N85+1 -> 65
B85: November | C85: =G84 -> 1920 | D85: =C85*0.095/12 -> 15.2 | E85: =E84 -> 30 | F85: =D85+E85 -> 45.2 | G85: =C85-E85 -> 1890 | N85: =N86+1 -> 64
B86: December | C86: =G85 -> 1890 | D86: =C86*0.095/12 -> 14.9625 | E86: =E85 -> 30 | F86: =D86+E86 -> 44.9625 | G86: =C86-E86 -> 1860 | N86: =N87+1 -> 63
B87: January | C87: =G86 -> 1860 | D87: =C87*0.095/12 -> 14.725 | E87: =E86 -> 30 | F87: =D87+E87 -> 44.725 | G87: =C87-E87 -> 1830 | N87: =N88+1 -> 62
B88: February | C88: =G87 -> 1830 | D88: =C88*0.095/12 -> 14.4875 | E88: =E87 -> 30 | F88: =D88+E88 -> 44.4875 | G88: =C88-E88 -> 1800 | N88: =N89+1 -> 61
B89: March | C89: =G88 -> 1800 | D89: =C89*0.095/12 -> 14.25 | E89: =E88 -> 30 | F89: =D89+E89 -> 44.25 | G89: =C89-E89 -> 1770 | N89: =N90+1 -> 60
A90: 2031-32 | B90: April | C90: =G89 -> 1770 | D90: =C90*0.095/12 -> 14.0125 | E90: =E89+10 -> 40 | F90: =D90+E90 -> 54.0125 | G90: =C90-E90 -> 1730 | N90: =N91+1 -> 59
B91: May | C91: =G90 -> 1730 | D91: =C91*0.095/12 -> 13.695833 | E91: =E90 -> 40 | F91: =D91+E91 -> 53.695833 | G91: =C91-E91 -> 1690 | N91: =N92+1 -> 58
B92: June | C92: =G91 -> 1690 | D92: =C92*0.095/12 -> 13.379167 | E92: =E91 -> 40 | F92: =D92+E92 -> 53.379167 | G92: =C92-E92 -> 1650 | N92: =N93+1 -> 57
B93: July | C93: =G92 -> 1650 | D93: =C93*0.095/12 -> 13.0625 | E93: =E92 -> 40 | F93: =D93+E93 -> 53.0625 | G93: =C93-E93 -> 1610 | N93: =N94+1 -> 56
B94: August | C94: =G93 -> 1610 | D94: =C94*0.095/12 -> 12.745833 | E94: =E93 -> 40 | F94: =D94+E94 -> 52.745833 | G94: =C94-E94 -> 1570 | I94: =SUM(D90:D101) -> 147.25 | J94: =SUM(E90:E101) -> 480 | K94: =SUM(F90:F101) -> 627.25 | N94: =N95+1 -> 55
B95: September | C95: =G94 -> 1570 | D95: =C95*0.095/12 -> 12.429167 | E95: =E94 -> 40 | F95: =D95+E95 -> 52.429167 | G95: =C95-E95 -> 1530 | N95: =N96+1 -> 54
B96: October | C96: =G95 -> 1530 | D96: =C96*0.095/12 -> 12.1125 | E96: =E95 -> 40 | F96: =D96+E96 -> 52.1125 | G96: =C96-E96 -> 1490 | N96: =N97+1 -> 53
B97: November | C97: =G96 -> 1490 | D97: =C97*0.095/12 -> 11.795833 | E97: =E96 -> 40 | F97: =D97+E97 -> 51.795833 | G97: =C97-E97 -> 1450 | N97: =N98+1 -> 52
B98: December | C98: =G97 -> 1450 | D98: =C98*0.095/12 -> 11.479167 | E98: =E97 -> 40 | F98: =D98+E98 -> 51.479167 | G98: =C98-E98 -> 1410 | N98: =N99+1 -> 51
B99: January | C99: =G98 -> 1410 | D99: =C99*0.095/12 -> 11.1625 | E99: =E98 -> 40 | F99: =D99+E99 -> 51.1625 | G99: =C99-E99 -> 1370 | N99: =N100+1 -> 50
B100: February | C100: =G99 -> 1370 | D100: =C100*0.095/12 -> 10.845833 | E100: =E99 -> 40 | F100: =D100+E100 -> 50.845833 | G100: =C100-E100 -> 1330 | N100: =N101+1 -> 49
B101: March | C101: =G100 -> 1330 | D101: =C101*0.095/12 -> 10.529167 | E101: =E100 -> 40 | F101: =D101+E101 -> 50.529167 | G101: =C101-E101 -> 1290 | N101: =N102+1 -> 48
A102: 2032-33 | B102: April | C102: =G101 -> 1290 | D102: =C102*0.095/12 -> 10.2125 | E102: =E101+5 -> 45 | F102: =D102+E102 -> 55.2125 | G102: =C102-E102 -> 1245 | N102: =N103+1 -> 47
B103: May | C103: =G102 -> 1245 | D103: =C103*0.095/12 -> 9.85625 | E103: =E102 -> 45 | F103: =D103+E103 -> 54.85625 | G103: =C103-E103 -> 1200 | N103: =N104+1 -> 46
B104: June | C104: =G103 -> 1200 | D104: =C104*0.095/12 -> 9.5 | E104: =E103 -> 45 | F104: =D104+E104 -> 54.5 | G104: =C104-E104 -> 1155 | N104: =N105+1 -> 45
B105: July | C105: =G104 -> 1155 | D105: =C105*0.095/12 -> 9.14375 | E105: =E104 -> 45 | F105: =D105+E105 -> 54.14375 | G105: =C105-E105 -> 1110 | N105: =N106+1 -> 44
B106: August | C106: =G105 -> 1110 | D106: =C106*0.095/12 -> 8.7875 | E106: =E105 -> 45 | F106: =D106+E106 -> 53.7875 | G106: =C106-E106 -> 1065 | I106: =SUM(D102:D113) -> 99.0375 | J106: =SUM(E102:E113) -> 540 | K106: =SUM(F102:F113) -> 639.0375 | N106: =N107+1 -> 43
...

Sheet depreciation
F2: 42
A4: APPENDIX 5
A5: Depreciation Schedule
A7: Statement showing calculation of Depreciation
J9: Rs. In Lakhs
D10: Year 1 | E10: Year 2 | F10: Year 3 | G10: Year 4 | H10: Year 5 | I10: Year 6 | J10: Year 7 | K10: Year 8 | L10: Year 9 | M10: Year 10 | O10: Preliminary & Pre-opreative Expenses
A12: LAND COST & DEVELOPMENT
A14: Opening Balance (WDV) | D14: =D129 -> 0 | E14: =+D18 -> 0 | F14: =+E18 -> 0 | G14: =+F18 -> 0 | H14: =+G18 -> 0 | I14: =+H18 -> 0 | J14: =+I18 -> 0 | K14: =+J18 -> 0 | L14: =+K18 -> 0 | M14: =+L18 -> 0
A16: Less: Depreciation @ 0 % | D16: 0 | E16: 0 | F16: 0 | G16: 0 | H16: 0 | I16: 0 | J16: 0 | K16: 0 | L16: 0 | M16: 0
A18: Written Down Value | D18: =D14-D16 -> 0 | E18: =E14-E16 -> 0 | F18: =F14-F16 -> 0 | G18: =G14-G16 -> 0 | H18: =H14-H16 -> 0 | I18: =I14-I16 -> 0 | J18: =J14-J16 -> 0 | K18: =K14-K16 -> 0 | ... M18: =M14-M16 -> 0
A20: FURNITURE & ACCESSORIES
A22: Opening Balance (WDV) | D22: =E128 -> 414.32261 | E22: =+D26+'CASH FLOW'!F26 -> 372.89035 | F22: =+E26+'CASH FLOW'!G26 -> 366.45809 | G22: =+F26+'CASH FLOW'!H26 -> 325.02583 | H22: =+G26+'CASH FLOW'!I26 -> 328.59356 | I22: =+H26+'CASH FLOW'!J26 -> 332.1613 | J22: =+I26+'CASH FLOW'!K26 -> 335.72904 | K22: =+J26+'CASH FLOW'!L26 -> 334.29678 | L22: =+K26+'CASH FLOW'!M26 -> 327.86452 | M22: =+L26+'CASH FLOW'!N26 -> 331.43226
A24: Less: Depreciation @ 10 % | D24: =0.1*D22 -> 41.432261 | E24: =0.1*D22 -> 41.432261 | F24: =0.1*D22 -> 41.432261 | G24: =0.1*D22 -> 41.432261 | H24: =0.1*D22 -> 41.432261 | I24: =0.1*D22 -> 41.432261 | J24: =0.1*D22 -> 41.432261 | K24: =0.1*D22 -> 41.432261 | L24: =0.1*D22 -> 41.432261 | M24: =0.1*D22 -> 41.432261
A26: Written Down Value | D26: =D22-D24 -> 372.89035 | E26: =E22-E24 -> 331.45809 | F26: =F22-F24 -> 325.02583 | G26: =G22-G24 -> 283.59356 | H26: =H22-H24 -> 287.1613 | I26: =I22-I24 -> 290.72904 | J26: =J22-J24 -> 294.29678 | K26: =K22-K24 -> 292.86452 | ... M26: =M22-M24 -> 290
A28: BUILDING
A30: Opening Balance (WDV) | D30: =D128 -> 3178.2803 | E30: =+D34+'CASH FLOW'!F25 -> 2860.4523 | F30: =+E34+'CASH FLOW'!G25 -> 2592.6242 | G30: =+F34+'CASH FLOW'!H25 -> 2274.7962 | H30: =+G34+'CASH FLOW'!I25 -> 2016.9682 | I30: =+H34+'CASH FLOW'!J25 -> 1749.1401 | J30: =+I34+'CASH FLOW'!K25 -> 1486.3121 | K30: =+J34+'CASH FLOW'!L25 -> 1213.4841 | L30: =+K34+'CASH FLOW'!M25 -> 935.65606 | M30: =+L34+'CASH FLOW'!N25 -> 667.82803
A32: Less: Depreciation @ 10 % | D32: =0.1*D30 -> 317.82803 | E32: =0.1*D30 -> 317.82803 | F32: =0.1*D30 -> 317.82803 | G32: =0.1*D30 -> 317.82803 | H32: =0.1*D30 -> 317.82803 | I32: =0.1*D30 -> 317.82803 | J32: =0.1*D30 -> 317.82803 | K32: =0.1*D30 -> 317.82803 | L32: =0.1*D30 -> 317.82803 | M32: =0.1*D30 -> 317.82803
A34: Written Down Value | D34: =D30-D32 -> 2860.4523 | E34: =E30-E32 -> 2542.6242 | F34: =F30-F32 -> 2274.7962 | G34: =G30-G32 -> 1956.9682 | H34: =H30-H32 -> 1699.1401 | I34: =I30-I32 -> 1431.3121 | J34: =J30-J32 -> 1168.4841 | K34: =K30-K32 -> 895.65606 | ... M34: =M30-M32 -> 350
A36: ELECTRICAL INSTALLATION
A38: Opening Balance (WDV) | D38: =G128 -> 155.10878 | E38: =+D42 -> 139.59791 | F38: =+E42 -> 124.08703 | G38: =+F42 -> 108.57615 | H38: =+G42 -> 93.06527 | I38: =+H42 -> 77.554392 | J38: =+I42 -> 62.043513 | K38: =+J42 -> 46.532635 | L38: =+K42 -> 31.021757 | M38: =+L42 -> 15.510878
A40: Less: Depreciation @ 10% | D40: =0.1*D38 -> 15.510878 | E40: =0.1*D38 -> 15.510878 | F40: =0.1*D38 -> 15.510878 | G40: =0.1*D38 -> 15.510878 | H40: =0.1*D38 -> 15.510878 | I40: =0.1*D38 -> 15.510878 | J40: =0.1*D38 -> 15.510878 | K40: =0.1*D38 -> 15.510878 | L40: =0.1*D38 -> 15.510878 | M40: =0.1*D38 -> 15.510878
A42: Written Down Value | D42: =D38-D40 -> 139.59791 | E42: =E38-E40 -> 124.08703 | F42: =F38-F40 -> 108.57615 | G42: =G38-G40 -> 93.06527 | H42: =H38-H40 -> 77.554392 | I42: =I38-I40 -> 62.043513 | J42: =J38-J40 -> 46.532635 | K42: =K38-K40 -> 31.021757 | ... M42: =M38-M40 -> -4.9737992e-14
A44: PLANT & MACHINERY
A46: Opening Balance (WDV) | D46: =F128 -> 516.15262 | E46: =+D50+'CASH FLOW'!F28 -> 438.72973 | F46: =+E50+'CASH FLOW'!G28 -> 371.30683 | G46: =+F50+'CASH FLOW'!H28 -> 303.88394 | H46: =+G50+'CASH FLOW'!I28 -> 241.46105 | I46: =+H50+'CASH FLOW'!J28 -> 179.03815 | J46: =+I50+'CASH FLOW'!K28 -> 116.61526 | K46: =+J50+'CASH FLOW'!L28 -> 54.192369 | L46: =+K50+'CASH FLOW'!M28 -> -13.230524 | M46: =+L50+'CASH FLOW'!N28 -> -70.653417 | O46: =E46-D50 -> 0 | P46: =F46-E50 -> 10 | Q46: =G46-F50 -> 10 | R46: =H46-G50 -> 15 | S46: =I46-H50 -> 15 | T46: =J46-I50 -> 15 | U46: =K46-J50 -> 15 | V46: =L46-K50 -> 10
O47: ='CASH FLOW'!F28 -> 0 | P47: ='CASH FLOW'!G28 -> 10 | Q47: ='CASH FLOW'!H28 -> 10 | R47: ='CASH FLOW'!I28 -> 15 | S47: ='CASH FLOW'!J28 -> 15 | T47: ='CASH FLOW'!K28 -> 15 | U47: ='CASH FLOW'!L28 -> 15 | V47: ='CASH FLOW'!M28 -> 10
A48: Less: Depreciation @ 15% | D48: =0.15*D46 -> 77.422893 | E48: =0.15*D46 -> 77.422893 | F48: =0.15*D46 -> 77.422893 | G48: =0.15*D46 -> 77.422893 | H48: =0.15*D46 -> 77.422893 | I48: =0.15*D46 -> 77.422893 | J48: =0.15*D46 -> 77.422893 | K48: =0.15*D46 -> 77.422893 | L48: =0.15*D46 -> 77.422893 | M48: =0.15*D46 -> 77.422893
A50: Written Down Value | D50: =D46-D48 -> 438.72973 | E50: =E46-E48 -> 361.30683 | F50: =F46-F48 -> 293.88394 | G50: =G46-G48 -> 226.46105 | H50: =H46-H48 -> 164.03815 | I50: =I46-I48 -> 101.61526 | J50: =J46-J48 -> 39.192369 | K50: =K46-K48 -> -23.230524 | ... M50: =M46-M48 -> -148.07631
A53: TOTAL DEP. OF THE YEAR | D53: =D48+D32+D24+D40 -> 452.19406 | E53: =E48+E32+E24+E40 -> 452.19406 | F53: =F48+F32+F24+F40 -> 452.19406 | G53: =G48+G32+G24+G40 -> 452.19406 | H53: =H48+H32+H24+H40 -> 452.19406 | I53: =I48+I32+I24+I40 -> 452.19406 | J53: =J48+J32+J24+J40 -> 452.19406 | K53: =K48+K32+K24+K40 -> 452.19406 | ... M53: =M48+M32+M24+M40 -> 452.19406
O54: =D14+D22+D30+D38+D46 -> 4263.8643 | P54: =O54-D137 -> 0
A55: TOTAL WDV | D55: =D18+D50+D34+D26+D42 -> 3811.6702 | E55: =E18+E50+E34+E26+E42 -> 3359.4762 | F55: =F18+F50+F34+F26+F42 -> 3002.2821 | G55: =G18+G50+G34+G26+G42 -> 2560.088 | H55: =H18+H50+H34+H26+H42 -> 2227.894 | I55: =I18+I50+I34+I26+I42 -> 1885.6999 | J55: =J18+J50+J34+J26+J42 -> 1548.5059 | K55: =K18+K50+K34+K26+K42 -> 1196.3118 | ... M55: =M18+M50+M34+M26+M42 -> 491.92369 | U55: =D55+D53 -> 4263.8643 | V55: 1836.27 | W55: =V55-U55 -> -2427.5943
F60: (44)
F62: APPENDIX 6
F63: Depreciation Schedule
F64: Rs. Lakhs
A66: Statement showing calculation of Depreciation
A67: FOR COMPANIES ACT PURPOSE WDV SINGLE SHIFT BASIS
D69: Year 1 | E69: Year 2 | F69: Year 3 | G69: Year 4 | H69: Year 5 | I69: Year 6 | J69: Year 7 | K69: Year 8 | L69: Year 9 | M69: Year 9
A71: LAND COST & DEVELOPMENT
A73: Opening Balance (WDV) | D73: =D14 -> 0 | E73: =+D77 -> 0 | F73: =+E77 -> 0 | G73: =+F77 -> 0 | H73: =+G77 -> 0 | I73: =+H77 -> 0 | J73: =+I77 -> 0 | K73: =+J77 -> 0 | L73: =+K77 -> 0 | M73: =+L77 -> 0
A75: Less: Depreciation @ 0 % | D75: 0 | E75: 0 | F75: 0 | G75: 0 | H75: 0 | I75: 0 | J75: 0 | K75: 0 | L75: 0 | M75: 0
A77: Written Down Value | D77: =D73-D75 -> 0 | E77: =E73-E75 -> 0 | F77: =F73-F75 -> 0 | G77: =G73-G75 -> 0 | H77: =H73-H75 -> 0 | I77: =I73-I75 -> 0 | J77: =J73-J75 -> 0 | K77: =K73-K75 -> 0 | ... M77: =M73-M75 -> 0
A79: FURNITURE & ACCESSORIES
A81: Opening Balance (WDV) | D81: =D22 -> 414.32261 | E81: =+D85+'CASH FLOW'!F26 -> 393.60648 | F81: =+E85+'CASH FLOW'!G26 -> 389.24583 | G81: =+F85+'CASH FLOW'!H26 -> 350.32125 | H81: =+G85+'CASH FLOW'!I26 -> 360.28912 | I81: =+H85+'CASH FLOW'!J26 -> 369.26021 | J81: =+I85+'CASH FLOW'!K26 -> 377.33419 | K81: =+J85+'CASH FLOW'!L26 -> 379.60077 | L81: =+K85+'CASH FLOW'!M26 -> 376.64069 | M81: =+L85+'CASH FLOW'!N26 -> 383.97662
A83: Less: Depreciation @ 25.88% | D83: =$E$123*D81/2 -> 20.71613 | E83: =$E$123*E81 -> 39.360648 | F83: =$E$123*F81 -> 38.924583 | G83: =$E$123*G81 -> 35.032125 | H83: =$E$123*H81 -> 36.028912 | I83: =$E$123*I81 -> 36.926021 | J83: =$E$123*J81 -> 37.733419 | K83: =$E$123*K81 -> 37.960077 | L83: =$E$123*L81 -> 37.664069 | M83: =$E$123*M81 -> 38.397662
A85: Written Down Value | D85: =D81-D83 -> 393.60648 | E85: =E81-E83 -> 354.24583 | F85: =F81-F83 -> 350.32125 | G85: =G81-G83 -> 315.28912 | H85: =H81-H83 -> 324.26021 | I85: =I81-I83 -> 332.33419 | J85: =J81-J83 -> 339.60077 | K85: =K81-K83 -> 341.64069 | ... M85: =M81-M83 -> 345.57896
A88: BUILDING
A90: Opening Balance (WDV) | D90: =D30 -> 3178.2803 | E90: =+D94+'CASH FLOW'!F25 -> 3019.3663 | F90: =+E94+'CASH FLOW'!G25 -> 2767.4296 | G90: =+F94+'CASH FLOW'!H25 -> 2490.6867 | H90: =+G94+'CASH FLOW'!I25 -> 2301.618 | I90: =+H94+'CASH FLOW'!J25 -> 2121.4562 | J90: =+I94+'CASH FLOW'!K25 -> 1964.3106 | K90: =+J94+'CASH FLOW'!L25 -> 1812.8795 | L90: =+K94+'CASH FLOW'!M25 -> 1671.5916 | M90: =+L94+'CASH FLOW'!N25 -> 1554.4324
A92: Less: Depreciation @ 5 % | D92: =$D$123*D90/2 -> 158.91401 | E92: =$D$123*E90 -> 301.93663 | F92: =$D$123*F90 -> 276.74296 | G92: =$D$123*G90 -> 249.06867 | H92: =$D$123*H90 -> 230.1618 | I92: =$D$123*I90 -> 212.14562 | J92: =$D$123*J90 -> 196.43106 | K92: =$D$123*K90 -> 181.28795 | L92: =$D$123*L90 -> 167.15916 | M92: =$D$123*M90 -> 155.44324
A94: Written Down Value | D94: =D90-D92 -> 3019.3663 | E94: =E90-E92 -> 2717.4296 | F94: =F90-F92 -> 2490.6867 | G94: =G90-G92 -> 2241.618 | H94: =H90-H92 -> 2071.4562 | I94: =I90-I92 -> 1909.3106 | J94: =J90-J92 -> 1767.8795 | K94: =K90-K92 -> 1631.5916 | ... M94: =M90-M92 -> 1398.9892
A97: ELECTRICAL INSTALLATION
A99: Opening Balance (WDV) | D99: =D38 -> 155.10878 | E99: =+D103 -> 147.35334 | F99: =+E103 -> 132.61801 | G99: =+F103 -> 119.35621 | H99: =+G103 -> 107.42059 | I99: =+H103 -> 96.678529 | J99: =+I103 -> 87.010676 | K99: =+J103 -> 78.309609 | L99: =+K103 -> 70.478648 | M99: =+L103 -> 63.430783
A101: Less: Depreciation @ 13.91% | D101: =$G$123*D99/2 -> 7.7554392 | E101: =$G$123*E99 -> 14.735334 | F101: =$G$123*F99 -> 13.261801 | G101: =$G$123*G99 -> 11.935621 | H101: =$G$123*H99 -> 10.742059 | I101: =$G$123*I99 -> 9.6678529 | J101: =$G$123*J99 -> 8.7010676 | K101: =$G$123*K99 -> 7.8309609 | L101: =$G$123*L99 -> 7.0478648 | M101: =$G$123*M99 -> 6.3430783
A103: Written Down Value | D103: =D99-D101 -> 147.35334 | E103: =E99-E101 -> 132.61801 | F103: =F99-F101 -> 119.35621 | G103: =G99-G101 -> 107.42059 | H103: =H99-H101 -> 96.678529 | I103: =I99-I101 -> 87.010676 | J103: =J99-J101 -> 78.309609 | K103: =K99-K101 -> 70.478648 | ... M103: =M99-M101 -> 57.087705
A105: PLANT & MACHINERY
A107: Opening Balance (WDV) | D107: =D46 -> 516.15262 | E107: =+D111+'CASH FLOW'!F28 -> 477.44117 | F107: =+E111+'CASH FLOW'!G28 -> 415.825 | G107: =+F111+'CASH FLOW'!H28 -> 363.45125 | H107: =+G111+'CASH FLOW'!I28 -> 323.93356 | I107: =+H111+'CASH FLOW'!J28 -> 290.34353 | J107: =+I111+'CASH FLOW'!K28 -> 261.792 | K107: =+J111+'CASH FLOW'!L28 -> 237.5232 | L107: =+K111+'CASH FLOW'!M28 -> 211.89472 | M107: =+L111+'CASH FLOW'!N28 -> 200.11051
A109: Less: Depreciation @ 13.91% | D109: =$F$123*D107/2 -> 38.711446 | E109: =$F$123*E107 -> 71.616176 | F109: =$F$123*F107 -> 62.373749 | G109: =$F$123*G107 -> 54.517687 | H109: =$F$123*H107 -> 48.590034 | I109: =$F$123*I107 -> 43.551529 | J109: =$F$123*J107 -> 39.2688 | K109: =$F$123*K107 -> 35.62848 | L109: =$F$123*L107 -> 31.784208 | M109: =$F$123*M107 -> 30.016577
A111: Written Down Value | D111: =D107-D109 -> 477.44117 | E111: =E107-E109 -> 405.825 | F111: =F107-F109 -> 353.45125 | G111: =G107-G109 -> 308.93356 | H111: =H107-H109 -> 275.34353 | I111: =I107-I109 -> 246.792 | J111: =J107-J109 -> 222.5232 | K111: =K107-K109 -> 201.89472 | ... M111: =M107-M109 -> 170.09393
A114: TOTAL DEP. OF THE YEAR | D114: =D109+D92+D83+D101 -> 226.09703 | E114: =E109+E92+E83+E101 -> 427.64878 | F114: =F109+F92+F83+F101 -> 391.3031 | G114: =G109+G92+G83+G101 -> 350.5541 | H114: =H109+H92+H83+H101 -> 325.52281 | I114: =I109+I92+I83+I101 -> 302.29102 | J114: =J109+J92+J83+J101 -> 282.13434 | K114: =K109+K92+K83+K101 -> 262.70747 | ... M114: =M109+M92+M83+M101 -> 230.20056
A116: TOTAL WDV | D116: =D77+D111+D94+D85+D103 -> 4037.7673 | E116: =E77+E111+E94+E85+E103 -> 3610.1185 | F116: =F77+F111+F94+F85+F103 -> 3313.8154 | G116: =G77+G111+G94+G85+G103 -> 2973.2613 | H116: =H77+H111+H94+H85+H103 -> 2767.7385 | I116: =I77+I111+I94+I85+I103 -> 2575.4474 | J116: =J77+J111+J94+J85+J103 -> 2408.3131 | K116: =K77+K111+K94+K85+K103 -> 2245.6056 | ... M116: =M77+M111+M94+M85+M103 -> 1971.7498
U119: =U55+'CAPITAL COST'!D22 -> 4549.5843 | V119: =H128 -> 4263.8643 | W119: =V119-U119 -> -285.72
F120: 43
D122: Buildings | E122: Furniture & Fixtures | F122: Plant & Machinery | G122: MISC FIXED ASSETS
A123: Rate of dep. | D123: 0.1 | E123: 0.1 | F123: 0.15 | G123: 0.1 | H123: TOTAL
A124: Cost | D124: ='CAPITAL COST'!C14 -> 2878.9368 | E124: ='CAPITAL COST'!C16 -> 375.3 | F124: ='CAPITAL COST'!C20 -> 467.53924 | G124: ='CAPITAL COST'!C18 -> 140.5 | H124: =SUM(D124:G124) -> 3862.276
A125: Contingency | C125: ='CAPITAL COST'!C26 -> 115.86828 | D125: =$C$125/$H$124*D124 -> 86.368103 | E125: =$C$125/$H$124*E124 -> 11.259 | F125: =$C$125/$H$124*F124 -> 14.026177 | G125: =$C$125/$H$124*G124 -> 4.215 | H125: =SUM(D125:G125) -> 115.86828
A126: Preoperative expenses | C126: ='CAPITAL COST'!D22 -> 285.72 | D126: =$C$126/$H$124*D124 -> 212.97541 | E126: =$C$126/$H$124*E124 -> 27.763608 | F126: =$C$126/$H$124*F124 -> 34.5872 | G126: =$C$126/$H$124*G124 -> 10.393783 | H126: =SUM(D126:G126) -> 285.72
A128: Total | D128: =SUM(D124:D126) -> 3178.2803 | E128: =SUM(E124:E126) -> 414.32261 | F128: =SUM(F124:F126) -> 516.15262 | G128: =SUM(G124:G126) -> 155.10878 | H128: =SUM(D128:G128) -> 4263.8643 | N128: ='CAPITAL COST'!C28+'CAPITAL COST'!#REF!-'CAPITAL COST'!C24 -> #REF!
A129: Land & Land development | D129: ='CAPITAL COST'!D12 -> 0
A131: Depreciation | D131: =D128*D123 -> 317.82803 | E131: =E128*E123 -> 41.432261 | F131: =F128*F123 -> 77.422893 | G131: =G128*G123 -> 15.510878 | H131: =SUM(D131:G131) -> 452.19406
D135: Year 1 | E135: Year 2 | F135: Year 3 | G135: Year 4 | H135: Year 5 | I135: Year 6 | J135: Year 7 | K135: Year 8 | L135: Year 9 | M135: Year 10
